Workbook
Name Smic: 'Barèmes'!$D$6
Name MG: 'Barèmes'!$D$7
Name MinLegal: 'Barèmes'!$D$8
Name MinConv: 'Barèmes'!$D$9
Name MinConvTitre: 'Barèmes'!$D$10
Name Ent9Min: 'Barèmes'!$D$11
Name PlancherEnt: 'Barèmes'!$D$12
Name SeuilMaj: 'Barèmes'!$D$13
Name MajSupMin: 'Barèmes'!$D$14
Name MajFerie: 'Barèmes'!$D$15
Name TxCotis: 'Barèmes'!$D$16
Name TxCotisAM: 'Barèmes'!$D$17
Name CoefNet: 'Barèmes'!$D$18
Name JoursCPMois: 'Barèmes'!$D$19
Name PlafondCP: 'Barèmes'!$D$20
Name FeriesEff: 'Barèmes'!$F$23:$F$35
Name ParentNom: 'Contrat'!$C$6
Name AssmatNom: 'Contrat'!$C$7
Name EnfantNom: 'Contrat'!$C$8
Name DateDebut: 'Contrat'!$C$11
Name TypeAccueil: 'Contrat'!$C$12
Name TypeCode: 'Contrat'!$G$12
Name Semaines: 'Contrat'!$C$13
Name AlsaceMoselle: 'Contrat'!$C$14
Name PlanH: 'Contrat'!$E$19:$E$25
Name HSem: 'Contrat'!$E$26
Name JSem: 'Contrat'!$E$27
Name TauxBrut: 'Contrat'!$C$31
Name TauxNet: 'Contrat'!$C$32
Name MajCompl: 'Contrat'!$C$33
Name MajSup: 'Contrat'!$C$34
Name Entretien9h: 'Contrat'!$C$37
Name FournitRepas: 'Contrat'!$C$38
Name PrixRepas: 'Contrat'!$C$39
Name RepasParJour: 'Contrat'!$C$40
Name TarifKm: 'Contrat'!$C$41
Name ModeCP: 'Contrat'!$C$44
Name ModeCode: 'Contrat'!$G$44
Name MoisCPDate: 'Contrat'!$G$45
Name PerDu: 'Contrat'!$C$49:$C$60
Name PerAu: 'Contrat'!$D$49:$D$60
Name PerCode: 'Contrat'!$G$49:$G$60
Name SemRet: 'Contrat'!$L$6
Name HeuresMens: 'Contrat'!$L$8
Name JoursMens: 'Contrat'!$L$9
Name SalMensBrut: 'Contrat'!$L$10
Name SalMensNet: 'Contrat'!$L$11
Name RecapStart: 'Récap annuel'!$R$11:$R$22
Name RecapEff: 'Récap annuel'!$S$11:$S$22
Name RecapPaid: 'Récap annuel'!$T$11:$T$22
Name RecapBrutHF: 'Récap annuel'!$U$11:$U$22
Name RecapActive: 'Récap annuel'!$V$11:$V$22
Name CPA_J: 'Congés payés'!$C$8
Name CPA_Sal: 'Congés payés'!$D$9
Name CPA_Maint: 'Congés payés'!$C$12
Name CPA_Dix: 'Congés payés'!$C$13
Name CPA_Due: 'Congés payés'!$C$14
Name CPB_J: 'Congés payés'!$C$22
Name CPB_Brut: 'Congés payés'!$C$23
Name CPTaken: 'Congés payés'!$C$46

Sheet Bienvenue
B2: NID SEREIN · OUTILS POUR PARENTS EMPLOYEURS
B3: Kit Parent Employeur — Assistante maternelle
B4: Édition 2026-2027 · du 1er juin 2026 au 31 mai 2027 · barèmes au 1er juin 2026
B6: EN 4 ÉTAPES
B7: 1 | C7: Votre contrat | D7: 2 | E7: Chaque mois | F7: 3 | G7: Pajemploi | H7: 4 | I7: Congés et fin
C8: Une seule fois : planning, taux horaire, indemnités, vacances prévues. | E8: Notez seulement les exceptions : absence, heures en plus, jour férié… Le reste est prérempli. | G8: Recopiez le cadre vert « À déclarer sur Pajemploi ». Les chiffres sont prêts. | I8: Congés payés, régularisation, préavis, indemnité de rupture : tout est calculé.
B11: SOMMAIRE | G11: LÉGENDE
C12: → Contrat | E12: À remplir en premier | H12: Cellule à remplir
C13: → Récap annuel | E13: L'année en un coup d'œil | H13: Résultat calculé
C14: → Juin 2026 | E14: Présence + déclaration du mois | H14: Congé payé
C15: → Juillet 2026 | E15: Présence + déclaration du mois | H15: Absence de l'enfant payée
C16: → Août 2026 | E16: Présence + déclaration du mois | H16: Absence retenue sur le salaire
C17: → Septembre 2026 | E17: Présence + déclaration du mois | H17: Jour férié
C18: → Octobre 2026 | E18: Présence + déclaration du mois | H18: Semaine non programmée / hors contrat
C19: → Novembre 2026 | E19: Présence + déclaration du mois
C20: → Décembre 2026 | E20: Présence + déclaration du mois | G20: BON À SAVOIR
C21: → Janvier 2027 | E21: Présence + déclaration du mois | G21: • Un fichier par enfant : depuis janvier 2026, Pajemploi demande une déclaration par enfant.
C22: → Février 2027 | E22: Présence + déclaration du mois
C23: → Mars 2027 | E23: Présence + déclaration du mois | G23: • Déclaration entre le 25 du mois et le 5 du mois suivant.
C24: → Avril 2027 | E24: Présence + déclaration du mois
C25: → Mai 2027 | E25: Présence + déclaration du mois | G25: • Le net affiché est une estimation : Pajemploi calcule le net exact à partir du brut.
C26: → Congés payés | E26: Droits et paiements
C27: → Fin de contrat | E27: Préavis, régularisation, solde | G27: • Les cellules calculées sont protégées contre les fausses manipulations (sans mot de passe).
C28: → Barèmes | E28: Taux légaux et sources
G29: • Fonctionne avec Excel, Google Sheets (Fichier › Importer) et LibreOffice.
B33: Outil d'aide au calcul fondé sur la convention collective des particuliers employeurs et de l'emploi à domicile (IDCC 3239) et sur les fiches officielles DREETS et Pajemploi en vigueur au 1er juin 2026. Il ne remplace pas un conseil juridique. En cas de doute : votre relais petite enfance (RPE), la DREETS de votre région ou Pajemploi.

Sheet Contrat
B2: Votre contrat | L2: Nid Serein · Édition 2026-2027
B3: À remplir une seule fois. Les cellules jaunes sont à compléter, tout le reste se calcule.
B5: 1 · LES PERSONNES | I5: VOTRE MENSUALISATION
B6: Parent employeur | C6: Camille et Thomas Martin | I6: Semaines d'accueil retenues | L6: =IF(TypeCode=1,52,N(Semaines))
B7: Assistante maternelle | C7: Sophie Bernard | I7: Heures par semaine | L7: =HSem
B8: Enfant accueilli (1 fichier par enfant) | C8: Léo | I8: Heures mensualisées | L8: =ROUND(HSem*SemRet/12,2)
I9: Jours d'activité mensualisés | L9: =ROUND(JSem*SemRet/12,2)
B10: 2 · LE CONTRAT | I10: Salaire mensualisé brut | L10: =ROUND(TauxBrut*(MIN(HSem,SeuilMaj)+MAX(0,HSem-SeuilMaj)*(1+MajSup))*SemRet/12,2)
B11: Date de début du contrat (embauche) | C11: 45901 | I11: Salaire mensualisé net (estimé) | L11: =ROUND(SalMensBrut*CoefNet,2)
B12: Type d'accueil | C12: 46 semaines ou moins (année incomplète) | G12: =IF(LEFT(C12,2)="52",1,2)
B13: Semaines d'accueil programmées sur 12 mois | C13: 42 | D13: année incomplète uniquement (46 max.) | I13: SUR PAJEMPLOI, CHAQUE MOIS
B14: Domicile de l'assmat en Alsace-Moselle ? | C14: Non | I14: Nombre d'heures normales | L14: =ROUND(HeuresMens,0)
B15: Date de fin du contrat | C15: =IF(DateFin="","",DateFin) | D15: se renseigne dans l'onglet « Fin de contrat » | I15: Nombre de jours d'activité | L15: =ROUNDUP(JoursMens,0)
I16: Valeurs prévues par la mensualisation (hors absences retenues, qui sont déduites automatiquement chaque mois).
B17: 3 · LA SEMAINE TYPE
B18: Jour | C18: Arrivée | D18: Départ | E18: Heures | F18: ou heures/jour
B19: Lundi | C19: 0.33333333 | D19: 0.72916667 | E19: =IF(F19<>"",F19,IF(AND(C19<>"",D19<>""),ROUND(MOD(D19-C19,1)*24,2),0)) | I19: CONTRÔLES DE CONFORMITÉ
B20: Mardi | C20: 0.33333333 | D20: 0.72916667 | E20: =IF(F20<>"",F20,IF(AND(C20<>"",D20<>""),ROUND(MOD(D20-C20,1)*24,2),0)) | I20: =IF(DateDebut="","• Saisissez la date de début du contrat.","✓ Date de début renseignée")
B21: Mercredi | E21: =IF(F21<>"",F21,IF(AND(C21<>"",D21<>""),ROUND(MOD(D21-C21,1)*24,2),0)) | I21: =IF(HSem=0,"• Complétez la semaine type.",IF(HSem>48,"⚠ Plus de 48 h par semaine : vérifiez la durée maximale autorisée.","✓ "&FIXED(HSem,2)&" h par semaine sur "&JSem&" jour(s)"))
B22: Jeudi | C22: 0.33333333 | D22: 0.72916667 | E22: =IF(F22<>"",F22,IF(AND(C22<>"",D22<>""),ROUND(MOD(D22-C22,1)*24,2),0)) | I22: =IF(TauxBrut=0,"• Saisissez le taux horaire.",IF(TauxBrut<MinConv,"⚠ Taux brut inférieur au minimum conventionnel ("&FIXED(MinConv,2)&" € brut)","✓ Taux conforme au minimum conventionnel"))
B23: Vendredi | C23: 0.33333333 | D23: 0.72916667 | E23: =IF(F23<>"",F23,IF(AND(C23<>"",D23<>""),ROUND(MOD(D23-C23,1)*24,2),0)) | I23: =IF(TypeCode=1,"✓ Accueil 52 semaines : congés payés inclus dans le salaire",IF(OR(N(Semaines)=0,Semaines>46),"⚠ Année incomplète : indiquez 46 semaines d'accueil ou moins","✓ Année incomplète sur "&Semaines&" semaines"))
B24: Samedi | E24: =IF(F24<>"",F24,IF(AND(C24<>"",D24<>""),ROUND(MOD(D24-C24,1)*24,2),0)) | I24: =IF(Entretien9h<Ent9Min,"⚠ Entretien inférieur au minimum ("&FIXED(Ent9Min,2)&" € pour 9 h)","✓ Indemnité d'entretien conforme")
B25: Dimanche | E25: =IF(F25<>"",F25,IF(AND(C25<>"",D25<>""),ROUND(MOD(D25-C25,1)*24,2),0)) | I25: =IF(MajSup<MajSupMin,"⚠ Majoration au-delà de 45 h : 10 % minimum","✓ Majoration au-delà de 45 h conforme")
B26: Total par semaine | E26: =SUM(E19:E25) | I26: =IF(AND(FournitRepas="L'assistante maternelle",PrixRepas=0),"• Indiquez le prix d'un repas.","✓ Repas : "&LOWER(FournitRepas))
B27: Jours d'accueil par semaine | E27: =COUNTIF(E19:E25,">0")
B29: 4 · LA RÉMUNÉRATION
B30: Taux horaire convenu au contrat | C30: 4.8 | D30: brut | E30: ← brut ou net
B31: → taux horaire brut | C31: =IF(C30="",0,IF(D30="net",C30/CoefNet,C30))
B32: → taux horaire net (estimé) | C32: =IF(D30="net",C30,C31*CoefNet)
B33: Majoration des heures complémentaires (facultative) | C33: 0
B34: Majoration des heures au-delà de 45 h (10 % min.) | C34: 0.1
B36: 5 · LES INDEMNITÉS
B37: Indemnité d'entretien pour une journée de 9 h | C37: 4 | D37: proratisée selon la durée, 2,65 € min./jour
B38: Les repas sont fournis par | C38: L'assistante maternelle
B39: Prix d'un repas fourni par l'assmat | C39: 3.5
B40: Repas par jour d'accueil (par défaut) | C40: 1
B41: Indemnité kilométrique (€ par km) | C41: 0
B43: 6 · CONGÉS PAYÉS (ANNÉE INCOMPLÈTE)
B44: Mode de paiement prévu au contrat | C44: Au fur et à mesure de la prise des congés | G44: =IFERROR(MATCH(C44,'Barèmes'!$J$41:$J$43,0),3)
B45: Mois de la prise principale (si ce mode est choisi) | C45: Août 2026 | G45: =IFERROR(EDATE(DATE(2026,6,1),MATCH(C45,'Barèmes'!$K$41:$K$52,0)-1),"")
B47: 7 · PÉRIODES SANS ACCUEIL PRÉVUES (VACANCES, CONGÉS)
B48: Type de période | C48: Du | D48: Au | E48: Commentaire
B49: Semaine(s) non programmée(s) | C49: 46230 | D49: 46236 | E49: Vacances des parents | G49: =IFERROR(MATCH(B49,'Barèmes'!$I$41:$I$44,0),0)
B50: Congés payés de l'assmat | C50: 46237 | D50: 46256 | E50: Congés d'été de Sophie | G50: =IFERROR(MATCH(B50,'Barèmes'!$I$41:$I$44,0),0)
B51: Semaine(s) non programmée(s) | C51: 46258 | D51: 46263 | G51: =IFERROR(MATCH(B51,'Barèmes'!$I$41:$I$44,0),0)
B52: Semaine(s) non programmée(s) | C52: 46314 | D52: 46326 | E52: Toussaint | G52: =IFERROR(MATCH(B52,'Barèmes'!$I$41:$I$44,0),0)
B53: Congés payés de l'assmat | C53: 46377 | D53: 46382 | E53: Congés de Noël de Sophie | G53: =IFERROR(MATCH(B53,'Barèmes'!$I$41:$I$44,0),0)
B54: Semaine(s) non programmée(s) | C54: 46384 | D54: 46389 | G54: =IFERROR(MATCH(B54,'Barèmes'!$I$41:$I$44,0),0)
B55: Semaine(s) non programmée(s) | C55: 46433 | D55: 46438 | E55: Vacances d'hiver | G55: =IFERROR(MATCH(B55,'Barèmes'!$I$41:$I$44,0),0)
G56: =IFERROR(MATCH(B56,'Barèmes'!$I$41:$I$44,0),0)
G57: =IFERROR(MATCH(B57,'Barèmes'!$I$41:$I$44,0),0)
G58: =IFERROR(MATCH(B58,'Barèmes'!$I$41:$I$44,0),0)
G59: =IFERROR(MATCH(B59,'Barèmes'!$I$41:$I$44,0),0)
G60: =IFERROR(MATCH(B60,'Barèmes'!$I$41:$I$44,0),0)
B61: Les dates « Du » et « Au » sont incluses. Les périodes ne doivent pas se chevaucher. Les jours de ces périodes sont préremplis dans les feuilles mensuelles.

Sheet Récap annuel
B2: Récapitulatif annuel | Q2: Nid Serein · Édition 2026-2027
B3: Toute l'année d'un coup d'œil — utile pour la déclaration d'impôts et les congés payés.
B5: TOTAL VERSÉ À L'ASSMAT | F5: SALAIRES NETS DÉCLARÉS | J5: INDEMNITÉS VERSÉES | N5: HEURES D'ACCUEIL RÉALISÉES
B6: =L23 | F6: =H23 | J6: =I23+J23+K23+IndemRupture | N6: =P23
B10: Mois | C10: Salaire brut | D10: dont retenues | E10: H. compl. | F10: H. major. | G10: CP versés | H10: Net déclaré | I10: Entretien | J10: Repas | K10: Km | L10: Total versé | M10: Heures norm. (Paj.) | N10: Jours activité | O10: Jours CP (Paj.) | P10: Heures réalisées | Q10: Maladie enfant (j)
B11: Juin 2026 | C11: ='Juin 2026'!F15 | D11: ='Juin 2026'!F7 | E11: ='Juin 2026'!E8 | F11: ='Juin 2026'!E9 | G11: ='Juin 2026'!F11 | H11: ='Juin 2026'!K11 | I11: ='Juin 2026'!K12 | J11: ='Juin 2026'!K13 | K11: ='Juin 2026'!K14 | L11: ='Juin 2026'!M11 | M11: ='Juin 2026'!K6 | N11: ='Juin 2026'!K7 | O11: ='Juin 2026'!K8 | P11: ='Juin 2026'!AB16 | Q11: ='Juin 2026'!AB11 | R11: ='Juin 2026'!AB2 | S11: ='Juin 2026'!AB12 | T11: ='Juin 2026'!AB13 | U11: ='Juin 2026'!AB15 | V11: ='Juin 2026'!AB19
B12: Juillet 2026 | C12: ='Juillet 2026'!F15 | D12: ='Juillet 2026'!F7 | E12: ='Juillet 2026'!E8 | F12: ='Juillet 2026'!E9 | G12: ='Juillet 2026'!F11 | H12: ='Juillet 2026'!K11 | I12: ='Juillet 2026'!K12 | J12: ='Juillet 2026'!K13 | K12: ='Juillet 2026'!K14 | L12: ='Juillet 2026'!M11 | M12: ='Juillet 2026'!K6 | N12: ='Juillet 2026'!K7 | O12: ='Juillet 2026'!K8 | P12: ='Juillet 2026'!AB16 | Q12: ='Juillet 2026'!AB11 | R12: ='Juillet 2026'!AB2 | S12: ='Juillet 2026'!AB12 | T12: ='Juillet 2026'!AB13 | U12: ='Juillet 2026'!AB15 | V12: ='Juillet 2026'!AB19
B13: Août 2026 | C13: ='Août 2026'!F15 | D13: ='Août 2026'!F7 | E13: ='Août 2026'!E8 | F13: ='Août 2026'!E9 | G13: ='Août 2026'!F11 | H13: ='Août 2026'!K11 | I13: ='Août 2026'!K12 | J13: ='Août 2026'!K13 | K13: ='Août 2026'!K14 | L13: ='Août 2026'!M11 | M13: ='Août 2026'!K6 | N13: ='Août 2026'!K7 | O13: ='Août 2026'!K8 | P13: ='Août 2026'!AB16 | Q13: ='Août 2026'!AB11 | R13: ='Août 2026'!AB2 | S13: ='Août 2026'!AB12 | T13: ='Août 2026'!AB13 | U13: ='Août 2026'!AB15 | V13: ='Août 2026'!AB19
B14: Septembre 2026 | C14: ='Septembre 2026'!F15 | D14: ='Septembre 2026'!F7 | E14: ='Septembre 2026'!E8 | F14: ='Septembre 2026'!E9 | G14: ='Septembre 2026'!F11 | H14: ='Septembre 2026'!K11 | I14: ='Septembre 2026'!K12 | J14: ='Septembre 2026'!K13 | K14: ='Septembre 2026'!K14 | L14: ='Septembre 2026'!M11 | M14: ='Septembre 2026'!K6 | N14: ='Septembre 2026'!K7 | O14: ='Septembre 2026'!K8 | P14: ='Septembre 2026'!AB16 | Q14: ='Septembre 2026'!AB11 | R14: ='Septembre 2026'!AB2 | S14: ='Septembre 2026'!AB12 | T14: ='Septembre 2026'!AB13 | U14: ='Septembre 2026'!AB15 | V14: ='Septembre 2026'!AB19
B15: Octobre 2026 | C15: ='Octobre 2026'!F15 | D15: ='Octobre 2026'!F7 | E15: ='Octobre 2026'!E8 | F15: ='Octobre 2026'!E9 | G15: ='Octobre 2026'!F11 | H15: ='Octobre 2026'!K11 | I15: ='Octobre 2026'!K12 | J15: ='Octobre 2026'!K13 | K15: ='Octobre 2026'!K14 | L15: ='Octobre 2026'!M11 | M15: ='Octobre 2026'!K6 | N15: ='Octobre 2026'!K7 | O15: ='Octobre 2026'!K8 | P15: ='Octobre 2026'!AB16 | Q15: ='Octobre 2026'!AB11 | R15: ='Octobre 2026'!AB2 | S15: ='Octobre 2026'!AB12 | T15: ='Octobre 2026'!AB13 | U15: ='Octobre 2026'!AB15 | V15: ='Octobre 2026'!AB19
B16: Novembre 2026 | C16: ='Novembre 2026'!F15 | D16: ='Novembre 2026'!F7 | E16: ='Novembre 2026'!E8 | F16: ='Novembre 2026'!E9 | G16: ='Novembre 2026'!F11 | H16: ='Novembre 2026'!K11 | I16: ='Novembre 2026'!K12 | J16: ='Novembre 2026'!K13 | K16: ='Novembre 2026'!K14 | L16: ='Novembre 2026'!M11 | M16: ='Novembre 2026'!K6 | N16: ='Novembre 2026'!K7 | O16: ='Novembre 2026'!K8 | P16: ='Novembre 2026'!AB16 | Q16: ='Novembre 2026'!AB11 | R16: ='Novembre 2026'!AB2 | S16: ='Novembre 2026'!AB12 | T16: ='Novembre 2026'!AB13 | U16: ='Novembre 2026'!AB15 | V16: ='Novembre 2026'!AB19
B17: Décembre 2026 | C17: ='Décembre 2026'!F15 | D17: ='Décembre 2026'!F7 | E17: ='Décembre 2026'!E8 | F17: ='Décembre 2026'!E9 | G17: ='Décembre 2026'!F11 | H17: ='Décembre 2026'!K11 | I17: ='Décembre 2026'!K12 | J17: ='Décembre 2026'!K13 | K17: ='Décembre 2026'!K14 | L17: ='Décembre 2026'!M11 | M17: ='Décembre 2026'!K6 | N17: ='Décembre 2026'!K7 | O17: ='Décembre 2026'!K8 | P17: ='Décembre 2026'!AB16 | Q17: ='Décembre 2026'!AB11 | R17: ='Décembre 2026'!AB2 | S17: ='Décembre 2026'!AB12 | T17: ='Décembre 2026'!AB13 | U17: ='Décembre 2026'!AB15 | V17: ='Décembre 2026'!AB19
B18: Janvier 2027 | C18: ='Janvier 2027'!F15 | D18: ='Janvier 2027'!F7 | E18: ='Janvier 2027'!E8 | F18: ='Janvier 2027'!E9 | G18: ='Janvier 2027'!F11 | H18: ='Janvier 2027'!K11 | I18: ='Janvier 2027'!K12 | J18: ='Janvier 2027'!K13 | K18: ='Janvier 2027'!K14 | L18: ='Janvier 2027'!M11 | M18: ='Janvier 2027'!K6 | N18: ='Janvier 2027'!K7 | O18: ='Janvier 2027'!K8 | P18: ='Janvier 2027'!AB16 | Q18: ='Janvier 2027'!AB11 | R18: ='Janvier 2027'!AB2 | S18: ='Janvier 2027'!AB12 | T18: ='Janvier 2027'!AB13 | U18: ='Janvier 2027'!AB15 | V18: ='Janvier 2027'!AB19
B19: Février 2027 | C19: ='Février 2027'!F15 | D19: ='Février 2027'!F7 | E19: ='Février 2027'!E8 | F19: ='Février 2027'!E9 | G19: ='Février 2027'!F11 | H19: ='Février 2027'!K11 | I19: ='Février 2027'!K12 | J19: ='Février 2027'!K13 | K19: ='Février 2027'!K14 | L19: ='Février 2027'!M11 | M19: ='Février 2027'!K6 | N19: ='Février 2027'!K7 | O19: ='Février 2027'!K8 | P19: ='Février 2027'!AB16 | Q19: ='Février 2027'!AB11 | R19: ='Février 2027'!AB2 | S19: ='Février 2027'!AB12 | T19: ='Février 2027'!AB13 | U19: ='Février 2027'!AB15 | V19: ='Février 2027'!AB19
B20: Mars 2027 | C20: ='Mars 2027'!F15 | D20: ='Mars 2027'!F7 | E20: ='Mars 2027'!E8 | F20: ='Mars 2027'!E9 | G20: ='Mars 2027'!F11 | H20: ='Mars 2027'!K11 | I20: ='Mars 2027'!K12 | J20: ='Mars 2027'!K13 | K20: ='Mars 2027'!K14 | L20: ='Mars 2027'!M11 | M20: ='Mars 2027'!K6 | N20: ='Mars 2027'!K7 | O20: ='Mars 2027'!K8 | P20: ='Mars 2027'!AB16 | Q20: ='Mars 2027'!AB11 | R20: ='Mars 2027'!AB2 | S20: ='Mars 2027'!AB12 | T20: ='Mars 2027'!AB13 | U20: ='Mars 2027'!AB15 | V20: ='Mars 2027'!AB19
B21: Avril 2027 | C21: ='Avril 2027'!F15 | D21: ='Avril 2027'!F7 | E21: ='Avril 2027'!E8 | F21: ='Avril 2027'!E9 | G21: ='Avril 2027'!F11 | H21: ='Avril 2027'!K11 | I21: ='Avril 2027'!K12 | J21: ='Avril 2027'!K13 | K21: ='Avril 2027'!K14 | L21: ='Avril 2027'!M11 | M21: ='Avril 2027'!K6 | N21: ='Avril 2027'!K7 | O21: ='Avril 2027'!K8 | P21: ='Avril 2027'!AB16 | Q21: ='Avril 2027'!AB11 | R21: ='Avril 2027'!AB2 | S21: ='Avril 2027'!AB12 | T21: ='Avril 2027'!AB13 | U21: ='Avril 2027'!AB15 | V21: ='Avril 2027'!AB19
B22: Mai 2027 | C22: ='Mai 2027'!F15 | D22: ='Mai 2027'!F7 | E22: ='Mai 2027'!E8 | F22: ='Mai 2027'!E9 | G22: ='Mai 2027'!F11 | H22: ='Mai 2027'!K11 | I22: ='Mai 2027'!K12 | J22: ='Mai 2027'!K13 | K22: ='Mai 2027'!K14 | L22: ='Mai 2027'!M11 | M22: ='Mai 2027'!K6 | N22: ='Mai 2027'!K7 | O22: ='Mai 2027'!K8 | P22: ='Mai 2027'!AB16 | Q22: ='Mai 2027'!AB11 | R22: ='Mai 2027'!AB2 | S22: ='Mai 2027'!AB12 | T22: ='Mai 2027'!AB13 | U22: ='Mai 2027'!AB15 | V22: ='Mai 2027'!AB19
B23: Total | C23: =SUM(C11:C22) | D23: =SUM(D11:D22) | E23: =SUM(E11:E22) | F23: =SUM(F11:F22) | G23: =SUM(G11:G22) | H23: =SUM(H11:H22) | I23: =SUM(I11:I22) | J23: =SUM(J11:J22) | ... Q23: =SUM(Q11:Q22)
B25: =IF(Q23>5,"⚠ "&Q23&" jours de maladie de l'enfant retenus sur la période : la convention limite ces retenues à 5 jours par an (absences courtes) ; au-delà le salaire est dû, sauf absence d'au moins 14 jours consécutifs.","✓ Retenues pour maladie de l'enfant dans la limite de 5 jours.")

Sheet Juin 2026
B2: Juin 2026 | N2: Nid Serein · Édition 2026-2027 | AB2: 46174
B3: ="Présence, salaire et déclaration Pajemploi"&IF(EnfantNom<>""," — "&EnfantNom,"")&IF(AssmatNom<>""," chez "&AssmatNom,"") | AB3: =DAY(EOMONTH(AB2,0))
B5: SALAIRE DU MOIS (BRUT) | I5: À DÉCLARER SUR PAJEMPLOI | M5: À VERSER À L'ASSMAT | AB5: =SUM(Q18:Q48)
B6: Salaire mensualisé | F6: =IF(AB19=1,SalMensBrut,0) | I6: Nombre d'heures normales | K6: =IFERROR(IF(F6=0,0,ROUND(HeuresMens+F7/TauxBrut,0)),0) | M6: Salaire net (estimé) | AB6: =SUM(L18:L48)
B7: Retenue pour absence(s) | F7: =IF(AB19=1,-AB9,0) | I7: Nombre de jours d'activité | K7: =IF(F6=0,0,ROUNDUP(JoursMens*(F6+F7)/F6,0)) | M7: =K11 | AB7: =SUM(X18:X48)
B8: Heures complémentaires | E8: =AB17 | F8: =ROUND(E8*TauxBrut*(1+MajCompl),2) | I8: Jours de congés payés | K8: ='Congés payés'!F34 | M8: Indemnités (non imposables) | AB8: =SUM(W18:W48)
B9: Heures majorées (au-delà de 45 h) | E9: =AB18 | F9: =ROUND(E9*TauxBrut*(1+MajSup),2) | I9: Heures complémentaires | K9: =E8 | M9: =SUM(K12:K15) | AB9: =ROUND(IF(TypeCode=1,IF(AB5>0,SalMensBrut*AB6/AB5,0),IF(AB7>0,SalMensBrut*AB8/AB7,0)),2)
B10: Jours fériés travaillés | F10: =ROUND(SUM(AA18:AA48)*TauxBrut,2) | I10: Heures majorées | K10: =E9 | M10: TOTAL DU MOIS | AB10: =SUM(Z18:Z48)
B11: Congés payés versés ce mois-ci | F11: ='Congés payés'!E34 | I11: Salaire net total | K11: =ROUND(F15*CoefNet,2) | M11: =M7+M9 | AB11: =SUM(AD18:AD48)
B12: Fin de contrat (régularisation, congés) | F12: =IF(AB14=1,FinSoumis,0) | I12: Indemnités d'entretien | K12: =SUM(M18:M48) | AB12: =SUM(AC18:AC48)
B13: Autre somme brute (prime, rappel…) | I13: Indemnités de repas | K13: =ROUND(SUM(Y18:Y48)*PrixRepas,2) | M13: Avec Pajemploi+, ce montant (moins votre CMG) est prélevé puis versé à l'assmat par Pajemploi. | AB13: =IF(OR(AB19=0,SalMensBrut=0),0,HeuresMens*(F6+F7)/SalMensBrut)
I14: Indemnités kilométriques | K14: =ROUND(SUM(H18:H48)*TarifKm,2) | AB14: =IF(DateFin="",0,IF(AND(DateFin>=AB2,DateFin<=EOMONTH(AB2,0)),1,0))
B15: Salaire brut du mois | F15: =SUM(F6:F13) | I15: Indemnité de rupture | K15: =IF(AB14=1,IndemRupture,0) | AB15: =SUM(F6:F11)+F13
B16: =IF(AB19=0,"Mois hors contrat (avant le début ou après la fin) : rien à déclarer ce mois-ci.",IF(AB20>4,"⚠ Deux périodes de l'onglet Contrat se chevauchent : corrigez-les.",IF(AB11>5,"⚠ Plus de 5 jours de maladie de l'enfant retenus : au-delà de 5 jours par an (absences courtes), le salaire est dû, sauf absence d'au moins 14 jours consécutifs.",""))) | AB16: =SUM(K18:K48)
B17: Date | C17: Jour | D17: ✎ Statut (si différent) | E17: ✎ Arrivée | F17: ✎ Départ | G17: ✎ Repas | H17: ✎ Km | I17: Statut retenu | J17: Prévu | K17: Réalisé | L17: Retenue | M17: Entretien | N17: ✎ Notes | AB17: =G59
B18: =IF(1<=$AB$3,$AB$2+1-1,"") | C18: =IF(B18="","",CHOOSE(WEEKDAY(B18,2),"lun","mar","mer","jeu","ven","sam","dim")) | I18: =IF(B18="","",IF(R18=0,"Hors contrat",IF(D18<>"",D18,IF(U18=1,IF(T18=1,IF(AND(DAY(B18)=1,MONTH(B18)=5),"1er mai travaillé","Férié travaillé (+10 %)"),"Accueil"),IF(S18=1,IF(OR(WEEKDAY(B18,2)=7,T18=1),IF(AND(T18=1,Q18>0),"Férié chômé payé","Repos"),"Congé payé assmat"),IF(S18=4,IF(Q18>0,"Congé sans solde assmat","Repos"),IF(Q18=0,"Repos",IF(S18=2,"Semaine non programmée",IF(S18=3,"Absence enfant – payée",IF(T18=1,"Férié chômé payé","Accueil")))))))))) | J18: =IF(OR(I18="Accueil",I18="Férié travaillé (+10 %)",I18="1er mai travaillé"),IF(OR(S18=1,S18=2),0,Q18),0) | K18: =IF(OR(I18="Accueil",I18="Férié travaillé (+10 %)",I18="1er mai travaillé"),IF(U18=1,ROUND(MOD(F18-E18,1)*24,2),J18),0) | L18: =IF(OR(I18="Maladie enfant – retenue",I18="Absence assmat – non payée",I18="Congé sans solde assmat",I18="Hors contrat"),Q18,0) | M18: =IF(K18>0,ROUND(MAX(PlancherEnt,Entretien9h/9*K18),2),0) | P18: =IF(B18="","",B18-WEEKDAY(B18,2)+1) | Q18: =IF(B18="",0,INDEX(PlanH,WEEKDAY(B18,2))) | R18: =IF(B18="",0,IF(AND(OR(DateDebut="",B18>=DateDebut),OR(DateFin="",B18<=DateFin)),1,0)) | S18: =IF(B18="",0,SUMPRODUCT((PerDu<=B18)*(PerAu>=B18)*PerCode)) | T18: =IF(B18="",0,IF(COUNTIF(FeriesEff,B18)>0,1,0)) | U18: =IF(AND(E18<>"",F18<>""),1,0) | V18: =MAX(0,K18-J18) | W18: =IF(L18>0,1,0) | X18: =IF(Q18>0,1,0) | Y18: =IF(FournitRepas="L'assistante maternelle",IF(G18<>"",G18,IF(K18>0,RepasParJour,0)),0) | Z18: =IF(I18="Congé payé assmat",IF(AND(WEEKDAY(B18,2)<=6,T18=0),1,0),0) | AA18: =IF(I18="Férié travaillé (+10 %)",K18*MajFerie,IF(I18="1er mai travaillé",K18,0)) | AB18: =H59 | AC18: =IF(B18="",0,IF(B18<AnnivRegul,0,IF(OR(I18="Accueil",I18="Férié travaillé (+10 %)",I18="1er mai travaillé"),MIN(K18,J18),IF(OR(I18="Absence enfant – payée",I18="Férié chômé payé"),Q18,0)))) | AD18: =IF(I18="Maladie enfant – retenue",1,0)
B19: =IF(2<=$AB$3,$AB$2+2-1,"") | C19: =IF(B19="","",CHOOSE(WEEKDAY(B19,2),"lun","mar","mer","jeu","ven","sam","dim")) | I19: =IF(B19="","",IF(R19=0,"Hors contrat",IF(D19<>"",D19,IF(U19=1,IF(T19=1,IF(AND(DAY(B19)=1,MONTH(B19)=5),"1er mai travaillé","Férié travaillé (+10 %)"),"Accueil"),IF(S19=1,IF(OR(WEEKDAY(B19,2)=7,T19=1),IF(AND(T19=1,Q19>0),"Férié chômé payé","Repos"),"Congé payé assmat"),IF(S19=4,IF(Q19>0,"Congé sans solde assmat","Repos"),IF(Q19=0,"Repos",IF(S19=2,"Semaine non programmée",IF(S19=3,"Absence enfant – payée",IF(T19=1,"Férié chômé payé","Accueil")))))))))) | J19: =IF(OR(I19="Accueil",I19="Férié travaillé (+10 %)",I19="1er mai travaillé"),IF(OR(S19=1,S19=2),0,Q19),0) | K19: =IF(OR(I19="Accueil",I19="Férié travaillé (+10 %)",I19="1er mai travaillé"),IF(U19=1,ROUND(MOD(F19-E19,1)*24,2),J19),0) | L19: =IF(OR(I19="Maladie enfant – retenue",I19="Absence assmat – non payée",I19="Congé sans solde assmat",I19="Hors contrat"),Q19,0) | M19: =IF(K19>0,ROUND(MAX(PlancherEnt,Entretien9h/9*K19),2),0) | P19: =IF(B19="","",B19-WEEKDAY(B19,2)+1) | Q19: =IF(B19="",0,INDEX(PlanH,WEEKDAY(B19,2))) | R19: =IF(B19="",0,IF(AND(OR(DateDebut="",B19>=DateDebut),OR(DateFin="",B19<=DateFin)),1,0)) | S19: =IF(B19="",0,SUMPRODUCT((PerDu<=B19)*(PerAu>=B19)*PerCode)) | T19: =IF(B19="",0,IF(COUNTIF(FeriesEff,B19)>0,1,0)) | U19: =IF(AND(E19<>"",F19<>""),1,0) | V19: =MAX(0,K19-J19) | W19: =IF(L19>0,1,0) | X19: =IF(Q19>0,1,0) | Y19: =IF(FournitRepas="L'assistante maternelle",IF(G19<>"",G19,IF(K19>0,RepasParJour,0)),0) | Z19: =IF(I19="Congé payé assmat",IF(AND(WEEKDAY(B19,2)<=6,T19=0),1,0),0) | AA19: =IF(I19="Férié travaillé (+10 %)",K19*MajFerie,IF(I19="1er mai travaillé",K19,0)) | AB19: =MAX(R18:R48) | AC19: =IF(B19="",0,IF(B19<AnnivRegul,0,IF(OR(I19="Accueil",I19="Férié travaillé (+10 %)",I19="1er mai travaillé"),MIN(K19,J19),IF(OR(I19="Absence enfant – payée",I19="Férié chômé payé"),Q19,0)))) | AD19: =IF(I19="Maladie enfant – retenue",1,0)
B20: =IF(3<=$AB$3,$AB$2+3-1,"") | C20: =IF(B20="","",CHOOSE(WEEKDAY(B20,2),"lun","mar","mer","jeu","ven","sam","dim")) | I20: =IF(B20="","",IF(R20=0,"Hors contrat",IF(D20<>"",D20,IF(U20=1,IF(T20=1,IF(AND(DAY(B20)=1,MONTH(B20)=5),"1er mai travaillé","Férié travaillé (+10 %)"),"Accueil"),IF(S20=1,IF(OR(WEEKDAY(B20,2)=7,T20=1),IF(AND(T20=1,Q20>0),"Férié chômé payé","Repos"),"Congé payé assmat"),IF(S20=4,IF(Q20>0,"Congé sans solde assmat","Repos"),IF(Q20=0,"Repos",IF(S20=2,"Semaine non programmée",IF(S20=3,"Absence enfant – payée",IF(T20=1,"Férié chômé payé","Accueil")))))))))) | J20: =IF(OR(I20="Accueil",I20="Férié travaillé (+10 %)",I20="1er mai travaillé"),IF(OR(S20=1,S20=2),0,Q20),0) | K20: =IF(OR(I20="Accueil",I20="Férié travaillé (+10 %)",I20="1er mai travaillé"),IF(U20=1,ROUND(MOD(F20-E20,1)*24,2),J20),0) | L20: =IF(OR(I20="Maladie enfant – retenue",I20="Absence assmat – non payée",I20="Congé sans solde assmat",I20="Hors contrat"),Q20,0) | M20: =IF(K20>0,ROUND(MAX(PlancherEnt,Entretien9h/9*K20),2),0) | P20: =IF(B20="","",B20-WEEKDAY(B20,2)+1) | Q20: =IF(B20="",0,INDEX(PlanH,WEEKDAY(B20,2))) | R20: =IF(B20="",0,IF(AND(OR(DateDebut="",B20>=DateDebut),OR(DateFin="",B20<=DateFin)),1,0)) | S20: =IF(B20="",0,SUMPRODUCT((PerDu<=B20)*(PerAu>=B20)*PerCode)) | T20: =IF(B20="",0,IF(COUNTIF(FeriesEff,B20)>0,1,0)) | U20: =IF(AND(E20<>"",F20<>""),1,0) | V20: =MAX(0,K20-J20) | W20: =IF(L20>0,1,0) | X20: =IF(Q20>0,1,0) | Y20: =IF(FournitRepas="L'assistante maternelle",IF(G20<>"",G20,IF(K20>0,RepasParJour,0)),0) | Z20: =IF(I20="Congé payé assmat",IF(AND(WEEKDAY(B20,2)<=6,T20=0),1,0),0) | AA20: =IF(I20="Férié travaillé (+10 %)",K20*MajFerie,IF(I20="1er mai travaillé",K20,0)) | AB20: =MAX(S18:S48) | AC20: =IF(B20="",0,IF(B20<AnnivRegul,0,IF(OR(I20="Accueil",I20="Férié travaillé (+10 %)",I20="1er mai travaillé"),MIN(K20,J20),IF(OR(I20="Absence enfant – payée",I20="Férié chômé payé"),Q20,0)))) | AD20: =IF(I20="Maladie enfant – retenue",1,0)
B21: =IF(4<=$AB$3,$AB$2+4-1,"") | C21: =IF(B21="","",CHOOSE(WEEKDAY(B21,2),"lun","mar","mer","jeu","ven","sam","dim")) | I21: =IF(B21="","",IF(R21=0,"Hors contrat",IF(D21<>"",D21,IF(U21=1,IF(T21=1,IF(AND(DAY(B21)=1,MONTH(B21)=5),"1er mai travaillé","Férié travaillé (+10 %)"),"Accueil"),IF(S21=1,IF(OR(WEEKDAY(B21,2)=7,T21=1),IF(AND(T21=1,Q21>0),"Férié chômé payé","Repos"),"Congé payé assmat"),IF(S21=4,IF(Q21>0,"Congé sans solde assmat","Repos"),IF(Q21=0,"Repos",IF(S21=2,"Semaine non programmée",IF(S21=3,"Absence enfant – payée",IF(T21=1,"Férié chômé payé","Accueil")))))))))) | J21: =IF(OR(I21="Accueil",I21="Férié travaillé (+10 %)",I21="1er mai travaillé"),IF(OR(S21=1,S21=2),0,Q21),0) | K21: =IF(OR(I21="Accueil",I21="Férié travaillé (+10 %)",I21="1er mai travaillé"),IF(U21=1,ROUND(MOD(F21-E21,1)*24,2),J21),0) | L21: =IF(OR(I21="Maladie enfant – retenue",I21="Absence assmat – non payée",I21="Congé sans solde assmat",I21="Hors contrat"),Q21,0) | M21: =IF(K21>0,ROUND(MAX(PlancherEnt,Entretien9h/9*K21),2),0) | P21: =IF(B21="","",B21-WEEKDAY(B21,2)+1) | Q21: =IF(B21="",0,INDEX(PlanH,WEEKDAY(B21,2))) | R21: =IF(B21="",0,IF(AND(OR(DateDebut="",B21>=DateDebut),OR(DateFin="",B21<=DateFin)),1,0)) | S21: =IF(B21="",0,SUMPRODUCT((PerDu<=B21)*(PerAu>=B21)*PerCode)) | T21: =IF(B21="",0,IF(COUNTIF(FeriesEff,B21)>0,1,0)) | U21: =IF(AND(E21<>"",F21<>""),1,0) | V21: =MAX(0,K21-J21) | W21: =IF(L21>0,1,0) | X21: =IF(Q21>0,1,0) | Y21: =IF(FournitRepas="L'assistante maternelle",IF(G21<>"",G21,IF(K21>0,RepasParJour,0)),0) | Z21: =IF(I21="Congé payé assmat",IF(AND(WEEKDAY(B21,2)<=6,T21=0),1,0),0) | AA21: =IF(I21="Férié travaillé (+10 %)",K21*MajFerie,IF(I21="1er mai travaillé",K21,0)) | AC21: =IF(B21="",0,IF(B21<AnnivRegul,0,IF(OR(I21="Accueil",I21="Férié travaillé (+10 %)",I21="1er mai travaillé"),MIN(K21,J21),IF(OR(I21="Absence enfant – payée",I21="Férié chômé payé"),Q21,0)))) | AD21: =IF(I21="Maladie enfant – retenue",1,0)
B22: =IF(5<=$AB$3,$AB$2+5-1,"") | C22: =IF(B22="","",CHOOSE(WEEKDAY(B22,2),"lun","mar","mer","jeu","ven","sam","dim")) | I22: =IF(B22="","",IF(R22=0,"Hors contrat",IF(D22<>"",D22,IF(U22=1,IF(T22=1,IF(AND(DAY(B22)=1,MONTH(B22)=5),"1er mai travaillé","Férié travaillé (+10 %)"),"Accueil"),IF(S22=1,IF(OR(WEEKDAY(B22,2)=7,T22=1),IF(AND(T22=1,Q22>0),"Férié chômé payé","Repos"),"Congé payé assmat"),IF(S22=4,IF(Q22>0,"Congé sans solde assmat","Repos"),IF(Q22=0,"Repos",IF(S22=2,"Semaine non programmée",IF(S22=3,"Absence enfant – payée",IF(T22=1,"Férié chômé payé","Accueil")))))))))) | J22: =IF(OR(I22="Accueil",I22="Férié travaillé (+10 %)",I22="1er mai travaillé"),IF(OR(S22=1,S22=2),0,Q22),0) | K22: =IF(OR(I22="Accueil",I22="Férié travaillé (+10 %)",I22="1er mai travaillé"),IF(U22=1,ROUND(MOD(F22-E22,1)*24,2),J22),0) | L22: =IF(OR(I22="Maladie enfant – retenue",I22="Absence assmat – non payée",I22="Congé sans solde assmat",I22="Hors contrat"),Q22,0) | M22: =IF(K22>0,ROUND(MAX(PlancherEnt,Entretien9h/9*K22),2),0) | P22: =IF(B22="","",B22-WEEKDAY(B22,2)+1) | Q22: =IF(B22="",0,INDEX(PlanH,WEEKDAY(B22,2))) | R22: =IF(B22="",0,IF(AND(OR(DateDebut="",B22>=DateDebut),OR(DateFin="",B22<=DateFin)),1,0)) | S22: =IF(B22="",0,SUMPRODUCT((PerDu<=B22)*(PerAu>=B22)*PerCode)) | T22: =IF(B22="",0,IF(COUNTIF(FeriesEff,B22)>0,1,0)) | U22: =IF(AND(E22<>"",F22<>""),1,0) | V22: =MAX(0,K22-J22) | W22: =IF(L22>0,1,0) | X22: =IF(Q22>0,1,0) | Y22: =IF(FournitRepas="L'assistante maternelle",IF(G22<>"",G22,IF(K22>0,RepasParJour,0)),0) | Z22: =IF(I22="Congé payé assmat",IF(AND(WEEKDAY(B22,2)<=6,T22=0),1,0),0) | AA22: =IF(I22="Férié travaillé (+10 %)",K22*MajFerie,IF(I22="1er mai travaillé",K22,0)) | AC22: =IF(B22="",0,IF(B22<AnnivRegul,0,IF(OR(I22="Accueil",I22="Férié travaillé (+10 %)",I22="1er mai travaillé"),MIN(K22,J22),IF(OR(I22="Absence enfant – payée",I22="Férié chômé payé"),Q22,0)))) | AD22: =IF(I22="Maladie enfant – retenue",1,0)
B23: =IF(6<=$AB$3,$AB$2+6-1,"") | C23: =IF(B23="","",CHOOSE(WEEKDAY(B23,2),"lun","mar","mer","jeu","ven","sam","dim")) | I23: =IF(B23="","",IF(R23=0,"Hors contrat",IF(D23<>"",D23,IF(U23=1,IF(T23=1,IF(AND(DAY(B23)=1,MONTH(B23)=5),"1er mai travaillé","Férié travaillé (+10 %)"),"Accueil"),IF(S23=1,IF(OR(WEEKDAY(B23,2)=7,T23=1),IF(AND(T23=1,Q23>0),"Férié chômé payé","Repos"),"Congé payé assmat"),IF(S23=4,IF(Q23>0,"Congé sans solde assmat","Repos"),IF(Q23=0,"Repos",IF(S23=2,"Semaine non programmée",IF(S23=3,"Absence enfant – payée",IF(T23=1,"Férié chômé payé","Accueil")))))))))) | J23: =IF(OR(I23="Accueil",I23="Férié travaillé (+10 %)",I23="1er mai travaillé"),IF(OR(S23=1,S23=2),0,Q23),0) | K23: =IF(OR(I23="Accueil",I23="Férié travaillé (+10 %)",I23="1er mai travaillé"),IF(U23=1,ROUND(MOD(F23-E23,1)*24,2),J23),0) | L23: =IF(OR(I23="Maladie enfant – retenue",I23="Absence assmat – non payée",I23="Congé sans solde assmat",I23="Hors contrat"),Q23,0) | M23: =IF(K23>0,ROUND(MAX(PlancherEnt,Entretien9h/9*K23),2),0) | P23: =IF(B23="","",B23-WEEKDAY(B23,2)+1) | Q23: =IF(B23="",0,INDEX(PlanH,WEEKDAY(B23,2))) | R23: =IF(B23="",0,IF(AND(OR(DateDebut="",B23>=DateDebut),OR(DateFin="",B23<=DateFin)),1,0)) | S23: =IF(B23="",0,SUMPRODUCT((PerDu<=B23)*(PerAu>=B23)*PerCode)) | T23: =IF(B23="",0,IF(COUNTIF(FeriesEff,B23)>0,1,0)) | U23: =IF(AND(E23<>"",F23<>""),1,0) | V23: =MAX(0,K23-J23) | W23: =IF(L23>0,1,0) | X23: =IF(Q23>0,1,0) | Y23: =IF(FournitRepas="L'assistante maternelle",IF(G23<>"",G23,IF(K23>0,RepasParJour,0)),0) | Z23: =IF(I23="Congé payé assmat",IF(AND(WEEKDAY(B23,2)<=6,T23=0),1,0),0) | AA23: =IF(I23="Férié travaillé (+10 %)",K23*MajFerie,IF(I23="1er mai travaillé",K23,0)) | AC23: =IF(B23="",0,IF(B23<AnnivRegul,0,IF(OR(I23="Accueil",I23="Férié travaillé (+10 %)",I23="1er mai travaillé"),MIN(K23,J23),IF(OR(I23="Absence enfant – payée",I23="Férié chômé payé"),Q23,0)))) | AD23: =IF(I23="Maladie enfant – retenue",1,0)
B24: =IF(7<=$AB$3,$AB$2+7-1,"") | C24: =IF(B24="","",CHOOSE(WEEKDAY(B24,2),"lun","mar","mer","jeu","ven","sam","dim")) | I24: =IF(B24="","",IF(R24=0,"Hors contrat",IF(D24<>"",D24,IF(U24=1,IF(T24=1,IF(AND(DAY(B24)=1,MONTH(B24)=5),"1er mai travaillé","Férié travaillé (+10 %)"),"Accueil"),IF(S24=1,IF(OR(WEEKDAY(B24,2)=7,T24=1),IF(AND(T24=1,Q24>0),"Férié chômé payé","Repos"),"Congé payé assmat"),IF(S24=4,IF(Q24>0,"Congé sans solde assmat","Repos"),IF(Q24=0,"Repos",IF(S24=2,"Semaine non programmée",IF(S24=3,"Absence enfant – payée",IF(T24=1,"Férié chômé payé","Accueil")))))))))) | J24: =IF(OR(I24="Accueil",I24="Férié travaillé (+10 %)",I24="1er mai travaillé"),IF(OR(S24=1,S24=2),0,Q24),0) | K24: =IF(OR(I24="Accueil",I24="Férié travaillé (+10 %)",I24="1er mai travaillé"),IF(U24=1,ROUND(MOD(F24-E24,1)*24,2),J24),0) | L24: =IF(OR(I24="Maladie enfant – retenue",I24="Absence assmat – non payée",I24="Congé sans solde assmat",I24="Hors contrat"),Q24,0) | M24: =IF(K24>0,ROUND(MAX(PlancherEnt,Entretien9h/9*K24),2),0) | P24: =IF(B24="","",B24-WEEKDAY(B24,2)+1) | Q24: =IF(B24="",0,INDEX(PlanH,WEEKDAY(B24,2))) | R24: =IF(B24="",0,IF(AND(OR(DateDebut="",B24>=DateDebut),OR(DateFin="",B24<=DateFin)),1,0)) | S24: =IF(B24="",0,SUMPRODUCT((PerDu<=B24)*(PerAu>=B24)*PerCode)) | T24: =IF(B24="",0,IF(COUNTIF(FeriesEff,B24)>0,1,0)) | U24: =IF(AND(E24<>"",F24<>""),1,0) | V24: =MAX(0,K24-J24) | W24: =IF(L24>0,1,0) | X24: =IF(Q24>0,1,0) | Y24: =IF(FournitRepas="L'assistante maternelle",IF(G24<>"",G24,IF(K24>0,RepasParJour,0)),0) | Z24: =IF(I24="Congé payé assmat",IF(AND(WEEKDAY(B24,2)<=6,T24=0),1,0),0) | AA24: =IF(I24="Férié travaillé (+10 %)",K24*MajFerie,IF(I24="1er mai travaillé",K24,0)) | AC24: =IF(B24="",0,IF(B24<AnnivRegul,0,IF(OR(I24="Accueil",I24="Férié travaillé (+10 %)",I24="1er mai travaillé"),MIN(K24,J24),IF(OR(I24="Absence enfant – payée",I24="Férié chômé payé"),Q24,0)))) | AD24: =IF(I24="Maladie enfant – retenue",1,0)
B25: =IF(8<=$AB$3,$AB$2+8-1,"") | C25: =IF(B25="","",CHOOSE(WEEKDAY(B25,2),"lun","mar","mer","jeu","ven","sam","dim")) | I25: =IF(B25="","",IF(R25=0,"Hors contrat",IF(D25<>"",D25,IF(U25=1,IF(T25=1,IF(AND(DAY(B25)=1,MONTH(B25)=5),"1er mai travaillé","Férié travaillé (+10 %)"),"Accueil"),IF(S25=1,IF(OR(WEEKDAY(B25,2)=7,T25=1),IF(AND(T25=1,Q25>0),"Férié chômé payé","Repos"),"Congé payé assmat"),IF(S25=4,IF(Q25>0,"Congé sans solde assmat","Repos"),IF(Q25=0,"Repos",IF(S25=2,"Semaine non programmée",IF(S25=3,"Absence enfant – payée",IF(T25=1,"Férié chômé payé","Accueil")))))))))) | J25: =IF(OR(I25="Accueil",I25="Férié travaillé (+10 %)",I25="1er mai travaillé"),IF(OR(S25=1,S25=2),0,Q25),0) | K25: =IF(OR(I25="Accueil",I25="Férié travaillé (+10 %)",I25="1er mai travaillé"),IF(U25=1,ROUND(MOD(F25-E25,1)*24,2),J25),0) | L25: =IF(OR(I25="Maladie enfant – retenue",I25="Absence assmat – non payée",I25="Congé sans solde assmat",I25="Hors contrat"),Q25,0) | M25: =IF(K25>0,ROUND(MAX(PlancherEnt,Entretien9h/9*K25),2),0) | P25: =IF(B25="","",B25-WEEKDAY(B25,2)+1) | Q25: =IF(B25="",0,INDEX(PlanH,WEEKDAY(B25,2))) | R25: =IF(B25="",0,IF(AND(OR(DateDebut="",B25>=DateDebut),OR(DateFin="",B25<=DateFin)),1,0)) | S25: =IF(B25="",0,SUMPRODUCT((PerDu<=B25)*(PerAu>=B25)*PerCode)) | T25: =IF(B25="",0,IF(COUNTIF(FeriesEff,B25)>0,1,0)) | U25: =IF(AND(E25<>"",F25<>""),1,0) | V25: =MAX(0,K25-J25) | W25: =IF(L25>0,1,0) | X25: =IF(Q25>0,1,0) | Y25: =IF(FournitRepas="L'assistante maternelle",IF(G25<>"",G25,IF(K25>0,RepasParJour,0)),0) | Z25: =IF(I25="Congé payé assmat",IF(AND(WEEKDAY(B25,2)<=6,T25=0),1,0),0) | AA25: =IF(I25="Férié travaillé (+10 %)",K25*MajFerie,IF(I25="1er mai travaillé",K25,0)) | AC25: =IF(B25="",0,IF(B25<AnnivRegul,0,IF(OR(I25="Accueil",I25="Férié travaillé (+10 %)",I25="1er mai travaillé"),MIN(K25,J25),IF(OR(I25="Absence enfant – payée",I25="Férié chômé payé"),Q25,0)))) | AD25: =IF(I25="Maladie enfant – retenue",1,0)
B26: =IF(9<=$AB$3,$AB$2+9-1,"") | C26: =IF(B26="","",CHOOSE(WEEKDAY(B26,2),"lun","mar","mer","jeu","ven","sam","dim")) | I26: =IF(B26="","",IF(R26=0,"Hors contrat",IF(D26<>"",D26,IF(U26=1,IF(T26=1,IF(AND(DAY(B26)=1,MONTH(B26)=5),"1er mai travaillé","Férié travaillé (+10 %)"),"Accueil"),IF(S26=1,IF(OR(WEEKDAY(B26,2)=7,T26=1),IF(AND(T26=1,Q26>0),"Férié chômé payé","Repos"),"Congé payé assmat"),IF(S26=4,IF(Q26>0,"Congé sans solde assmat","Repos"),IF(Q26=0,"Repos",IF(S26=2,"Semaine non programmée",IF(S26=3,"Absence enfant – payée",IF(T26=1,"Férié chômé payé","Accueil")))))))))) | J26: =IF(OR(I26="Accueil",I26="Férié travaillé (+10 %)",I26="1er mai travaillé"),IF(OR(S26=1,S26=2),0,Q26),0) | K26: =IF(OR(I26="Accueil",I26="Férié travaillé (+10 %)",I26="1er mai travaillé"),IF(U26=1,ROUND(MOD(F26-E26,1)*24,2),J26),0) | L26: =IF(OR(I26="Maladie enfant – retenue",I26="Absence assmat – non payée",I26="Congé sans solde assmat",I26="Hors contrat"),Q26,0) | M26: =IF(K26>0,ROUND(MAX(PlancherEnt,Entretien9h/9*K26),2),0) | P26: =IF(B26="","",B26-WEEKDAY(B26,2)+1) | Q26: =IF(B26="",0,INDEX(PlanH,WEEKDAY(B26,2))) | R26: =IF(B26="",0,IF(AND(OR(DateDebut="",B26>=DateDebut),OR(DateFin="",B26<=DateFin)),1,0)) | S26: =IF(B26="",0,SUMPRODUCT((PerDu<=B26)*(PerAu>=B26)*PerCode)) | T26: =IF(B26="",0,IF(COUNTIF(FeriesEff,B26)>0,1,0)) | U26: =IF(AND(E26<>"",F26<>""),1,0) | V26: =MAX(0,K26-J26) | W26: =IF(L26>0,1,0) | X26: =IF(Q26>0,1,0) | Y26: =IF(FournitRepas="L'assistante maternelle",IF(G26<>"",G26,IF(K26>0,RepasParJour,0)),0) | Z26: =IF(I26="Congé payé assmat",IF(AND(WEEKDAY(B26,2)<=6,T26=0),1,0),0) | AA26: =IF(I26="Férié travaillé (+10 %)",K26*MajFerie,IF(I26="1er mai travaillé",K26,0)) | AC26: =IF(B26="",0,IF(B26<AnnivRegul,0,IF(OR(I26="Accueil",I26="Férié travaillé (+10 %)",I26="1er mai travaillé"),MIN(K26,J26),IF(OR(I26="Absence enfant – payée",I26="Férié chômé payé"),Q26,0)))) | AD26: =IF(I26="Maladie enfant – retenue",1,0)
B27: =IF(10<=$AB$3,$AB$2+10-1,"") | C27: =IF(B27="","",CHOOSE(WEEKDAY(B27,2),"lun","mar","mer","jeu","ven","sam","dim")) | I27: =IF(B27="","",IF(R27=0,"Hors contrat",IF(D27<>"",D27,IF(U27=1,IF(T27=1,IF(AND(DAY(B27)=1,MONTH(B27)=5),"1er mai travaillé","Férié travaillé (+10 %)"),"Accueil"),IF(S27=1,IF(OR(WEEKDAY(B27,2)=7,T27=1),IF(AND(T27=1,Q27>0),"Férié chômé payé","Repos"),"Congé payé assmat"),IF(S27=4,IF(Q27>0,"Congé sans solde assmat","Repos"),IF(Q27=0,"Repos",IF(S27=2,"Semaine non programmée",IF(S27=3,"Absence enfant – payée",IF(T27=1,"Férié chômé payé","Accueil")))))))))) | J27: =IF(OR(I27="Accueil",I27="Férié travaillé (+10 %)",I27="1er mai travaillé"),IF(OR(S27=1,S27=2),0,Q27),0) | K27: =IF(OR(I27="Accueil",I27="Férié travaillé (+10 %)",I27="1er mai travaillé"),IF(U27=1,ROUND(MOD(F27-E27,1)*24,2),J27),0) | L27: =IF(OR(I27="Maladie enfant – retenue",I27="Absence assmat – non payée",I27="Congé sans solde assmat",I27="Hors contrat"),Q27,0) | M27: =IF(K27>0,ROUND(MAX(PlancherEnt,Entretien9h/9*K27),2),0) | P27: =IF(B27="","",B27-WEEKDAY(B27,2)+1) | Q27: =IF(B27="",0,INDEX(PlanH,WEEKDAY(B27,2))) | R27: =IF(B27="",0,IF(AND(OR(DateDebut="",B27>=DateDebut),OR(DateFin="",B27<=DateFin)),1,0)) | S27: =IF(B27="",0,SUMPRODUCT((PerDu<=B27)*(PerAu>=B27)*PerCode)) | T27: =IF(B27="",0,IF(COUNTIF(FeriesEff,B27)>0,1,0)) | U27: =IF(AND(E27<>"",F27<>""),1,0) | V27: =MAX(0,K27-J27) | W27: =IF(L27>0,1,0) | X27: =IF(Q27>0,1,0) | Y27: =IF(FournitRepas="L'assistante maternelle",IF(G27<>"",G27,IF(K27>0,RepasParJour,0)),0) | Z27: =IF(I27="Congé payé assmat",IF(AND(WEEKDAY(B27,2)<=6,T27=0),1,0),0) | AA27: =IF(I27="Férié travaillé (+10 %)",K27*MajFerie,IF(I27="1er mai travaillé",K27,0)) | AC27: =IF(B27="",0,IF(B27<AnnivRegul,0,IF(OR(I27="Accueil",I27="Férié travaillé (+10 %)",I27="1er mai travaillé"),MIN(K27,J27),IF(OR(I27="Absence enfant – payée",I27="Férié chômé payé"),Q27,0)))) | AD27: =IF(I27="Maladie enfant – retenue",1,0)
B28: =IF(11<=$AB$3,$AB$2+11-1,"") | C28: =IF(B28="","",CHOOSE(WEEKDAY(B28,2),"lun","mar","mer","jeu","ven","sam","dim")) | I28: =IF(B28="","",IF(R28=0,"Hors contrat",IF(D28<>"",D28,IF(U28=1,IF(T28=1,IF(AND(DAY(B28)=1,MONTH(B28)=5),"1er mai travaillé","Férié travaillé (+10 %)"),"Accueil"),IF(S28=1,IF(OR(WEEKDAY(B28,2)=7,T28=1),IF(AND(T28=1,Q28>0),"Férié chômé payé","Repos"),"Congé payé assmat"),IF(S28=4,IF(Q28>0,"Congé sans solde assmat","Repos"),IF(Q28=0,"Repos",IF(S28=2,"Semaine non programmée",IF(S28=3,"Absence enfant – payée",IF(T28=1,"Férié chômé payé","Accueil")))))))))) | J28: =IF(OR(I28="Accueil",I28="Férié travaillé (+10 %)",I28="1er mai travaillé"),IF(OR(S28=1,S28=2),0,Q28),0) | K28: =IF(OR(I28="Accueil",I28="Férié travaillé (+10 %)",I28="1er mai travaillé"),IF(U28=1,ROUND(MOD(F28-E28,1)*24,2),J28),0) | L28: =IF(OR(I28="Maladie enfant – retenue",I28="Absence assmat – non payée",I28="Congé sans solde assmat",I28="Hors contrat"),Q28,0) | M28: =IF(K28>0,ROUND(MAX(PlancherEnt,Entretien9h/9*K28),2),0) | P28: =IF(B28="","",B28-WEEKDAY(B28,2)+1) | Q28: =IF(B28="",0,INDEX(PlanH,WEEKDAY(B28,2))) | R28: =IF(B28="",0,IF(AND(OR(DateDebut="",B28>=DateDebut),OR(DateFin="",B28<=DateFin)),1,0)) | S28: =IF(B28="",0,SUMPRODUCT((PerDu<=B28)*(PerAu>=B28)*PerCode)) | T28: =IF(B28="",0,IF(COUNTIF(FeriesEff,B28)>0,1,0)) | U28: =IF(AND(E28<>"",F28<>""),1,0) | V28: =MAX(0,K28-J28) | W28: =IF(L28>0,1,0) | X28: =IF(Q28>0,1,0) | Y28: =IF(FournitRepas="L'assistante maternelle",IF(G28<>"",G28,IF(K28>0,RepasParJour,0)),0) | Z28: =IF(I28="Congé payé assmat",IF(AND(WEEKDAY(B28,2)<=6,T28=0),1,0),0) | AA28: =IF(I28="Férié travaillé (+10 %)",K28*MajFerie,IF(I28="1er mai travaillé",K28,0)) | AC28: =IF(B28="",0,IF(B28<AnnivRegul,0,IF(OR(I28="Accueil",I28="Férié travaillé (+10 %)",I28="1er mai travaillé"),MIN(K28,J28),IF(OR(I28="Absence enfant – payée",I28="Férié chômé payé"),Q28,0)))) | AD28: =IF(I28="Maladie enfant – retenue",1,0)
B29: =IF(12<=$AB$3,$AB$2+12-1,"") | C29: =IF(B29="","",CHOOSE(WEEKDAY(B29,2),"lun","mar","mer","jeu","ven","sam","dim")) | I29: =IF(B29="","",IF(R29=0,"Hors contrat",IF(D29<>"",D29,IF(U29=1,IF(T29=1,IF(AND(DAY(B29)=1,MONTH(B29)=5),"1er mai travaillé","Férié travaillé (+10 %)"),"Accueil"),IF(S29=1,IF(OR(WEEKDAY(B29,2)=7,T29=1),IF(AND(T29=1,Q29>0),"Férié chômé payé","Repos"),"Congé payé assmat"),IF(S29=4,IF(Q29>0,"Congé sans solde assmat","Repos"),IF(Q29=0,"Repos",IF(S29=2,"Semaine non programmée",IF(S29=3,"Absence enfant – payée",IF(T29=1,"Férié chômé payé","Accueil")))))))))) | J29: =IF(OR(I29="Accueil",I29="Férié travaillé (+10 %)",I29="1er mai travaillé"),IF(OR(S29=1,S29=2),0,Q29),0) | K29: =IF(OR(I29="Accueil",I29="Férié travaillé (+10 %)",I29="1er mai travaillé"),IF(U29=1,ROUND(MOD(F29-E29,1)*24,2),J29),0) | L29: =IF(OR(I29="Maladie enfant – retenue",I29="Absence assmat – non payée",I29="Congé sans solde assmat",I29="Hors contrat"),Q29,0) | M29: =IF(K29>0,ROUND(MAX(PlancherEnt,Entretien9h/9*K29),2),0) | P29: =IF(B29="","",B29-WEEKDAY(B29,2)+1) | Q29: =IF(B29="",0,INDEX(PlanH,WEEKDAY(B29,2))) | R29: =IF(B29="",0,IF(AND(OR(DateDebut="",B29>=DateDebut),OR(DateFin="",B29<=DateFin)),1,0)) | S29: =IF(B29="",0,SUMPRODUCT((PerDu<=B29)*(PerAu>=B29)*PerCode)) | T29: =IF(B29="",0,IF(COUNTIF(FeriesEff,B29)>0,1,0)) | U29: =IF(AND(E29<>"",F29<>""),1,0) | V29: =MAX(0,K29-J29) | W29: =IF(L29>0,1,0) | X29: =IF(Q29>0,1,0) | Y29: =IF(FournitRepas="L'assistante maternelle",IF(G29<>"",G29,IF(K29>0,RepasParJour,0)),0) | Z29: =IF(I29="Congé payé assmat",IF(AND(WEEKDAY(B29,2)<=6,T29=0),1,0),0) | AA29: =IF(I29="Férié travaillé (+10 %)",K29*MajFerie,IF(I29="1er mai travaillé",K29,0)) | AC29: =IF(B29="",0,IF(B29<AnnivRegul,0,IF(OR(I29="Accueil",I29="Férié travaillé (+10 %)",I29="1er mai travaillé"),MIN(K29,J29),IF(OR(I29="Absence enfant – payée",I29="Férié chômé payé"),Q29,0)))) | AD29: =IF(I29="Maladie enfant – retenue",1,0)
B30: =IF(13<=$AB$3,$AB$2+13-1,"") | C30: =IF(B30="","",CHOOSE(WEEKDAY(B30,2),"lun","mar","mer","jeu","ven","sam","dim")) | I30: =IF(B30="","",IF(R30=0,"Hors contrat",IF(D30<>"",D30,IF(U30=1,IF(T30=1,IF(AND(DAY(B30)=1,MONTH(B30)=5),"1er mai travaillé","Férié travaillé (+10 %)"),"Accueil"),IF(S30=1,IF(OR(WEEKDAY(B30,2)=7,T30=1),IF(AND(T30=1,Q30>0),"Férié chômé payé","Repos"),"Congé payé assmat"),IF(S30=4,IF(Q30>0,"Congé sans solde assmat","Repos"),IF(Q30=0,"Repos",IF(S30=2,"Semaine non programmée",IF(S30=3,"Absence enfant – payée",IF(T30=1,"Férié chômé payé","Accueil")))))))))) | J30: =IF(OR(I30="Accueil",I30="Férié travaillé (+10 %)",I30="1er mai travaillé"),IF(OR(S30=1,S30=2),0,Q30),0) | K30: =IF(OR(I30="Accueil",I30="Férié travaillé (+10 %)",I30="1er mai travaillé"),IF(U30=1,ROUND(MOD(F30-E30,1)*24,2),J30),0) | L30: =IF(OR(I30="Maladie enfant – retenue",I30="Absence assmat – non payée",I30="Congé sans solde assmat",I30="Hors contrat"),Q30,0) | M30: =IF(K30>0,ROUND(MAX(PlancherEnt,Entretien9h/9*K30),2),0) | P30: =IF(B30="","",B30-WEEKDAY(B30,2)+1) | Q30: =IF(B30="",0,INDEX(PlanH,WEEKDAY(B30,2))) | R30: =IF(B30="",0,IF(AND(OR(DateDebut="",B30>=DateDebut),OR(DateFin="",B30<=DateFin)),1,0)) | S30: =IF(B30="",0,SUMPRODUCT((PerDu<=B30)*(PerAu>=B30)*PerCode)) | T30: =IF(B30="",0,IF(COUNTIF(FeriesEff,B30)>0,1,0)) | U30: =IF(AND(E30<>"",F30<>""),1,0) | V30: =MAX(0,K30-J30) | W30: =IF(L30>0,1,0) | X30: =IF(Q30>0,1,0) | Y30: =IF(FournitRepas="L'assistante maternelle",IF(G30<>"",G30,IF(K30>0,RepasParJour,0)),0) | Z30: =IF(I30="Congé payé assmat",IF(AND(WEEKDAY(B30,2)<=6,T30=0),1,0),0) | AA30: =IF(I30="Férié travaillé (+10 %)",K30*MajFerie,IF(I30="1er mai travaillé",K30,0)) | AC30: =IF(B30="",0,IF(B30<AnnivRegul,0,IF(OR(I30="Accueil",I30="Férié travaillé (+10 %)",I30="1er mai travaillé"),MIN(K30,J30),IF(OR(I30="Absence enfant – payée",I30="Férié chômé payé"),Q30,0)))) | AD30: =IF(I30="Maladie enfant – retenue",1,0)
B31: =IF(14<=$AB$3,$AB$2+14-1,"") | C31: =IF(B31="","",CHOOSE(WEEKDAY(B31,2),"lun","mar","mer","jeu","ven","sam","dim")) | I31: =IF(B31="","",IF(R31=0,"Hors contrat",IF(D31<>"",D31,IF(U31=1,IF(T31=1,IF(AND(DAY(B31)=1,MONTH(B31)=5),"1er mai travaillé","Férié travaillé (+10 %)"),"Accueil"),IF(S31=1,IF(OR(WEEKDAY(B31,2)=7,T31=1),IF(AND(T31=1,Q31>0),"Férié chômé payé","Repos"),"Congé payé assmat"),IF(S31=4,IF(Q31>0,"Congé sans solde assmat","Repos"),IF(Q31=0,"Repos",IF(S31=2,"Semaine non programmée",IF(S31=3,"Absence enfant – payée",IF(T31=1,"Férié chômé payé","Accueil")))))))))) | J31: =IF(OR(I31="Accueil",I31="Férié travaillé (+10 %)",I31="1er mai travaillé"),IF(OR(S31=1,S31=2),0,Q31),0) | K31: =IF(OR(I31="Accueil",I31="Férié travaillé (+10 %)",I31="1er mai travaillé"),IF(U31=1,ROUND(MOD(F31-E31,1)*24,2),J31),0) | L31: =IF(OR(I31="Maladie enfant – retenue",I31="Absence assmat – non payée",I31="Congé sans solde assmat",I31="Hors contrat"),Q31,0) | M31: =IF(K31>0,ROUND(MAX(PlancherEnt,Entretien9h/9*K31),2),0) | P31: =IF(B31="","",B31-WEEKDAY(B31,2)+1) | Q31: =IF(B31="",0,INDEX(PlanH,WEEKDAY(B31,2))) | R31: =IF(B31="",0,IF(AND(OR(DateDebut="",B31>=DateDebut),OR(DateFin="",B31<=DateFin)),1,0)) | S31: =IF(B31="",0,SUMPRODUCT((PerDu<=B31)*(PerAu>=B31)*PerCode)) | T31: =IF(B31="",0,IF(COUNTIF(FeriesEff,B31)>0,1,0)) | U31: =IF(AND(E31<>"",F31<>""),1,0) | V31: =MAX(0,K31-J31) | W31: =IF(L31>0,1,0) | X31: =IF(Q31>0,1,0) | Y31: =IF(FournitRepas="L'assistante maternelle",IF(G31<>"",G31,IF(K31>0,RepasParJour,0)),0) | Z31: =IF(I31="Congé payé assmat",IF(AND(WEEKDAY(B31,2)<=6,T31=0),1,0),0) | AA31: =IF(I31="Férié travaillé (+10 %)",K31*MajFerie,IF(I31="1er mai travaillé",K31,0)) | AC31: =IF(B31="",0,IF(B31<AnnivRegul,0,IF(OR(I31="Accueil",I31="Férié travaillé (+10 %)",I31="1er mai travaillé"),MIN(K31,J31),IF(OR(I31="Absence enfant – payée",I31="Férié chômé payé"),Q31,0)))) | AD31: =IF(I31="Maladie enfant – retenue",1,0)
B32: =IF(15<=$AB$3,$AB$2+15-1,"") | C32: =IF(B32="","",CHOOSE(WEEKDAY(B32,2),"lun","mar","mer","jeu","ven","sam","dim")) | I32: =IF(B32="","",IF(R32=0,"Hors contrat",IF(D32<>"",D32,IF(U32=1,IF(T32=1,IF(AND(DAY(B32)=1,MONTH(B32)=5),"1er mai travaillé","Férié travaillé (+10 %)"),"Accueil"),IF(S32=1,IF(OR(WEEKDAY(B32,2)=7,T32=1),IF(AND(T32=1,Q32>0),"Férié chômé payé","Repos"),"Congé payé assmat"),IF(S32=4,IF(Q32>0,"Congé sans solde assmat","Repos"),IF(Q32=0,"Repos",IF(S32=2,"Semaine non programmée",IF(S32=3,"Absence enfant – payée",IF(T32=1,"Férié chômé payé","Accueil")))))))))) | J32: =IF(OR(I32="Accueil",I32="Férié travaillé (+10 %)",I32="1er mai travaillé"),IF(OR(S32=1,S32=2),0,Q32),0) | K32: =IF(OR(I32="Accueil",I32="Férié travaillé (+10 %)",I32="1er mai travaillé"),IF(U32=1,ROUND(MOD(F32-E32,1)*24,2),J32),0) | L32: =IF(OR(I32="Maladie enfant – retenue",I32="Absence assmat – non payée",I32="Congé sans solde assmat",I32="Hors contrat"),Q32,0) | M32: =IF(K32>0,ROUND(MAX(PlancherEnt,Entretien9h/9*K32),2),0) | P32: =IF(B32="","",B32-WEEKDAY(B32,2)+1) | Q32: =IF(B32="",0,INDEX(PlanH,WEEKDAY(B32,2))) | R32: =IF(B32="",0,IF(AND(OR(DateDebut="",B32>=DateDebut),OR(DateFin="",B32<=DateFin)),1,0)) | S32: =IF(B32="",0,SUMPRODUCT((PerDu<=B32)*(PerAu>=B32)*PerCode)) | T32: =IF(B32="",0,IF(COUNTIF(FeriesEff,B32)>0,1,0)) | U32: =IF(AND(E32<>"",F32<>""),1,0) | V32: =MAX(0,K32-J32) | W32: =IF(L32>0,1,0) | X32: =IF(Q32>0,1,0) | Y32: =IF(FournitRepas="L'assistante maternelle",IF(G32<>"",G32,IF(K32>0,RepasParJour,0)),0) | Z32: =IF(I32="Congé payé assmat",IF(AND(WEEKDAY(B32,2)<=6,T32=0),1,0),0) | AA32: =IF(I32="Férié travaillé (+10 %)",K32*MajFerie,IF(I32="1er mai travaillé",K32,0)) | AC32: =IF(B32="",0,IF(B32<AnnivRegul,0,IF(OR(I32="Accueil",I32="Férié travaillé (+10 %)",I32="1er mai travaillé"),MIN(K32,J32),IF(OR(I32="Absence enfant – payée",I32="Férié chômé payé"),Q32,0)))) | AD32: =IF(I32="Maladie enfant – retenue",1,0)
B33: =IF(16<=$AB$3,$AB$2+16-1,"") | C33: =IF(B33="","",CHOOSE(WEEKDAY(B33,2),"lun","mar","mer","jeu","ven","sam","dim")) | I33: =IF(B33="","",IF(R33=0,"Hors contrat",IF(D33<>"",D33,IF(U33=1,IF(T33=1,IF(AND(DAY(B33)=1,MONTH(B33)=5),"1er mai travaillé","Férié travaillé (+10 %)"),"Accueil"),IF(S33=1,IF(OR(WEEKDAY(B33,2)=7,T33=1),IF(AND(T33=1,Q33>0),"Férié chômé payé","Repos"),"Congé payé assmat"),IF(S33=4,IF(Q33>0,"Congé sans solde assmat","Repos"),IF(Q33=0,"Repos",IF(S33=2,"Semaine non programmée",IF(S33=3,"Absence enfant – payée",IF(T33=1,"Férié chômé payé","Accueil")))))))))) | J33: =IF(OR(I33="Accueil",I33="Férié travaillé (+10 %)",I33="1er mai travaillé"),IF(OR(S33=1,S33=2),0,Q33),0) | K33: =IF(OR(I33="Accueil",I33="Férié travaillé (+10 %)",I33="1er mai travaillé"),IF(U33=1,ROUND(MOD(F33-E33,1)*24,2),J33),0) | L33: =IF(OR(I33="Maladie enfant – retenue",I33="Absence assmat – non payée",I33="Congé sans solde assmat",I33="Hors contrat"),Q33,0) | M33: =IF(K33>0,ROUND(MAX(PlancherEnt,Entretien9h/9*K33),2),0) | P33: =IF(B33="","",B33-WEEKDAY(B33,2)+1) | Q33: =IF(B33="",0,INDEX(PlanH,WEEKDAY(B33,2))) | R33: =IF(B33="",0,IF(AND(OR(DateDebut="",B33>=DateDebut),OR(DateFin="",B33<=DateFin)),1,0)) | S33: =IF(B33="",0,SUMPRODUCT((PerDu<=B33)*(PerAu>=B33)*PerCode)) | T33: =IF(B33="",0,IF(COUNTIF(FeriesEff,B33)>0,1,0)) | U33: =IF(AND(E33<>"",F33<>""),1,0) | V33: =MAX(0,K33-J33) | W33: =IF(L33>0,1,0) | X33: =IF(Q33>0,1,0) | Y33: =IF(FournitRepas="L'assistante maternelle",IF(G33<>"",G33,IF(K33>0,RepasParJour,0)),0) | Z33: =IF(I33="Congé payé assmat",IF(AND(WEEKDAY(B33,2)<=6,T33=0),1,0),0) | AA33: =IF(I33="Férié travaillé (+10 %)",K33*MajFerie,IF(I33="1er mai travaillé",K33,0)) | AC33: =IF(B33="",0,IF(B33<AnnivRegul,0,IF(OR(I33="Accueil",I33="Férié travaillé (+10 %)",I33="1er mai travaillé"),MIN(K33,J33),IF(OR(I33="Absence enfant – payée",I33="Férié chômé payé"),Q33,0)))) | AD33: =IF(I33="Maladie enfant – retenue",1,0)
B34: =IF(17<=$AB$3,$AB$2+17-1,"") | C34: =IF(B34="","",CHOOSE(WEEKDAY(B34,2),"lun","mar","mer","jeu","ven","sam","dim")) | I34: =IF(B34="","",IF(R34=0,"Hors contrat",IF(D34<>"",D34,IF(U34=1,IF(T34=1,IF(AND(DAY(B34)=1,MONTH(B34)=5),"1er mai travaillé","Férié travaillé (+10 %)"),"Accueil"),IF(S34=1,IF(OR(WEEKDAY(B34,2)=7,T34=1),IF(AND(T34=1,Q34>0),"Férié chômé payé","Repos"),"Congé payé assmat"),IF(S34=4,IF(Q34>0,"Congé sans solde assmat","Repos"),IF(Q34=0,"Repos",IF(S34=2,"Semaine non programmée",IF(S34=3,"Absence enfant – payée",IF(T34=1,"Férié chômé payé","Accueil")))))))))) | J34: =IF(OR(I34="Accueil",I34="Férié travaillé (+10 %)",I34="1er mai travaillé"),IF(OR(S34=1,S34=2),0,Q34),0) | K34: =IF(OR(I34="Accueil",I34="Férié travaillé (+10 %)",I34="1er mai travaillé"),IF(U34=1,ROUND(MOD(F34-E34,1)*24,2),J34),0) | L34: =IF(OR(I34="Maladie enfant – retenue",I34="Absence assmat – non payée",I34="Congé sans solde assmat",I34="Hors contrat"),Q34,0) | M34: =IF(K34>0,ROUND(MAX(PlancherEnt,Entretien9h/9*K34),2),0) | P34: =IF(B34="","",B34-WEEKDAY(B34,2)+1) | Q34: =IF(B34="",0,INDEX(PlanH,WEEKDAY(B34,2))) | R34: =IF(B34="",0,IF(AND(OR(DateDebut="",B34>=DateDebut),OR(DateFin="",B34<=DateFin)),1,0)) | S34: =IF(B34="",0,SUMPRODUCT((PerDu<=B34)*(PerAu>=B34)*PerCode)) | T34: =IF(B34="",0,IF(COUNTIF(FeriesEff,B34)>0,1,0)) | U34: =IF(AND(E34<>"",F34<>""),1,0) | V34: =MAX(0,K34-J34) | W34: =IF(L34>0,1,0) | X34: =IF(Q34>0,1,0) | Y34: =IF(FournitRepas="L'assistante maternelle",IF(G34<>"",G34,IF(K34>0,RepasParJour,0)),0) | Z34: =IF(I34="Congé payé assmat",IF(AND(WEEKDAY(B34,2)<=6,T34=0),1,0),0) | AA34: =IF(I34="Férié travaillé (+10 %)",K34*MajFerie,IF(I34="1er mai travaillé",K34,0)) | AC34: =IF(B34="",0,IF(B34<AnnivRegul,0,IF(OR(I34="Accueil",I34="Férié travaillé (+10 %)",I34="1er mai travaillé"),MIN(K34,J34),IF(OR(I34="Absence enfant – payée",I34="Férié chômé payé"),Q34,0)))) | AD34: =IF(I34="Maladie enfant – retenue",1,0)
B35: =IF(18<=$AB$3,$AB$2+18-1,"") | C35: =IF(B35="","",CHOOSE(WEEKDAY(B35,2),"lun","mar","mer","jeu","ven","sam","dim")) | I35: =IF(B35="","",IF(R35=0,"Hors contrat",IF(D35<>"",D35,IF(U35=1,IF(T35=1,IF(AND(DAY(B35)=1,MONTH(B35)=5),"1er mai travaillé","Férié travaillé (+10 %)"),"Accueil"),IF(S35=1,IF(OR(WEEKDAY(B35,2)=7,T35=1),IF(AND(T35=1,Q35>0),"Férié chômé payé","Repos"),"Congé payé assmat"),IF(S35=4,IF(Q35>0,"Congé sans solde assmat","Repos"),IF(Q35=0,"Repos",IF(S35=2,"Semaine non programmée",IF(S35=3,"Absence enfant – payée",IF(T35=1,"Férié chômé payé","Accueil")))))))))) | J35: =IF(OR(I35="Accueil",I35="Férié travaillé (+10 %)",I35="1er mai travaillé"),IF(OR(S35=1,S35=2),0,Q35),0) | K35: =IF(OR(I35="Accueil",I35="Férié travaillé (+10 %)",I35="1er mai travaillé"),IF(U35=1,ROUND(MOD(F35-E35,1)*24,2),J35),0) | L35: =IF(OR(I35="Maladie enfant – retenue",I35="Absence assmat – non payée",I35="Congé sans solde assmat",I35="Hors contrat"),Q35,0) | M35: =IF(K35>0,ROUND(MAX(PlancherEnt,Entretien9h/9*K35),2),0) | P35: =IF(B35="","",B35-WEEKDAY(B35,2)+1) | Q35: =IF(B35="",0,INDEX(PlanH,WEEKDAY(B35,2))) | R35: =IF(B35="",0,IF(AND(OR(DateDebut="",B35>=DateDebut),OR(DateFin="",B35<=DateFin)),1,0)) | S35: =IF(B35="",0,SUMPRODUCT((PerDu<=B35)*(PerAu>=B35)*PerCode)) | T35: =IF(B35="",0,IF(COUNTIF(FeriesEff,B35)>0,1,0)) | U35: =IF(AND(E35<>"",F35<>""),1,0) | V35: =MAX(0,K35-J35) | W35: =IF(L35>0,1,0) | X35: =IF(Q35>0,1,0) | Y35: =IF(FournitRepas="L'assistante maternelle",IF(G35<>"",G35,IF(K35>0,RepasParJour,0)),0) | Z35: =IF(I35="Congé payé assmat",IF(AND(WEEKDAY(B35,2)<=6,T35=0),1,0),0) | AA35: =IF(I35="Férié travaillé (+10 %)",K35*MajFerie,IF(I35="1er mai travaillé",K35,0)) | AC35: =IF(B35="",0,IF(B35<AnnivRegul,0,IF(OR(I35="Accueil",I35="Férié travaillé (+10 %)",I35="1er mai travaillé"),MIN(K35,J35),IF(OR(I35="Absence enfant – payée",I35="Férié chômé payé"),Q35,0)))) | AD35: =IF(I35="Maladie enfant – retenue",1,0)
B36: =IF(19<=$AB$3,$AB$2+19-1,"") | C36: =IF(B36="","",CHOOSE(WEEKDAY(B36,2),"lun","mar","mer","jeu","ven","sam","dim")) | I36: =IF(B36="","",IF(R36=0,"Hors contrat",IF(D36<>"",D36,IF(U36=1,IF(T36=1,IF(AND(DAY(B36)=1,MONTH(B36)=5),"1er mai travaillé","Férié travaillé (+10 %)"),"Accueil"),IF(S36=1,IF(OR(WEEKDAY(B36,2)=7,T36=1),IF(AND(T36=1,Q36>0),"Férié chômé payé","Repos"),"Congé payé assmat"),IF(S36=4,IF(Q36>0,"Congé sans solde assmat","Repos"),IF(Q36=0,"Repos",IF(S36=2,"Semaine non programmée",IF(S36=3,"Absence enfant – payée",IF(T36=1,"Férié chômé payé","Accueil")))))))))) | J36: =IF(OR(I36="Accueil",I36="Férié travaillé (+10 %)",I36="1er mai travaillé"),IF(OR(S36=1,S36=2),0,Q36),0) | K36: =IF(OR(I36="Accueil",I36="Férié travaillé (+10 %)",I36="1er mai travaillé"),IF(U36=1,ROUND(MOD(F36-E36,1)*24,2),J36),0) | L36: =IF(OR(I36="Maladie enfant – retenue",I36="Absence assmat – non payée",I36="Congé sans solde assmat",I36="Hors contrat"),Q36,0) | M36: =IF(K36>0,ROUND(MAX(PlancherEnt,Entretien9h/9*K36),2),0) | P36: =IF(B36="","",B36-WEEKDAY(B36,2)+1) | Q36: =IF(B36="",0,INDEX(PlanH,WEEKDAY(B36,2))) | R36: =IF(B36="",0,IF(AND(OR(DateDebut="",B36>=DateDebut),OR(DateFin="",B36<=DateFin)),1,0)) | S36: =IF(B36="",0,SUMPRODUCT((PerDu<=B36)*(PerAu>=B36)*PerCode)) | T36: =IF(B36="",0,IF(COUNTIF(FeriesEff,B36)>0,1,0)) | U36: =IF(AND(E36<>"",F36<>""),1,0) | V36: =MAX(0,K36-J36) | W36: =IF(L36>0,1,0) | X36: =IF(Q36>0,1,0) | Y36: =IF(FournitRepas="L'assistante maternelle",IF(G36<>"",G36,IF(K36>0,RepasParJour,0)),0) | Z36: =IF(I36="Congé payé assmat",IF(AND(WEEKDAY(B36,2)<=6,T36=0),1,0),0) | AA36: =IF(I36="Férié travaillé (+10 %)",K36*MajFerie,IF(I36="1er mai travaillé",K36,0)) | AC36: =IF(B36="",0,IF(B36<AnnivRegul,0,IF(OR(I36="Accueil",I36="Férié travaillé (+10 %)",I36="1er mai travaillé"),MIN(K36,J36),IF(OR(I36="Absence enfant – payée",I36="Férié chômé payé"),Q36,0)))) | AD36: =IF(I36="Maladie enfant – retenue",1,0)
B37: =IF(20<=$AB$3,$AB$2+20-1,"") | C37: =IF(B37="","",CHOOSE(WEEKDAY(B37,2),"lun","mar","mer","jeu","ven","sam","dim")) | I37: =IF(B37="","",IF(R37=0,"Hors contrat",IF(D37<>"",D37,IF(U37=1,IF(T37=1,IF(AND(DAY(B37)=1,MONTH(B37)=5),"1er mai travaillé","Férié travaillé (+10 %)"),"Accueil"),IF(S37=1,IF(OR(WEEKDAY(B37,2)=7,T37=1),IF(AND(T37=1,Q37>0),"Férié chômé payé","Repos"),"Congé payé assmat"),IF(S37=4,IF(Q37>0,"Congé sans solde assmat","Repos"),IF(Q37=0,"Repos",IF(S37=2,"Semaine non programmée",IF(S37=3,"Absence enfant – payée",IF(T37=1,"Férié chômé payé","Accueil")))))))))) | J37: =IF(OR(I37="Accueil",I37="Férié travaillé (+10 %)",I37="1er mai travaillé"),IF(OR(S37=1,S37=2),0,Q37),0) | K37: =IF(OR(I37="Accueil",I37="Férié travaillé (+10 %)",I37="1er mai travaillé"),IF(U37=1,ROUND(MOD(F37-E37,1)*24,2),J37),0) | L37: =IF(OR(I37="Maladie enfant – retenue",I37="Absence assmat – non payée",I37="Congé sans solde assmat",I37="Hors contrat"),Q37,0) | M37: =IF(K37>0,ROUND(MAX(PlancherEnt,Entretien9h/9*K37),2),0) | P37: =IF(B37="","",B37-WEEKDAY(B37,2)+1) | Q37: =IF(B37="",0,INDEX(PlanH,WEEKDAY(B37,2))) | R37: =IF(B37="",0,IF(AND(OR(DateDebut="",B37>=DateDebut),OR(DateFin="",B37<=DateFin)),1,0)) | S37: =IF(B37="",0,SUMPRODUCT((PerDu<=B37)*(PerAu>=B37)*PerCode)) | T37: =IF(B37="",0,IF(COUNTIF(FeriesEff,B37)>0,1,0)) | U37: =IF(AND(E37<>"",F37<>""),1,0) | V37: =MAX(0,K37-J37) | W37: =IF(L37>0,1,0) | X37: =IF(Q37>0,1,0) | Y37: =IF(FournitRepas="L'assistante maternelle",IF(G37<>"",G37,IF(K37>0,RepasParJour,0)),0) | Z37: =IF(I37="Congé payé assmat",IF(AND(WEEKDAY(B37,2)<=6,T37=0),1,0),0) | AA37: =IF(I37="Férié travaillé (+10 %)",K37*MajFerie,IF(I37="1er mai travaillé",K37,0)) | AC37: =IF(B37="",0,IF(B37<AnnivRegul,0,IF(OR(I37="Accueil",I37="Férié travaillé (+10 %)",I37="1er mai travaillé"),MIN(K37,J37),IF(OR(I37="Absence enfant – payée",I37="Férié chômé payé"),Q37,0)))) | AD37: =IF(I37="Maladie enfant – retenue",1,0)
B38: =IF(21<=$AB$3,$AB$2+21-1,"") | C38: =IF(B38="","",CHOOSE(WEEKDAY(B38,2),"lun","mar","mer","jeu","ven","sam","dim")) | I38: =IF(B38="","",IF(R38=0,"Hors contrat",IF(D38<>"",D38,IF(U38=1,IF(T38=1,IF(AND(DAY(B38)=1,MONTH(B38)=5),"1er mai travaillé","Férié travaillé (+10 %)"),"Accueil"),IF(S38=1,IF(OR(WEEKDAY(B38,2)=7,T38=1),IF(AND(T38=1,Q38>0),"Férié chômé payé","Repos"),"Congé payé assmat"),IF(S38=4,IF(Q38>0,"Congé sans solde assmat","Repos"),IF(Q38=0,"Repos",IF(S38=2,"Semaine non programmée",IF(S38=3,"Absence enfant – payée",IF(T38=1,"Férié chômé payé","Accueil")))))))))) | J38: =IF(OR(I38="Accueil",I38="Férié travaillé (+10 %)",I38="1er mai travaillé"),IF(OR(S38=1,S38=2),0,Q38),0) | K38: =IF(OR(I38="Accueil",I38="Férié travaillé (+10 %)",I38="1er mai travaillé"),IF(U38=1,ROUND(MOD(F38-E38,1)*24,2),J38),0) | L38: =IF(OR(I38="Maladie enfant – retenue",I38="Absence assmat – non payée",I38="Congé sans solde assmat",I38="Hors contrat"),Q38,0) | M38: =IF(K38>0,ROUND(MAX(PlancherEnt,Entretien9h/9*K38),2),0) | P38: =IF(B38="","",B38-WEEKDAY(B38,2)+1) | Q38: =IF(B38="",0,INDEX(PlanH,WEEKDAY(B38,2))) | R38: =IF(B38="",0,IF(AND(OR(DateDebut="",B38>=DateDebut),OR(DateFin="",B38<=DateFin)),1,0)) | S38: =IF(B38="",0,SUMPRODUCT((PerDu<=B38)*(PerAu>=B38)*PerCode)) | T38: =IF(B38="",0,IF(COUNTIF(FeriesEff,B38)>0,1,0)) | U38: =IF(AND(E38<>"",F38<>""),1,0) | V38: =MAX(0,K38-J38) | W38: =IF(L38>0,1,0) | X38: =IF(Q38>0,1,0) | Y38: =IF(FournitRepas="L'assistante maternelle",IF(G38<>"",G38,IF(K38>0,RepasParJour,0)),0) | Z38: =IF(I38="Congé payé assmat",IF(AND(WEEKDAY(B38,2)<=6,T38=0),1,0),0) | AA38: =IF(I38="Férié travaillé (+10 %)",K38*MajFerie,IF(I38="1er mai travaillé",K38,0)) | AC38: =IF(B38="",0,IF(B38<AnnivRegul,0,IF(OR(I38="Accueil",I38="Férié travaillé (+10 %)",I38="1er mai travaillé"),MIN(K38,J38),IF(OR(I38="Absence enfant – payée",I38="Férié chômé payé"),Q38,0)))) | AD38: =IF(I38="Maladie enfant – retenue",1,0)
B39: =IF(22<=$AB$3,$AB$2+22-1,"") | C39: =IF(B39="","",CHOOSE(WEEKDAY(B39,2),"lun","mar","mer","jeu","ven","sam","dim")) | I39: =IF(B39="","",IF(R39=0,"Hors contrat",IF(D39<>"",D39,IF(U39=1,IF(T39=1,IF(AND(DAY(B39)=1,MONTH(B39)=5),"1er mai travaillé","Férié travaillé (+10 %)"),"Accueil"),IF(S39=1,IF(OR(WEEKDAY(B39,2)=7,T39=1),IF(AND(T39=1,Q39>0),"Férié chômé payé","Repos"),"Congé payé assmat"),IF(S39=4,IF(Q39>0,"Congé sans solde assmat","Repos"),IF(Q39=0,"Repos",IF(S39=2,"Semaine non programmée",IF(S39=3,"Absence enfant – payée",IF(T39=1,"Férié chômé payé","Accueil")))))))))) | J39: =IF(OR(I39="Accueil",I39="Férié travaillé (+10 %)",I39="1er mai travaillé"),IF(OR(S39=1,S39=2),0,Q39),0) | K39: =IF(OR(I39="Accueil",I39="Férié travaillé (+10 %)",I39="1er mai travaillé"),IF(U39=1,ROUND(MOD(F39-E39,1)*24,2),J39),0) | L39: =IF(OR(I39="Maladie enfant – retenue",I39="Absence assmat – non payée",I39="Congé sans solde assmat",I39="Hors contrat"),Q39,0) | M39: =IF(K39>0,ROUND(MAX(PlancherEnt,Entretien9h/9*K39),2),0) | P39: =IF(B39="","",B39-WEEKDAY(B39,2)+1) | Q39: =IF(B39="",0,INDEX(PlanH,WEEKDAY(B39,2))) | R39: =IF(B39="",0,IF(AND(OR(DateDebut="",B39>=DateDebut),OR(DateFin="",B39<=DateFin)),1,0)) | S39: =IF(B39="",0,SUMPRODUCT((PerDu<=B39)*(PerAu>=B39)*PerCode)) | T39: =IF(B39="",0,IF(COUNTIF(FeriesEff,B39)>0,1,0)) | U39: =IF(AND(E39<>"",F39<>""),1,0) | V39: =MAX(0,K39-J39) | W39: =IF(L39>0,1,0) | X39: =IF(Q39>0,1,0) | Y39: =IF(FournitRepas="L'assistante maternelle",IF(G39<>"",G39,IF(K39>0,RepasParJour,0)),0) | Z39: =IF(I39="Congé payé assmat",IF(AND(WEEKDAY(B39,2)<=6,T39=0),1,0),0) | AA39: =IF(I39="Férié travaillé (+10 %)",K39*MajFerie,IF(I39="1er mai travaillé",K39,0)) | AC39: =IF(B39="",0,IF(B39<AnnivRegul,0,IF(OR(I39="Accueil",I39="Férié travaillé (+10 %)",I39="1er mai travaillé"),MIN(K39,J39),IF(OR(I39="Absence enfant – payée",I39="Férié chômé payé"),Q39,0)))) | AD39: =IF(I39="Maladie enfant – retenue",1,0)
B40: =IF(23<=$AB$3,$AB$2+23-1,"") | C40: =IF(B40="","",CHOOSE(WEEKDAY(B40,2),"lun","mar","mer","jeu","ven","sam","dim")) | I40: =IF(B40="","",IF(R40=0,"Hors contrat",IF(D40<>"",D40,IF(U40=1,IF(T40=1,IF(AND(DAY(B40)=1,MONTH(B40)=5),"1er mai travaillé","Férié travaillé (+10 %)"),"Accueil"),IF(S40=1,IF(OR(WEEKDAY(B40,2)=7,T40=1),IF(AND(T40=1,Q40>0),"Férié chômé payé","Repos"),"Congé payé assmat"),IF(S40=4,IF(Q40>0,"Congé sans solde assmat","Repos"),IF(Q40=0,"Repos",IF(S40=2,"Semaine non programmée",IF(S40=3,"Absence enfant – payée",IF(T40=1,"Férié chômé payé","Accueil")))))))))) | J40: =IF(OR(I40="Accueil",I40="Férié travaillé (+10 %)",I40="1er mai travaillé"),IF(OR(S40=1,S40=2),0,Q40),0) | K40: =IF(OR(I40="Accueil",I40="Férié travaillé (+10 %)",I40="1er mai travaillé"),IF(U40=1,ROUND(MOD(F40-E40,1)*24,2),J40),0) | L40: =IF(OR(I40="Maladie enfant – retenue",I40="Absence assmat – non payée",I40="Congé sans solde assmat",I40="Hors contrat"),Q40,0) | M40: =IF(K40>0,ROUND(MAX(PlancherEnt,Entretien9h/9*K40),2),0) | P40: =IF(B40="","",B40-WEEKDAY(B40,2)+1) | Q40: =IF(B40="",0,INDEX(PlanH,WEEKDAY(B40,2))) | R40: =IF(B40="",0,IF(AND(OR(DateDebut="",B40>=DateDebut),OR(DateFin="",B40<=DateFin)),1,0)) | S40: =IF(B40="",0,SUMPRODUCT((PerDu<=B40)*(PerAu>=B40)*PerCode)) | T40: =IF(B40="",0,IF(COUNTIF(FeriesEff,B40)>0,1,0)) | U40: =IF(AND(E40<>"",F40<>""),1,0) | V40: =MAX(0,K40-J40) | W40: =IF(L40>0,1,0) | X40: =IF(Q40>0,1,0) | Y40: =IF(FournitRepas="L'assistante maternelle",IF(G40<>"",G40,IF(K40>0,RepasParJour,0)),0) | Z40: =IF(I40="Congé payé assmat",IF(AND(WEEKDAY(B40,2)<=6,T40=0),1,0),0) | AA40: =IF(I40="Férié travaillé (+10 %)",K40*MajFerie,IF(I40="1er mai travaillé",K40,0)) | AC40: =IF(B40="",0,IF(B40<AnnivRegul,0,IF(OR(I40="Accueil",I40="Férié travaillé (+10 %)",I40="1er mai travaillé"),MIN(K40,J40),IF(OR(I40="Absence enfant – payée",I40="Férié chômé payé"),Q40,0)))) | AD40: =IF(I40="Maladie enfant – retenue",1,0)
B41: =IF(24<=$AB$3,$AB$2+24-1,"") | C41: =IF(B41="","",CHOOSE(WEEKDAY(B41,2),"lun","mar","mer","jeu","ven","sam","dim")) | I41: =IF(B41="","",IF(R41=0,"Hors contrat",IF(D41<>"",D41,IF(U41=1,IF(T41=1,IF(AND(DAY(B41)=1,MONTH(B41)=5),"1er mai travaillé","Férié travaillé (+10 %)"),"Accueil"),IF(S41=1,IF(OR(WEEKDAY(B41,2)=7,T41=1),IF(AND(T41=1,Q41>0),"Férié chômé payé","Repos"),"Congé payé assmat"),IF(S41=4,IF(Q41>0,"Congé sans solde assmat","Repos"),IF(Q41=0,"Repos",IF(S41=2,"Semaine non programmée",IF(S41=3,"Absence enfant – payée",IF(T41=1,"Férié chômé payé","Accueil")))))))))) | J41: =IF(OR(I41="Accueil",I41="Férié travaillé (+10 %)",I41="1er mai travaillé"),IF(OR(S41=1,S41=2),0,Q41),0) | K41: =IF(OR(I41="Accueil",I41="Férié travaillé (+10 %)",I41="1er mai travaillé"),IF(U41=1,ROUND(MOD(F41-E41,1)*24,2),J41),0) | L41: =IF(OR(I41="Maladie enfant – retenue",I41="Absence assmat – non payée",I41="Congé sans solde assmat",I41="Hors contrat"),Q41,0) | M41: =IF(K41>0,ROUND(MAX(PlancherEnt,Entretien9h/9*K41),2),0) | P41: =IF(B41="","",B41-WEEKDAY(B41,2)+1) | Q41: =IF(B41="",0,INDEX(PlanH,WEEKDAY(B41,2))) | R41: =IF(B41="",0,IF(AND(OR(DateDebut="",B41>=DateDebut),OR(DateFin="",B41<=DateFin)),1,0)) | S41: =IF(B41="",0,SUMPRODUCT((PerDu<=B41)*(PerAu>=B41)*PerCode)) | T41: =IF(B41="",0,IF(COUNTIF(FeriesEff,B41)>0,1,0)) | U41: =IF(AND(E41<>"",F41<>""),1,0) | V41: =MAX(0,K41-J41) | W41: =IF(L41>0,1,0) | X41: =IF(Q41>0,1,0) | Y41: =IF(FournitRepas="L'assistante maternelle",IF(G41<>"",G41,IF(K41>0,RepasParJour,0)),0) | Z41: =IF(I41="Congé payé assmat",IF(AND(WEEKDAY(B41,2)<=6,T41=0),1,0),0) | AA41: =IF(I41="Férié travaillé (+10 %)",K41*MajFerie,IF(I41="1er mai travaillé",K41,0)) | AC41: =IF(B41="",0,IF(B41<AnnivRegul,0,IF(OR(I41="Accueil",I41="Férié travaillé (+10 %)",I41="1er mai travaillé"),MIN(K41,J41),IF(OR(I41="Absence enfant – payée",I41="Férié chômé payé"),Q41,0)))) | AD41: =IF(I41="Maladie enfant – retenue",1,0)
B42: =IF(25<=$AB$3,$AB$2+25-1,"") | C42: =IF(B42="","",CHOOSE(WEEKDAY(B42,2),"lun","mar","mer","jeu","ven","sam","dim")) | I42: =IF(B42="","",IF(R42=0,"Hors contrat",IF(D42<>"",D42,IF(U42=1,IF(T42=1,IF(AND(DAY(B42)=1,MONTH(B42)=5),"1er mai travaillé","Férié travaillé (+10 %)"),"Accueil"),IF(S42=1,IF(OR(WEEKDAY(B42,2)=7,T42=1),IF(AND(T42=1,Q42>0),"Férié chômé payé","Repos"),"Congé payé assmat"),IF(S42=4,IF(Q42>0,"Congé sans solde assmat","Repos"),IF(Q42=0,"Repos",IF(S42=2,"Semaine non programmée",IF(S42=3,"Absence enfant – payée",IF(T42=1,"Férié chômé payé","Accueil")))))))))) | J42: =IF(OR(I42="Accueil",I42="Férié travaillé (+10 %)",I42="1er mai travaillé"),IF(OR(S42=1,S42=2),0,Q42),0) | K42: =IF(OR(I42="Accueil",I42="Férié travaillé (+10 %)",I42="1er mai travaillé"),IF(U42=1,ROUND(MOD(F42-E42,1)*24,2),J42),0) | L42: =IF(OR(I42="Maladie enfant – retenue",I42="Absence assmat – non payée",I42="Congé sans solde assmat",I42="Hors contrat"),Q42,0) | M42: =IF(K42>0,ROUND(MAX(PlancherEnt,Entretien9h/9*K42),2),0) | P42: =IF(B42="","",B42-WEEKDAY(B42,2)+1) | Q42: =IF(B42="",0,INDEX(PlanH,WEEKDAY(B42,2))) | R42: =IF(B42="",0,IF(AND(OR(DateDebut="",B42>=DateDebut),OR(DateFin="",B42<=DateFin)),1,0)) | S42: =IF(B42="",0,SUMPRODUCT((PerDu<=B42)*(PerAu>=B42)*PerCode)) | T42: =IF(B42="",0,IF(COUNTIF(FeriesEff,B42)>0,1,0)) | U42: =IF(AND(E42<>"",F42<>""),1,0) | V42: =MAX(0,K42-J42) | W42: =IF(L42>0,1,0) | X42: =IF(Q42>0,1,0) | Y42: =IF(FournitRepas="L'assistante maternelle",IF(G42<>"",G42,IF(K42>0,RepasParJour,0)),0) | Z42: =IF(I42="Congé payé assmat",IF(AND(WEEKDAY(B42,2)<=6,T42=0),1,0),0) | AA42: =IF(I42="Férié travaillé (+10 %)",K42*MajFerie,IF(I42="1er mai travaillé",K42,0)) | AC42: =IF(B42="",0,IF(B42<AnnivRegul,0,IF(OR(I42="Accueil",I42="Férié travaillé (+10 %)",I42="1er mai travaillé"),MIN(K42,J42),IF(OR(I42="Absence enfant – payée",I42="Férié chômé payé"),Q42,0)))) | AD42: =IF(I42="Maladie enfant – retenue",1,0)
B43: =IF(26<=$AB$3,$AB$2+26-1,"") | C43: =IF(B43="","",CHOOSE(WEEKDAY(B43,2),"lun","mar","mer","jeu","ven","sam","dim")) | I43: =IF(B43="","",IF(R43=0,"Hors contrat",IF(D43<>"",D43,IF(U43=1,IF(T43=1,IF(AND(DAY(B43)=1,MONTH(B43)=5),"1er mai travaillé","Férié travaillé (+10 %)"),"Accueil"),IF(S43=1,IF(OR(WEEKDAY(B43,2)=7,T43=1),IF(AND(T43=1,Q43>0),"Férié chômé payé","Repos"),"Congé payé assmat"),IF(S43=4,IF(Q43>0,"Congé sans solde assmat","Repos"),IF(Q43=0,"Repos",IF(S43=2,"Semaine non programmée",IF(S43=3,"Absence enfant – payée",IF(T43=1,"Férié chômé payé","Accueil")))))))))) | J43: =IF(OR(I43="Accueil",I43="Férié travaillé (+10 %)",I43="1er mai travaillé"),IF(OR(S43=1,S43=2),0,Q43),0) | K43: =IF(OR(I43="Accueil",I43="Férié travaillé (+10 %)",I43="1er mai travaillé"),IF(U43=1,ROUND(MOD(F43-E43,1)*24,2),J43),0) | L43: =IF(OR(I43="Maladie enfant – retenue",I43="Absence assmat – non payée",I43="Congé sans solde assmat",I43="Hors contrat"),Q43,0) | M43: =IF(K43>0,ROUND(MAX(PlancherEnt,Entretien9h/9*K43),2),0) | P43: =IF(B43="","",B43-WEEKDAY(B43,2)+1) | Q43: =IF(B43="",0,INDEX(PlanH,WEEKDAY(B43,2))) | R43: =IF(B43="",0,IF(AND(OR(DateDebut="",B43>=DateDebut),OR(DateFin="",B43<=DateFin)),1,0)) | S43: =IF(B43="",0,SUMPRODUCT((PerDu<=B43)*(PerAu>=B43)*PerCode)) | T43: =IF(B43="",0,IF(COUNTIF(FeriesEff,B43)>0,1,0)) | U43: =IF(AND(E43<>"",F43<>""),1,0) | V43: =MAX(0,K43-J43) | W43: =IF(L43>0,1,0) | X43: =IF(Q43>0,1,0) | Y43: =IF(FournitRepas="L'assistante maternelle",IF(G43<>"",G43,IF(K43>0,RepasParJour,0)),0) | Z43: =IF(I43="Congé payé assmat",IF(AND(WEEKDAY(B43,2)<=6,T43=0),1,0),0) | AA43: =IF(I43="Férié travaillé (+10 %)",K43*MajFerie,IF(I43="1er mai travaillé",K43,0)) | AC43: =IF(B43="",0,IF(B43<AnnivRegul,0,IF(OR(I43="Accueil",I43="Férié travaillé (+10 %)",I43="1er mai travaillé"),MIN(K43,J43),IF(OR(I43="Absence enfant – payée",I43="Férié chômé payé"),Q43,0)))) | AD43: =IF(I43="Maladie enfant – retenue",1,0)
B44: =IF(27<=$AB$3,$AB$2+27-1,"") | C44: =IF(B44="","",CHOOSE(WEEKDAY(B44,2),"lun","mar","mer","jeu","ven","sam","dim")) | I44: =IF(B44="","",IF(R44=0,"Hors contrat",IF(D44<>"",D44,IF(U44=1,IF(T44=1,IF(AND(DAY(B44)=1,MONTH(B44)=5),"1er mai travaillé","Férié travaillé (+10 %)"),"Accueil"),IF(S44=1,IF(OR(WEEKDAY(B44,2)=7,T44=1),IF(AND(T44=1,Q44>0),"Férié chômé payé","Repos"),"Congé payé assmat"),IF(S44=4,IF(Q44>0,"Congé sans solde assmat","Repos"),IF(Q44=0,"Repos",IF(S44=2,"Semaine non programmée",IF(S44=3,"Absence enfant – payée",IF(T44=1,"Férié chômé payé","Accueil")))))))))) | J44: =IF(OR(I44="Accueil",I44="Férié travaillé (+10 %)",I44="1er mai travaillé"),IF(OR(S44=1,S44=2),0,Q44),0) | K44: =IF(OR(I44="Accueil",I44="Férié travaillé (+10 %)",I44="1er mai travaillé"),IF(U44=1,ROUND(MOD(F44-E44,1)*24,2),J44),0) | L44: =IF(OR(I44="Maladie enfant – retenue",I44="Absence assmat – non payée",I44="Congé sans solde assmat",I44="Hors contrat"),Q44,0) | M44: =IF(K44>0,ROUND(MAX(PlancherEnt,Entretien9h/9*K44),2),0) | P44: =IF(B44="","",B44-WEEKDAY(B44,2)+1) | Q44: =IF(B44="",0,INDEX(PlanH,WEEKDAY(B44,2))) | R44: =IF(B44="",0,IF(AND(OR(DateDebut="",B44>=DateDebut),OR(DateFin="",B44<=DateFin)),1,0)) | S44: =IF(B44="",0,SUMPRODUCT((PerDu<=B44)*(PerAu>=B44)*PerCode)) | T44: =IF(B44="",0,IF(COUNTIF(FeriesEff,B44)>0,1,0)) | U44: =IF(AND(E44<>"",F44<>""),1,0) | V44: =MAX(0,K44-J44) | W44: =IF(L44>0,1,0) | X44: =IF(Q44>0,1,0) | Y44: =IF(FournitRepas="L'assistante maternelle",IF(G44<>"",G44,IF(K44>0,RepasParJour,0)),0) | Z44: =IF(I44="Congé payé assmat",IF(AND(WEEKDAY(B44,2)<=6,T44=0),1,0),0) | AA44: =IF(I44="Férié travaillé (+10 %)",K44*MajFerie,IF(I44="1er mai travaillé",K44,0)) | AC44: =IF(B44="",0,IF(B44<AnnivRegul,0,IF(OR(I44="Accueil",I44="Férié travaillé (+10 %)",I44="1er mai travaillé"),MIN(K44,J44),IF(OR(I44="Absence enfant – payée",I44="Férié chômé payé"),Q44,0)))) | AD44: =IF(I44="Maladie enfant – retenue",1,0)
B45: =IF(28<=$AB$3,$AB$2+28-1,"") | C45: =IF(B45="","",CHOOSE(WEEKDAY(B45,2),"lun","mar","mer","jeu","ven","sam","dim")) | I45: =IF(B45="","",IF(R45=0,"Hors contrat",IF(D45<>"",D45,IF(U45=1,IF(T45=1,IF(AND(DAY(B45)=1,MONTH(B45)=5),"1er mai travaillé","Férié travaillé (+10 %)"),"Accueil"),IF(S45=1,IF(OR(WEEKDAY(B45,2)=7,T45=1),IF(AND(T45=1,Q45>0),"Férié chômé payé","Repos"),"Congé payé assmat"),IF(S45=4,IF(Q45>0,"Congé sans solde assmat","Repos"),IF(Q45=0,"Repos",IF(S45=2,"Semaine non programmée",IF(S45=3,"Absence enfant – payée",IF(T45=1,"Férié chômé payé","Accueil")))))))))) | J45: =IF(OR(I45="Accueil",I45="Férié travaillé (+10 %)",I45="1er mai travaillé"),IF(OR(S45=1,S45=2),0,Q45),0) | K45: =IF(OR(I45="Accueil",I45="Férié travaillé (+10 %)",I45="1er mai travaillé"),IF(U45=1,ROUND(MOD(F45-E45,1)*24,2),J45),0) | L45: =IF(OR(I45="Maladie enfant – retenue",I45="Absence assmat – non payée",I45="Congé sans solde assmat",I45="Hors contrat"),Q45,0) | M45: =IF(K45>0,ROUND(MAX(PlancherEnt,Entretien9h/9*K45),2),0) | P45: =IF(B45="","",B45-WEEKDAY(B45,2)+1) | Q45: =IF(B45="",0,INDEX(PlanH,WEEKDAY(B45,2))) | R45: =IF(B45="",0,IF(AND(OR(DateDebut="",B45>=DateDebut),OR(DateFin="",B45<=DateFin)),1,0)) | S45: =IF(B45="",0,SUMPRODUCT((PerDu<=B45)*(PerAu>=B45)*PerCode)) | T45: =IF(B45="",0,IF(COUNTIF(FeriesEff,B45)>0,1,0)) | U45: =IF(AND(E45<>"",F45<>""),1,0) | V45: =MAX(0,K45-J45) | W45: =IF(L45>0,1,0) | X45: =IF(Q45>0,1,0) | Y45: =IF(FournitRepas="L'assistante maternelle",IF(G45<>"",G45,IF(K45>0,RepasParJour,0)),0) | Z45: =IF(I45="Congé payé assmat",IF(AND(WEEKDAY(B45,2)<=6,T45=0),1,0),0) | AA45: =IF(I45="Férié travaillé (+10 %)",K45*MajFerie,IF(I45="1er mai travaillé",K45,0)) | AC45: =IF(B45="",0,IF(B45<AnnivRegul,0,IF(OR(I45="Accueil",I45="Férié travaillé (+10 %)",I45="1er mai travaillé"),MIN(K45,J45),IF(OR(I45="Absence enfant – payée",I45="Férié chômé payé"),Q45,0)))) | AD45: =IF(I45="Maladie enfant – retenue",1,0)
B46: =IF(29<=$AB$3,$AB$2+29-1,"") | C46: =IF(B46="","",CHOOSE(WEEKDAY(B46,2),"lun","mar","mer","jeu","ven","sam","dim")) | I46: =IF(B46="","",IF(R46=0,"Hors contrat",IF(D46<>"",D46,IF(U46=1,IF(T46=1,IF(AND(DAY(B46)=1,MONTH(B46)=5),"1er mai travaillé","Férié travaillé (+10 %)"),"Accueil"),IF(S46=1,IF(OR(WEEKDAY(B46,2)=7,T46=1),IF(AND(T46=1,Q46>0),"Férié chômé payé","Repos"),"Congé payé assmat"),IF(S46=4,IF(Q46>0,"Congé sans solde assmat","Repos"),IF(Q46=0,"Repos",IF(S46=2,"Semaine non programmée",IF(S46=3,"Absence enfant – payée",IF(T46=1,"Férié chômé payé","Accueil")))))))))) | J46: =IF(OR(I46="Accueil",I46="Férié travaillé (+10 %)",I46="1er mai travaillé"),IF(OR(S46=1,S46=2),0,Q46),0) | K46: =IF(OR(I46="Accueil",I46="Férié travaillé (+10 %)",I46="1er mai travaillé"),IF(U46=1,ROUND(MOD(F46-E46,1)*24,2),J46),0) | L46: =IF(OR(I46="Maladie enfant – retenue",I46="Absence assmat – non payée",I46="Congé sans solde assmat",I46="Hors contrat"),Q46,0) | M46: =IF(K46>0,ROUND(MAX(PlancherEnt,Entretien9h/9*K46),2),0) | P46: =IF(B46="","",B46-WEEKDAY(B46,2)+1) | Q46: =IF(B46="",0,INDEX(PlanH,WEEKDAY(B46,2))) | R46: =IF(B46="",0,IF(AND(OR(DateDebut="",B46>=DateDebut),OR(DateFin="",B46<=DateFin)),1,0)) | S46: =IF(B46="",0,SUMPRODUCT((PerDu<=B46)*(PerAu>=B46)*PerCode)) | T46: =IF(B46="",0,IF(COUNTIF(FeriesEff,B46)>0,1,0)) | U46: =IF(AND(E46<>"",F46<>""),1,0) | V46: =MAX(0,K46-J46) | W46: =IF(L46>0,1,0) | X46: =IF(Q46>0,1,0) | Y46: =IF(FournitRepas="L'assistante maternelle",IF(G46<>"",G46,IF(K46>0,RepasParJour,0)),0) | Z46: =IF(I46="Congé payé assmat",IF(AND(WEEKDAY(B46,2)<=6,T46=0),1,0),0) | AA46: =IF(I46="Férié travaillé (+10 %)",K46*MajFerie,IF(I46="1er mai travaillé",K46,0)) | AC46: =IF(B46="",0,IF(B46<AnnivRegul,0,IF(OR(I46="Accueil",I46="Férié travaillé (+10 %)",I46="1er mai travaillé"),MIN(K46,J46),IF(OR(I46="Absence enfant – payée",I46="Férié chômé payé"),Q46,0)))) | AD46: =IF(I46="Maladie enfant – retenue",1,0)
B47: =IF(30<=$AB$3,$AB$2+30-1,"") | C47: =IF(B47="","",CHOOSE(WEEKDAY(B47,2),"lun","mar","mer","jeu","ven","sam","dim")) | I47: =IF(B47="","",IF(R47=0,"Hors contrat",IF(D47<>"",D47,IF(U47=1,IF(T47=1,IF(AND(DAY(B47)=1,MONTH(B47)=5),"1er mai travaillé","Férié travaillé (+10 %)"),"Accueil"),IF(S47=1,IF(OR(WEEKDAY(B47,2)=7,T47=1),IF(AND(T47=1,Q47>0),"Férié chômé payé","Repos"),"Congé payé assmat"),IF(S47=4,IF(Q47>0,"Congé sans solde assmat","Repos"),IF(Q47=0,"Repos",IF(S47=2,"Semaine non programmée",IF(S47=3,"Absence enfant – payée",IF(T47=1,"Férié chômé payé","Accueil")))))))))) | J47: =IF(OR(I47="Accueil",I47="Férié travaillé (+10 %)",I47="1er mai travaillé"),IF(OR(S47=1,S47=2),0,Q47),0) | K47: =IF(OR(I47="Accueil",I47="Férié travaillé (+10 %)",I47="1er mai travaillé"),IF(U47=1,ROUND(MOD(F47-E47,1)*24,2),J47),0) | L47: =IF(OR(I47="Maladie enfant – retenue",I47="Absence assmat – non payée",I47="Congé sans solde assmat",I47="Hors contrat"),Q47,0) | M47: =IF(K47>0,ROUND(MAX(PlancherEnt,Entretien9h/9*K47),2),0) | P47: =IF(B47="","",B47-WEEKDAY(B47,2)+1) | Q47: =IF(B47="",0,INDEX(PlanH,WEEKDAY(B47,2))) | R47: =IF(B47="",0,IF(AND(OR(DateDebut="",B47>=DateDebut),OR(DateFin="",B47<=DateFin)),1,0)) | S47: =IF(B47="",0,SUMPRODUCT((PerDu<=B47)*(PerAu>=B47)*PerCode)) | T47: =IF(B47="",0,IF(COUNTIF(FeriesEff,B47)>0,1,0)) | U47: =IF(AND(E47<>"",F47<>""),1,0) | V47: =MAX(0,K47-J47) | W47: =IF(L47>0,1,0) | X47: =IF(Q47>0,1,0) | Y47: =IF(FournitRepas="L'assistante maternelle",IF(G47<>"",G47,IF(K47>0,RepasParJour,0)),0) | Z47: =IF(I47="Congé payé assmat",IF(AND(WEEKDAY(B47,2)<=6,T47=0),1,0),0) | AA47: =IF(I47="Férié travaillé (+10 %)",K47*MajFerie,IF(I47="1er mai travaillé",K47,0)) | AC47: =IF(B47="",0,IF(B47<AnnivRegul,0,IF(OR(I47="Accueil",I47="Férié travaillé (+10 %)",I47="1er mai travaillé"),MIN(K47,J47),IF(OR(I47="Absence enfant – payée",I47="Férié chômé payé"),Q47,0)))) | AD47: =IF(I47="Maladie enfant – retenue",1,0)
B48: =IF(31<=$AB$3,$AB$2+31-1,"") | C48: =IF(B48="","",CHOOSE(WEEKDAY(B48,2),"lun","mar","mer","jeu","ven","sam","dim")) | I48: =IF(B48="","",IF(R48=0,"Hors contrat",IF(D48<>"",D48,IF(U48=1,IF(T48=1,IF(AND(DAY(B48)=1,MONTH(B48)=5),"1er mai travaillé","Férié travaillé (+10 %)"),"Accueil"),IF(S48=1,IF(OR(WEEKDAY(B48,2)=7,T48=1),IF(AND(T48=1,Q48>0),"Férié chômé payé","Repos"),"Congé payé assmat"),IF(S48=4,IF(Q48>0,"Congé sans solde assmat","Repos"),IF(Q48=0,"Repos",IF(S48=2,"Semaine non programmée",IF(S48=3,"Absence enfant – payée",IF(T48=1,"Férié chômé payé","Accueil")))))))))) | J48: =IF(OR(I48="Accueil",I48="Férié travaillé (+10 %)",I48="1er mai travaillé"),IF(OR(S48=1,S48=2),0,Q48),0) | K48: =IF(OR(I48="Accueil",I48="Férié travaillé (+10 %)",I48="1er mai travaillé"),IF(U48=1,ROUND(MOD(F48-E48,1)*24,2),J48),0) | L48: =IF(OR(I48="Maladie enfant – retenue",I48="Absence assmat – non payée",I48="Congé sans solde assmat",I48="Hors contrat"),Q48,0) | M48: =IF(K48>0,ROUND(MAX(PlancherEnt,Entretien9h/9*K48),2),0) | P48: =IF(B48="","",B48-WEEKDAY(B48,2)+1) | Q48: =IF(B48="",0,INDEX(PlanH,WEEKDAY(B48,2))) | R48: =IF(B48="",0,IF(AND(OR(DateDebut="",B48>=DateDebut),OR(DateFin="",B48<=DateFin)),1,0)) | S48: =IF(B48="",0,SUMPRODUCT((PerDu<=B48)*(PerAu>=B48)*PerCode)) | T48: =IF(B48="",0,IF(COUNTIF(FeriesEff,B48)>0,1,0)) | U48: =IF(AND(E48<>"",F48<>""),1,0) | V48: =MAX(0,K48-J48) | W48: =IF(L48>0,1,0) | X48: =IF(Q48>0,1,0) | Y48: =IF(FournitRepas="L'assistante maternelle",IF(G48<>"",G48,IF(K48>0,RepasParJour,0)),0) | Z48: =IF(I48="Congé payé assmat",IF(AND(WEEKDAY(B48,2)<=6,T48=0),1,0),0) | AA48: =IF(I48="Férié travaillé (+10 %)",K48*MajFerie,IF(I48="1er mai travaillé",K48,0)) | AC48: =IF(B48="",0,IF(B48<AnnivRegul,0,IF(OR(I48="Accueil",I48="Férié travaillé (+10 %)",I48="1er mai travaillé"),MIN(K48,J48),IF(OR(I48="Absence enfant – payée",I48="Férié chômé payé"),Q48,0)))) | AD48: =IF(I48="Maladie enfant – retenue",1,0)
G49: =SUM(Y18:Y48) | H49: =SUM(H18:H48) | I49: Totaux du mois | J49: =SUM(J18:J48) | K49: =SUM(K18:K48) | L49: =SUM(L18:L48) | M49: =SUM(M18:M48)
B51: HEURES PAR SEMAINE (CALCUL DES HEURES COMPLÉMENTAIRES ET MAJORÉES)
B52: Semaine du | C52: au | D52: Réalisées | E52: Au planning | F52: En plus | G52: dont compl. | H52: dont major. | I52: Une heure est « en plus » dès qu'elle dépasse le planning du jour. Jusqu'à 45 h dans la semaine, elle est complémentaire (taux normal, sauf majoration prévue au contrat). Au-delà de 45 h, elle est majorée (10 % minimum).
B53: =$AB$2-WEEKDAY($AB$2,2)+1 | C53: =IF(B53="","",MIN(B53+6,EOMONTH($AB$2,0))) | D53: =IF(B53="",0,SUMIFS($K$18:$K$48,$P$18:$P$48,B53)) | E53: =IF(B53="",0,SUMIFS($J$18:$J$48,$P$18:$P$48,B53)) | F53: =IF(B53="",0,SUMIFS($V$18:$V$48,$P$18:$P$48,B53)) | G53: =IF(B53="",0,F53-H53) | H53: =IF(B53="",0,MIN(F53,MAX(0,D53-SeuilMaj)))
B54: =IF(B53="","",IF(B53+7<=EOMONTH($AB$2,0),B53+7,"")) | C54: =IF(B54="","",MIN(B54+6,EOMONTH($AB$2,0))) | D54: =IF(B54="",0,SUMIFS($K$18:$K$48,$P$18:$P$48,B54)) | E54: =IF(B54="",0,SUMIFS($J$18:$J$48,$P$18:$P$48,B54)) | F54: =IF(B54="",0,SUMIFS($V$18:$V$48,$P$18:$P$48,B54)) | G54: =IF(B54="",0,F54-H54) | H54: =IF(B54="",0,MIN(F54,MAX(0,D54-SeuilMaj)))
B55: =IF(B54="","",IF(B54+7<=EOMONTH($AB$2,0),B54+7,"")) | C55: =IF(B55="","",MIN(B55+6,EOMONTH($AB$2,0))) | D55: =IF(B55="",0,SUMIFS($K$18:$K$48,$P$18:$P$48,B55)) | E55: =IF(B55="",0,SUMIFS($J$18:$J$48,$P$18:$P$48,B55)) | F55: =IF(B55="",0,SUMIFS($V$18:$V$48,$P$18:$P$48,B55)) | G55: =IF(B55="",0,F55-H55) | H55: =IF(B55="",0,MIN(F55,MAX(0,D55-SeuilMaj)))
B56: =IF(B55="","",IF(B55+7<=EOMONTH($AB$2,0),B55+7,"")) | C56: =IF(B56="","",MIN(B56+6,EOMONTH($AB$2,0))) | D56: =IF(B56="",0,SUMIFS($K$18:$K$48,$P$18:$P$48,B56)) | E56: =IF(B56="",0,SUMIFS($J$18:$J$48,$P$18:$P$48,B56)) | F56: =IF(B56="",0,SUMIFS($V$18:$V$48,$P$18:$P$48,B56)) | G56: =IF(B56="",0,F56-H56) | H56: =IF(B56="",0,MIN(F56,MAX(0,D56-SeuilMaj)))
B57: =IF(B56="","",IF(B56+7<=EOMONTH($AB$2,0),B56+7,"")) | C57: =IF(B57="","",MIN(B57+6,EOMONTH($AB$2,0))) | D57: =IF(B57="",0,SUMIFS($K$18:$K$48,$P$18:$P$48,B57)) | E57: =IF(B57="",0,SUMIFS($J$18:$J$48,$P$18:$P$48,B57)) | F57: =IF(B57="",0,SUMIFS($V$18:$V$48,$P$18:$P$48,B57)) | G57: =IF(B57="",0,F57-H57) | H57: =IF(B57="",0,MIN(F57,MAX(0,D57-SeuilMaj)))
B58: =IF(B57="","",IF(B57+7<=EOMONTH($AB$2,0),B57+7,"")) | C58: =IF(B58="","",MIN(B58+6,EOMONTH($AB$2,0))) | D58: =IF(B58="",0,SUMIFS($K$18:$K$48,$P$18:$P$48,B58)) | E58: =IF(B58="",0,SUMIFS($J$18:$J$48,$P$18:$P$48,B58)) | F58: =IF(B58="",0,SUMIFS($V$18:$V$48,$P$18:$P$48,B58)) | G58: =IF(B58="",0,F58-H58) | H58: =IF(B58="",0,MIN(F58,MAX(0,D58-SeuilMaj)))
D59: =SUM(D53:D58) | E59: =SUM(E53:E58) | F59: =SUM(F53:F58) | G59: =SUM(G53:G58) | H59: =SUM(H53:H58)
B62: Signature du parent employeur | I62: Signature de l'assistante maternelle

Sheet Juillet 2026
B2: Juillet 2026 | N2: Nid Serein · Édition 2026-2027 | AB2: 46204
B3: ="Présence, salaire et déclaration Pajemploi"&IF(EnfantNom<>""," — "&EnfantNom,"")&IF(AssmatNom<>""," chez "&AssmatNom,"") | AB3: =DAY(EOMONTH(AB2,0))
B5: SALAIRE DU MOIS (BRUT) | I5: À DÉCLARER SUR PAJEMPLOI | M5: À VERSER À L'ASSMAT | AB5: =SUM(Q18:Q48)
B6: Salaire mensualisé | F6: =IF(AB19=1,SalMensBrut,0) | I6: Nombre d'heures normales | K6: =IFERROR(IF(F6=0,0,ROUND(HeuresMens+F7/TauxBrut,0)),0) | M6: Salaire net (estimé) | AB6: =SUM(L18:L48)
B7: Retenue pour absence(s) | F7: =IF(AB19=1,-AB9,0) | I7: Nombre de jours d'activité | K7: =IF(F6=0,0,ROUNDUP(JoursMens*(F6+F7)/F6,0)) | M7: =K11 | AB7: =SUM(X18:X48)
B8: Heures complémentaires | E8: =AB17 | F8: =ROUND(E8*TauxBrut*(1+MajCompl),2) | I8: Jours de congés payés | K8: ='Congés payés'!F35 | M8: Indemnités (non imposables) | AB8: =SUM(W18:W48)
B9: Heures majorées (au-delà de 45 h) | E9: =AB18 | F9: =ROUND(E9*TauxBrut*(1+MajSup),2) | I9: Heures complémentaires | K9: =E8 | M9: =SUM(K12:K15) | AB9: =ROUND(IF(TypeCode=1,IF(AB5>0,SalMensBrut*AB6/AB5,0),IF(AB7>0,SalMensBrut*AB8/AB7,0)),2)
B10: Jours fériés travaillés | F10: =ROUND(SUM(AA18:AA48)*TauxBrut,2) | I10: Heures majorées | K10: =E9 | M10: TOTAL DU MOIS | AB10: =SUM(Z18:Z48)
B11: Congés payés versés ce mois-ci | F11: ='Congés payés'!E35 | I11: Salaire net total | K11: =ROUND(F15*CoefNet,2) | M11: =M7+M9 | AB11: =SUM(AD18:AD48)
B12: Fin de contrat (régularisation, congés) | F12: =IF(AB14=1,FinSoumis,0) | I12: Indemnités d'entretien | K12: =SUM(M18:M48) | AB12: =SUM(AC18:AC48)
B13: Autre somme brute (prime, rappel…) | I13: Indemnités de repas | K13: =ROUND(SUM(Y18:Y48)*PrixRepas,2) | M13: Avec Pajemploi+, ce montant (moins votre CMG) est prélevé puis versé à l'assmat par Pajemploi. | AB13: =IF(OR(AB19=0,SalMensBrut=0),0,HeuresMens*(F6+F7)/SalMensBrut)
I14: Indemnités kilométriques | K14: =ROUND(SUM(H18:H48)*TarifKm,2) | AB14: =IF(DateFin="",0,IF(AND(DateFin>=AB2,DateFin<=EOMONTH(AB2,0)),1,0))
B15: Salaire brut du mois | F15: =SUM(F6:F13) | I15: Indemnité de rupture | K15: =IF(AB14=1,IndemRupture,0) | AB15: =SUM(F6:F11)+F13
B16: =IF(AB19=0,"Mois hors contrat (avant le début ou après la fin) : rien à déclarer ce mois-ci.",IF(AB20>4,"⚠ Deux périodes de l'onglet Contrat se chevauchent : corrigez-les.",IF(AB11>5,"⚠ Plus de 5 jours de maladie de l'enfant retenus : au-delà de 5 jours par an (absences courtes), le salaire est dû, sauf absence d'au moins 14 jours consécutifs.",""))) | AB16: =SUM(K18:K48)
B17: Date | C17: Jour | D17: ✎ Statut (si différent) | E17: ✎ Arrivée | F17: ✎ Départ | G17: ✎ Repas | H17: ✎ Km | I17: Statut retenu | J17: Prévu | K17: Réalisé | L17: Retenue | M17: Entretien | N17: ✎ Notes | AB17: =G59
B18: =IF(1<=$AB$3,$AB$2+1-1,"") | C18: =IF(B18="","",CHOOSE(WEEKDAY(B18,2),"lun","mar","mer","jeu","ven","sam","dim")) | I18: =IF(B18="","",IF(R18=0,"Hors contrat",IF(D18<>"",D18,IF(U18=1,IF(T18=1,IF(AND(DAY(B18)=1,MONTH(B18)=5),"1er mai travaillé","Férié travaillé (+10 %)"),"Accueil"),IF(S18=1,IF(OR(WEEKDAY(B18,2)=7,T18=1),IF(AND(T18=1,Q18>0),"Férié chômé payé","Repos"),"Congé payé assmat"),IF(S18=4,IF(Q18>0,"Congé sans solde assmat","Repos"),IF(Q18=0,"Repos",IF(S18=2,"Semaine non programmée",IF(S18=3,"Absence enfant – payée",IF(T18=1,"Férié chômé payé","Accueil")))))))))) | J18: =IF(OR(I18="Accueil",I18="Férié travaillé (+10 %)",I18="1er mai travaillé"),IF(OR(S18=1,S18=2),0,Q18),0) | K18: =IF(OR(I18="Accueil",I18="Férié travaillé (+10 %)",I18="1er mai travaillé"),IF(U18=1,ROUND(MOD(F18-E18,1)*24,2),J18),0) | L18: =IF(OR(I18="Maladie enfant – retenue",I18="Absence assmat – non payée",I18="Congé sans solde assmat",I18="Hors contrat"),Q18,0) | M18: =IF(K18>0,ROUND(MAX(PlancherEnt,Entretien9h/9*K18),2),0) | P18: =IF(B18="","",B18-WEEKDAY(B18,2)+1) | Q18: =IF(B18="",0,INDEX(PlanH,WEEKDAY(B18,2))) | R18: =IF(B18="",0,IF(AND(OR(DateDebut="",B18>=DateDebut),OR(DateFin="",B18<=DateFin)),1,0)) | S18: =IF(B18="",0,SUMPRODUCT((PerDu<=B18)*(PerAu>=B18)*PerCode)) | T18: =IF(B18="",0,IF(COUNTIF(FeriesEff,B18)>0,1,0)) | U18: =IF(AND(E18<>"",F18<>""),1,0) | V18: =MAX(0,K18-J18) | W18: =IF(L18>0,1,0) | X18: =IF(Q18>0,1,0) | Y18: =IF(FournitRepas="L'assistante maternelle",IF(G18<>"",G18,IF(K18>0,RepasParJour,0)),0) | Z18: =IF(I18="Congé payé assmat",IF(AND(WEEKDAY(B18,2)<=6,T18=0),1,0),0) | AA18: =IF(I18="Férié travaillé (+10 %)",K18*MajFerie,IF(I18="1er mai travaillé",K18,0)) | AB18: =H59 | AC18: =IF(B18="",0,IF(B18<AnnivRegul,0,IF(OR(I18="Accueil",I18="Férié travaillé (+10 %)",I18="1er mai travaillé"),MIN(K18,J18),IF(OR(I18="Absence enfant – payée",I18="Férié chômé payé"),Q18,0)))) | AD18: =IF(I18="Maladie enfant – retenue",1,0)
B19: =IF(2<=$AB$3,$AB$2+2-1,"") | C19: =IF(B19="","",CHOOSE(WEEKDAY(B19,2),"lun","mar","mer","jeu","ven","sam","dim")) | I19: =IF(B19="","",IF(R19=0,"Hors contrat",IF(D19<>"",D19,IF(U19=1,IF(T19=1,IF(AND(DAY(B19)=1,MONTH(B19)=5),"1er mai travaillé","Férié travaillé (+10 %)"),"Accueil"),IF(S19=1,IF(OR(WEEKDAY(B19,2)=7,T19=1),IF(AND(T19=1,Q19>0),"Férié chômé payé","Repos"),"Congé payé assmat"),IF(S19=4,IF(Q19>0,"Congé sans solde assmat","Repos"),IF(Q19=0,"Repos",IF(S19=2,"Semaine non programmée",IF(S19=3,"Absence enfant – payée",IF(T19=1,"Férié chômé payé","Accueil")))))))))) | J19: =IF(OR(I19="Accueil",I19="Férié travaillé (+10 %)",I19="1er mai travaillé"),IF(OR(S19=1,S19=2),0,Q19),0) | K19: =IF(OR(I19="Accueil",I19="Férié travaillé (+10 %)",I19="1er mai travaillé"),IF(U19=1,ROUND(MOD(F19-E19,1)*24,2),J19),0) | L19: =IF(OR(I19="Maladie enfant – retenue",I19="Absence assmat – non payée",I19="Congé sans solde assmat",I19="Hors contrat"),Q19,0) | M19: =IF(K19>0,ROUND(MAX(PlancherEnt,Entretien9h/9*K19),2),0) | P19: =IF(B19="","",B19-WEEKDAY(B19,2)+1) | Q19: =IF(B19="",0,INDEX(PlanH,WEEKDAY(B19,2))) | R19: =IF(B19="",0,IF(AND(OR(DateDebut="",B19>=DateDebut),OR(DateFin="",B19<=DateFin)),1,0)) | S19: =IF(B19="",0,SUMPRODUCT((PerDu<=B19)*(PerAu>=B19)*PerCode)) | T19: =IF(B19="",0,IF(COUNTIF(FeriesEff,B19)>0,1,0)) | U19: =IF(AND(E19<>"",F19<>""),1,0) | V19: =MAX(0,K19-J19) | W19: =IF(L19>0,1,0) | X19: =IF(Q19>0,1,0) | Y19: =IF(FournitRepas="L'assistante maternelle",IF(G19<>"",G19,IF(K19>0,RepasParJour,0)),0) | Z19: =IF(I19="Congé payé assmat",IF(AND(WEEKDAY(B19,2)<=6,T19=0),1,0),0) | AA19: =IF(I19="Férié travaillé (+10 %)",K19*MajFerie,IF(I19="1er mai travaillé",K19,0)) | AB19: =MAX(R18:R48) | AC19: =IF(B19="",0,IF(B19<AnnivRegul,0,IF(OR(I19="Accueil",I19="Férié travaillé (+10 %)",I19="1er mai travaillé"),MIN(K19,J19),IF(OR(I19="Absence enfant – payée",I19="Férié chômé payé"),Q19,0)))) | AD19: =IF(I19="Maladie enfant – retenue",1,0)
B20: =IF(3<=$AB$3,$AB$2+3-1,"") | C20: =IF(B20="","",CHOOSE(WEEKDAY(B20,2),"lun","mar","mer","jeu","ven","sam","dim")) | I20: =IF(B20="","",IF(R20=0,"Hors contrat",IF(D20<>"",D20,IF(U20=1,IF(T20=1,IF(AND(DAY(B20)=1,MONTH(B20)=5),"1er mai travaillé","Férié travaillé (+10 %)"),"Accueil"),IF(S20=1,IF(OR(WEEKDAY(B20,2)=7,T20=1),IF(AND(T20=1,Q20>0),"Férié chômé payé","Repos"),"Congé payé assmat"),IF(S20=4,IF(Q20>0,"Congé sans solde assmat","Repos"),IF(Q20=0,"Repos",IF(S20=2,"Semaine non programmée",IF(S20=3,"Absence enfant – payée",IF(T20=1,"Férié chômé payé","Accueil")))))))))) | J20: =IF(OR(I20="Accueil",I20="Férié travaillé (+10 %)",I20="1er mai travaillé"),IF(OR(S20=1,S20=2),0,Q20),0) | K20: =IF(OR(I20="Accueil",I20="Férié travaillé (+10 %)",I20="1er mai travaillé"),IF(U20=1,ROUND(MOD(F20-E20,1)*24,2),J20),0) | L20: =IF(OR(I20="Maladie enfant – retenue",I20="Absence assmat – non payée",I20="Congé sans solde assmat",I20="Hors contrat"),Q20,0) | M20: =IF(K20>0,ROUND(MAX(PlancherEnt,Entretien9h/9*K20),2),0) | P20: =IF(B20="","",B20-WEEKDAY(B20,2)+1) | Q20: =IF(B20="",0,INDEX(PlanH,WEEKDAY(B20,2))) | R20: =IF(B20="",0,IF(AND(OR(DateDebut="",B20>=DateDebut),OR(DateFin="",B20<=DateFin)),1,0)) | S20: =IF(B20="",0,SUMPRODUCT((PerDu<=B20)*(PerAu>=B20)*PerCode)) | T20: =IF(B20="",0,IF(COUNTIF(FeriesEff,B20)>0,1,0)) | U20: =IF(AND(E20<>"",F20<>""),1,0) | V20: =MAX(0,K20-J20) | W20: =IF(L20>0,1,0) | X20: =IF(Q20>0,1,0) | Y20: =IF(FournitRepas="L'assistante maternelle",IF(G20<>"",G20,IF(K20>0,RepasParJour,0)),0) | Z20: =IF(I20="Congé payé assmat",IF(AND(WEEKDAY(B20,2)<=6,T20=0),1,0),0) | AA20: =IF(I20="Férié travaillé (+10 %)",K20*MajFerie,IF(I20="1er mai travaillé",K20,0)) | AB20: =MAX(S18:S48) | AC20: =IF(B20="",0,IF(B20<AnnivRegul,0,IF(OR(I20="Accueil",I20="Férié travaillé (+10 %)",I20="1er mai travaillé"),MIN(K20,J20),IF(OR(I20="Absence enfant – payée",I20="Férié chômé payé"),Q20,0)))) | AD20: =IF(I20="Maladie enfant – retenue",1,0)
B21: =IF(4<=$AB$3,$AB$2+4-1,"") | C21: =IF(B21="","",CHOOSE(WEEKDAY(B21,2),"lun","mar","mer","jeu","ven","sam","dim")) | I21: =IF(B21="","",IF(R21=0,"Hors contrat",IF(D21<>"",D21,IF(U21=1,IF(T21=1,IF(AND(DAY(B21)=1,MONTH(B21)=5),"1er mai travaillé","Férié travaillé (+10 %)"),"Accueil"),IF(S21=1,IF(OR(WEEKDAY(B21,2)=7,T21=1),IF(AND(T21=1,Q21>0),"Férié chômé payé","Repos"),"Congé payé assmat"),IF(S21=4,IF(Q21>0,"Congé sans solde assmat","Repos"),IF(Q21=0,"Repos",IF(S21=2,"Semaine non programmée",IF(S21=3,"Absence enfant – payée",IF(T21=1,"Férié chômé payé","Accueil")))))))))) | J21: =IF(OR(I21="Accueil",I21="Férié travaillé (+10 %)",I21="1er mai travaillé"),IF(OR(S21=1,S21=2),0,Q21),0) | K21: =IF(OR(I21="Accueil",I21="Férié travaillé (+10 %)",I21="1er mai travaillé"),IF(U21=1,ROUND(MOD(F21-E21,1)*24,2),J21),0) | L21: =IF(OR(I21="Maladie enfant – retenue",I21="Absence assmat – non payée",I21="Congé sans solde assmat",I21="Hors contrat"),Q21,0) | M21: =IF(K21>0,ROUND(MAX(PlancherEnt,Entretien9h/9*K21),2),0) | P21: =IF(B21="","",B21-WEEKDAY(B21,2)+1) | Q21: =IF(B21="",0,INDEX(PlanH,WEEKDAY(B21,2))) | R21: =IF(B21="",0,IF(AND(OR(DateDebut="",B21>=DateDebut),OR(DateFin="",B21<=DateFin)),1,0)) | S21: =IF(B21="",0,SUMPRODUCT((PerDu<=B21)*(PerAu>=B21)*PerCode)) | T21: =IF(B21="",0,IF(COUNTIF(FeriesEff,B21)>0,1,0)) | U21: =IF(AND(E21<>"",F21<>""),1,0) | V21: =MAX(0,K21-J21) | W21: =IF(L21>0,1,0) | X21: =IF(Q21>0,1,0) | Y21: =IF(FournitRepas="L'assistante maternelle",IF(G21<>"",G21,IF(K21>0,RepasParJour,0)),0) | Z21: =IF(I21="Congé payé assmat",IF(AND(WEEKDAY(B21,2)<=6,T21=0),1,0),0) | AA21: =IF(I21="Férié travaillé (+10 %)",K21*MajFerie,IF(I21="1er mai travaillé",K21,0)) | AC21: =IF(B21="",0,IF(B21<AnnivRegul,0,IF(OR(I21="Accueil",I21="Férié travaillé (+10 %)",I21="1er mai travaillé"),MIN(K21,J21),IF(OR(I21="Absence enfant – payée",I21="Férié chômé payé"),Q21,0)))) | AD21: =IF(I21="Maladie enfant – retenue",1,0)
B22: =IF(5<=$AB$3,$AB$2+5-1,"") | C22: =IF(B22="","",CHOOSE(WEEKDAY(B22,2),"lun","mar","mer","jeu","ven","sam","dim")) | I22: =IF(B22="","",IF(R22=0,"Hors contrat",IF(D22<>"",D22,IF(U22=1,IF(T22=1,IF(AND(DAY(B22)=1,MONTH(B22)=5),"1er mai travaillé","Férié travaillé (+10 %)"),"Accueil"),IF(S22=1,IF(OR(WEEKDAY(B22,2)=7,T22=1),IF(AND(T22=1,Q22>0),"Férié chômé payé","Repos"),"Congé payé assmat"),IF(S22=4,IF(Q22>0,"Congé sans solde assmat","Repos"),IF(Q22=0,"Repos",IF(S22=2,"Semaine non programmée",IF(S22=3,"Absence enfant – payée",IF(T22=1,"Férié chômé payé","Accueil")))))))))) | J22: =IF(OR(I22="Accueil",I22="Férié travaillé (+10 %)",I22="1er mai travaillé"),IF(OR(S22=1,S22=2),0,Q22),0) | K22: =IF(OR(I22="Accueil",I22="Férié travaillé (+10 %)",I22="1er mai travaillé"),IF(U22=1,ROUND(MOD(F22-E22,1)*24,2),J22),0) | L22: =IF(OR(I22="Maladie enfant – retenue",I22="Absence assmat – non payée",I22="Congé sans solde assmat",I22="Hors contrat"),Q22,0) | M22: =IF(K22>0,ROUND(MAX(PlancherEnt,Entretien9h/9*K22),2),0) | P22: =IF(B22="","",B22-WEEKDAY(B22,2)+1) | Q22: =IF(B22="",0,INDEX(PlanH,WEEKDAY(B22,2))) | R22: =IF(B22="",0,IF(AND(OR(DateDebut="",B22>=DateDebut),OR(DateFin="",B22<=DateFin)),1,0)) | S22: =IF(B22="",0,SUMPRODUCT((PerDu<=B22)*(PerAu>=B22)*PerCode)) | T22: =IF(B22="",0,IF(COUNTIF(FeriesEff,B22)>0,1,0)) | U22: =IF(AND(E22<>"",F22<>""),1,0) | V22: =MAX(0,K22-J22) | W22: =IF(L22>0,1,0) | X22: =IF(Q22>0,1,0) | Y22: =IF(FournitRepas="L'assistante maternelle",IF(G22<>"",G22,IF(K22>0,RepasParJour,0)),0) | Z22: =IF(I22="Congé payé assmat",IF(AND(WEEKDAY(B22,2)<=6,T22=0),1,0),0) | AA22: =IF(I22="Férié travaillé (+10 %)",K22*MajFerie,IF(I22="1er mai travaillé",K22,0)) | AC22: =IF(B22="",0,IF(B22<AnnivRegul,0,IF(OR(I22="Accueil",I22="Férié travaillé (+10 %)",I22="1er mai travaillé"),MIN(K22,J22),IF(OR(I22="Absence enfant – payée",I22="Férié chômé payé"),Q22,0)))) | AD22: =IF(I22="Maladie enfant – retenue",1,0)
B23: =IF(6<=$AB$3,$AB$2+6-1,"") | C23: =IF(B23="","",CHOOSE(WEEKDAY(B23,2),"lun","mar","mer","jeu","ven","sam","dim")) | I23: =IF(B23="","",IF(R23=0,"Hors contrat",IF(D23<>"",D23,IF(U23=1,IF(T23=1,IF(AND(DAY(B23)=1,MONTH(B23)=5),"1er mai travaillé","Férié travaillé (+10 %)"),"Accueil"),IF(S23=1,IF(OR(WEEKDAY(B23,2)=7,T23=1),IF(AND(T23=1,Q23>0),"Férié chômé payé","Repos"),"Congé payé assmat"),IF(S23=4,IF(Q23>0,"Congé sans solde assmat","Repos"),IF(Q23=0,"Repos",IF(S23=2,"Semaine non programmée",IF(S23=3,"Absence enfant – payée",IF(T23=1,"Férié chômé payé","Accueil")))))))))) | J23: =IF(OR(I23="Accueil",I23="Férié travaillé (+10 %)",I23="1er mai travaillé"),IF(OR(S23=1,S23=2),0,Q23),0) | K23: =IF(OR(I23="Accueil",I23="Férié travaillé (+10 %)",I23="1er mai travaillé"),IF(U23=1,ROUND(MOD(F23-E23,1)*24,2),J23),0) | L23: =IF(OR(I23="Maladie enfant – retenue",I23="Absence assmat – non payée",I23="Congé sans solde assmat",I23="Hors contrat"),Q23,0) | M23: =IF(K23>0,ROUND(MAX(PlancherEnt,Entretien9h/9*K23),2),0) | P23: =IF(B23="","",B23-WEEKDAY(B23,2)+1) | Q23: =IF(B23="",0,INDEX(PlanH,WEEKDAY(B23,2))) | R23: =IF(B23="",0,IF(AND(OR(DateDebut="",B23>=DateDebut),OR(DateFin="",B23<=DateFin)),1,0)) | S23: =IF(B23="",0,SUMPRODUCT((PerDu<=B23)*(PerAu>=B23)*PerCode)) | T23: =IF(B23="",0,IF(COUNTIF(FeriesEff,B23)>0,1,0)) | U23: =IF(AND(E23<>"",F23<>""),1,0) | V23: =MAX(0,K23-J23) | W23: =IF(L23>0,1,0) | X23: =IF(Q23>0,1,0) | Y23: =IF(FournitRepas="L'assistante maternelle",IF(G23<>"",G23,IF(K23>0,RepasParJour,0)),0) | Z23: =IF(I23="Congé payé assmat",IF(AND(WEEKDAY(B23,2)<=6,T23=0),1,0),0) | AA23: =IF(I23="Férié travaillé (+10 %)",K23*MajFerie,IF(I23="1er mai travaillé",K23,0)) | AC23: =IF(B23="",0,IF(B23<AnnivRegul,0,IF(OR(I23="Accueil",I23="Férié travaillé (+10 %)",I23="1er mai travaillé"),MIN(K23,J23),IF(OR(I23="Absence enfant – payée",I23="Férié chômé payé"),Q23,0)))) | AD23: =IF(I23="Maladie enfant – retenue",1,0)
B24: =IF(7<=$AB$3,$AB$2+7-1,"") | C24: =IF(B24="","",CHOOSE(WEEKDAY(B24,2),"lun","mar","mer","jeu","ven","sam","dim")) | I24: =IF(B24="","",IF(R24=0,"Hors contrat",IF(D24<>"",D24,IF(U24=1,IF(T24=1,IF(AND(DAY(B24)=1,MONTH(B24)=5),"1er mai travaillé","Férié travaillé (+10 %)"),"Accueil"),IF(S24=1,IF(OR(WEEKDAY(B24,2)=7,T24=1),IF(AND(T24=1,Q24>0),"Férié chômé payé","Repos"),"Congé payé assmat"),IF(S24=4,IF(Q24>0,"Congé sans solde assmat","Repos"),IF(Q24=0,"Repos",IF(S24=2,"Semaine non programmée",IF(S24=3,"Absence enfant – payée",IF(T24=1,"Férié chômé payé","Accueil")))))))))) | J24: =IF(OR(I24="Accueil",I24="Férié travaillé (+10 %)",I24="1er mai travaillé"),IF(OR(S24=1,S24=2),0,Q24),0) | K24: =IF(OR(I24="Accueil",I24="Férié travaillé (+10 %)",I24="1er mai travaillé"),IF(U24=1,ROUND(MOD(F24-E24,1)*24,2),J24),0) | L24: =IF(OR(I24="Maladie enfant – retenue",I24="Absence assmat – non payée",I24="Congé sans solde assmat",I24="Hors contrat"),Q24,0) | M24: =IF(K24>0,ROUND(MAX(PlancherEnt,Entretien9h/9*K24),2),0) | P24: =IF(B24="","",B24-WEEKDAY(B24,2)+1) | Q24: =IF(B24="",0,INDEX(PlanH,WEEKDAY(B24,2))) | R24: =IF(B24="",0,IF(AND(OR(DateDebut="",B24>=DateDebut),OR(DateFin="",B24<=DateFin)),1,0)) | S24: =IF(B24="",0,SUMPRODUCT((PerDu<=B24)*(PerAu>=B24)*PerCode)) | T24: =IF(B24="",0,IF(COUNTIF(FeriesEff,B24)>0,1,0)) | U24: =IF(AND(E24<>"",F24<>""),1,0) | V24: =MAX(0,K24-J24) | W24: =IF(L24>0,1,0) | X24: =IF(Q24>0,1,0) | Y24: =IF(FournitRepas="L'assistante maternelle",IF(G24<>"",G24,IF(K24>0,RepasParJour,0)),0) | Z24: =IF(I24="Congé payé assmat",IF(AND(WEEKDAY(B24,2)<=6,T24=0),1,0),0) | AA24: =IF(I24="Férié travaillé (+10 %)",K24*MajFerie,IF(I24="1er mai travaillé",K24,0)) | AC24: =IF(B24="",0,IF(B24<AnnivRegul,0,IF(OR(I24="Accueil",I24="Férié travaillé (+10 %)",I24="1er mai travaillé"),MIN(K24,J24),IF(OR(I24="Absence enfant – payée",I24="Férié chômé payé"),Q24,0)))) | AD24: =IF(I24="Maladie enfant – retenue",1,0)
B25: =IF(8<=$AB$3,$AB$2+8-1,"") | C25: =IF(B25="","",CHOOSE(WEEKDAY(B25,2),"lun","mar","mer","jeu","ven","sam","dim")) | I25: =IF(B25="","",IF(R25=0,"Hors contrat",IF(D25<>"",D25,IF(U25=1,IF(T25=1,IF(AND(DAY(B25)=1,MONTH(B25)=5),"1er mai travaillé","Férié travaillé (+10 %)"),"Accueil"),IF(S25=1,IF(OR(WEEKDAY(B25,2)=7,T25=1),IF(AND(T25=1,Q25>0),"Férié chômé payé","Repos"),"Congé payé assmat"),IF(S25=4,IF(Q25>0,"Congé sans solde assmat","Repos"),IF(Q25=0,"Repos",IF(S25=2,"Semaine non programmée",IF(S25=3,"Absence enfant – payée",IF(T25=1,"Férié chômé payé","Accueil")))))))))) | J25: =IF(OR(I25="Accueil",I25="Férié travaillé (+10 %)",I25="1er mai travaillé"),IF(OR(S25=1,S25=2),0,Q25),0) | K25: =IF(OR(I25="Accueil",I25="Férié travaillé (+10 %)",I25="1er mai travaillé"),IF(U25=1,ROUND(MOD(F25-E25,1)*24,2),J25),0) | L25: =IF(OR(I25="Maladie enfant – retenue",I25="Absence assmat – non payée",I25="Congé sans solde assmat",I25="Hors contrat"),Q25,0) | M25: =IF(K25>0,ROUND(MAX(PlancherEnt,Entretien9h/9*K25),2),0) | P25: =IF(B25="","",B25-WEEKDAY(B25,2)+1) | Q25: =IF(B25="",0,INDEX(PlanH,WEEKDAY(B25,2))) | R25: =IF(B25="",0,IF(AND(OR(DateDebut="",B25>=DateDebut),OR(DateFin="",B25<=DateFin)),1,0)) | S25: =IF(B25="",0,SUMPRODUCT((PerDu<=B25)*(PerAu>=B25)*PerCode)) | T25: =IF(B25="",0,IF(COUNTIF(FeriesEff,B25)>0,1,0)) | U25: =IF(AND(E25<>"",F25<>""),1,0) | V25: =MAX(0,K25-J25) | W25: =IF(L25>0,1,0) | X25: =IF(Q25>0,1,0) | Y25: =IF(FournitRepas="L'assistante maternelle",IF(G25<>"",G25,IF(K25>0,RepasParJour,0)),0) | Z25: =IF(I25="Congé payé assmat",IF(AND(WEEKDAY(B25,2)<=6,T25=0),1,0),0) | AA25: =IF(I25="Férié travaillé (+10 %)",K25*MajFerie,IF(I25="1er mai travaillé",K25,0)) | AC25: =IF(B25="",0,IF(B25<AnnivRegul,0,IF(OR(I25="Accueil",I25="Férié travaillé (+10 %)",I25="1er mai travaillé"),MIN(K25,J25),IF(OR(I25="Absence enfant – payée",I25="Férié chômé payé"),Q25,0)))) | AD25: =IF(I25="Maladie enfant – retenue",1,0)
B26: =IF(9<=$AB$3,$AB$2+9-1,"") | C26: =IF(B26="","",CHOOSE(WEEKDAY(B26,2),"lun","mar","mer","jeu","ven","sam","dim")) | I26: =IF(B26="","",IF(R26=0,"Hors contrat",IF(D26<>"",D26,IF(U26=1,IF(T26=1,IF(AND(DAY(B26)=1,MONTH(B26)=5),"1er mai travaillé","Férié travaillé (+10 %)"),"Accueil"),IF(S26=1,IF(OR(WEEKDAY(B26,2)=7,T26=1),IF(AND(T26=1,Q26>0),"Férié chômé payé","Repos"),"Congé payé assmat"),IF(S26=4,IF(Q26>0,"Congé sans solde assmat","Repos"),IF(Q26=0,"Repos",IF(S26=2,"Semaine non programmée",IF(S26=3,"Absence enfant – payée",IF(T26=1,"Férié chômé payé","Accueil")))))))))) | J26: =IF(OR(I26="Accueil",I26="Férié travaillé (+10 %)",I26="1er mai travaillé"),IF(OR(S26=1,S26=2),0,Q26),0) | K26: =IF(OR(I26="Accueil",I26="Férié travaillé (+10 %)",I26="1er mai travaillé"),IF(U26=1,ROUND(MOD(F26-E26,1)*24,2),J26),0) | L26: =IF(OR(I26="Maladie enfant – retenue",I26="Absence assmat – non payée",I26="Congé sans solde assmat",I26="Hors contrat"),Q26,0) | M26: =IF(K26>0,ROUND(MAX(PlancherEnt,Entretien9h/9*K26),2),0) | P26: =IF(B26="","",B26-WEEKDAY(B26,2)+1) | Q26: =IF(B26="",0,INDEX(PlanH,WEEKDAY(B26,2))) | R26: =IF(B26="",0,IF(AND(OR(DateDebut="",B26>=DateDebut),OR(DateFin="",B26<=DateFin)),1,0)) | S26: =IF(B26="",0,SUMPRODUCT((PerDu<=B26)*(PerAu>=B26)*PerCode)) | T26: =IF(B26="",0,IF(COUNTIF(FeriesEff,B26)>0,1,0)) | U26: =IF(AND(E26<>"",F26<>""),1,0) | V26: =MAX(0,K26-J26) | W26: =IF(L26>0,1,0) | X26: =IF(Q26>0,1,0) | Y26: =IF(FournitRepas="L'assistante maternelle",IF(G26<>"",G26,IF(K26>0,RepasParJour,0)),0) | Z26: =IF(I26="Congé payé assmat",IF(AND(WEEKDAY(B26,2)<=6,T26=0),1,0),0) | AA26: =IF(I26="Férié travaillé (+10 %)",K26*MajFerie,IF(I26="1er mai travaillé",K26,0)) | AC26: =IF(B26="",0,IF(B26<AnnivRegul,0,IF(OR(I26="Accueil",I26="Férié travaillé (+10 %)",I26="1er mai travaillé"),MIN(K26,J26),IF(OR(I26="Absence enfant – payée",I26="Férié chômé payé"),Q26,0)))) | AD26: =IF(I26="Maladie enfant – retenue",1,0)
B27: =IF(10<=$AB$3,$AB$2+10-1,"") | C27: =IF(B27="","",CHOOSE(WEEKDAY(B27,2),"lun","mar","mer","jeu","ven","sam","dim")) | I27: =IF(B27="","",IF(R27=0,"Hors contrat",IF(D27<>"",D27,IF(U27=1,IF(T27=1,IF(AND(DAY(B27)=1,MONTH(B27)=5),"1er mai travaillé","Férié travaillé (+10 %)"),"Accueil"),IF(S27=1,IF(OR(WEEKDAY(B27,2)=7,T27=1),IF(AND(T27=1,Q27>0),"Férié chômé payé","Repos"),"Congé payé assmat"),IF(S27=4,IF(Q27>0,"Congé sans solde assmat","Repos"),IF(Q27=0,"Repos",IF(S27=2,"Semaine non programmée",IF(S27=3,"Absence enfant – payée",IF(T27=1,"Férié chômé payé","Accueil")))))))))) | J27: =IF(OR(I27="Accueil",I27="Férié travaillé (+10 %)",I27="1er mai travaillé"),IF(OR(S27=1,S27=2),0,Q27),0) | K27: =IF(OR(I27="Accueil",I27="Férié travaillé (+10 %)",I27="1er mai travaillé"),IF(U27=1,ROUND(MOD(F27-E27,1)*24,2),J27),0) | L27: =IF(OR(I27="Maladie enfant – retenue",I27="Absence assmat – non payée",I27="Congé sans solde assmat",I27="Hors contrat"),Q27,0) | M27: =IF(K27>0,ROUND(MAX(PlancherEnt,Entretien9h/9*K27),2),0) | P27: =IF(B27="","",B27-WEEKDAY(B27,2)+1) | Q27: =IF(B27="",0,INDEX(PlanH,WEEKDAY(B27,2))) | R27: =IF(B27="",0,IF(AND(OR(DateDebut="",B27>=DateDebut),OR(DateFin="",B27<=DateFin)),1,0)) | S27: =IF(B27="",0,SUMPRODUCT((PerDu<=B27)*(PerAu>=B27)*PerCode)) | T27: =IF(B27="",0,IF(COUNTIF(FeriesEff,B27)>0,1,0)) | U27: =IF(AND(E27<>"",F27<>""),1,0) | V27: =MAX(0,K27-J27) | W27: =IF(L27>0,1,0) | X27: =IF(Q27>0,1,0) | Y27: =IF(FournitRepas="L'assistante maternelle",IF(G27<>"",G27,IF(K27>0,RepasParJour,0)),0) | Z27: =IF(I27="Congé payé assmat",IF(AND(WEEKDAY(B27,2)<=6,T27=0),1,0),0) | AA27: =IF(I27="Férié travaillé (+10 %)",K27*MajFerie,IF(I27="1er mai travaillé",K27,0)) | AC27: =IF(B27="",0,IF(B27<AnnivRegul,0,IF(OR(I27="Accueil",I27="Férié travaillé (+10 %)",I27="1er mai travaillé"),MIN(K27,J27),IF(OR(I27="Absence enfant – payée",I27="Férié chômé payé"),Q27,0)))) | AD27: =IF(I27="Maladie enfant – retenue",1,0)
B28: =IF(11<=$AB$3,$AB$2+11-1,"") | C28: =IF(B28="","",CHOOSE(WEEKDAY(B28,2),"lun","mar","mer","jeu","ven","sam","dim")) | I28: =IF(B28="","",IF(R28=0,"Hors contrat",IF(D28<>"",D28,IF(U28=1,IF(T28=1,IF(AND(DAY(B28)=1,MONTH(B28)=5),"1er mai travaillé","Férié travaillé (+10 %)"),"Accueil"),IF(S28=1,IF(OR(WEEKDAY(B28,2)=7,T28=1),IF(AND(T28=1,Q28>0),"Férié chômé payé","Repos"),"Congé payé assmat"),IF(S28=4,IF(Q28>0,"Congé sans solde assmat","Repos"),IF(Q28=0,"Repos",IF(S28=2,"Semaine non programmée",IF(S28=3,"Absence enfant – payée",IF(T28=1,"Férié chômé payé","Accueil")))))))))) | J28: =IF(OR(I28="Accueil",I28="Férié travaillé (+10 %)",I28="1er mai travaillé"),IF(OR(S28=1,S28=2),0,Q28),0) | K28: =IF(OR(I28="Accueil",I28="Férié travaillé (+10 %)",I28="1er mai travaillé"),IF(U28=1,ROUND(MOD(F28-E28,1)*24,2),J28),0) | L28: =IF(OR(I28="Maladie enfant – retenue",I28="Absence assmat – non payée",I28="Congé sans solde assmat",I28="Hors contrat"),Q28,0) | M28: =IF(K28>0,ROUND(MAX(PlancherEnt,Entretien9h/9*K28),2),0) | P28: =IF(B28="","",B28-WEEKDAY(B28,2)+1) | Q28: =IF(B28="",0,INDEX(PlanH,WEEKDAY(B28,2))) | R28: =IF(B28="",0,IF(AND(OR(DateDebut="",B28>=DateDebut),OR(DateFin="",B28<=DateFin)),1,0)) | S28: =IF(B28="",0,SUMPRODUCT((PerDu<=B28)*(PerAu>=B28)*PerCode)) | T28: =IF(B28="",0,IF(COUNTIF(FeriesEff,B28)>0,1,0)) | U28: =IF(AND(E28<>"",F28<>""),1,0) | V28: =MAX(0,K28-J28) | W28: =IF(L28>0,1,0) | X28: =IF(Q28>0,1,0) | Y28: =IF(FournitRepas="L'assistante maternelle",IF(G28<>"",G28,IF(K28>0,RepasParJour,0)),0) | Z28: =IF(I28="Congé payé assmat",IF(AND(WEEKDAY(B28,2)<=6,T28=0),1,0),0) | AA28: =IF(I28="Férié travaillé (+10 %)",K28*MajFerie,IF(I28="1er mai travaillé",K28,0)) | AC28: =IF(B28="",0,IF(B28<AnnivRegul,0,IF(OR(I28="Accueil",I28="Férié travaillé (+10 %)",I28="1er mai travaillé"),MIN(K28,J28),IF(OR(I28="Absence enfant – payée",I28="Férié chômé payé"),Q28,0)))) | AD28: =IF(I28="Maladie enfant – retenue",1,0)
B29: =IF(12<=$AB$3,$AB$2+12-1,"") | C29: =IF(B29="","",CHOOSE(WEEKDAY(B29,2),"lun","mar","mer","jeu","ven","sam","dim")) | I29: =IF(B29="","",IF(R29=0,"Hors contrat",IF(D29<>"",D29,IF(U29=1,IF(T29=1,IF(AND(DAY(B29)=1,MONTH(B29)=5),"1er mai travaillé","Férié travaillé (+10 %)"),"Accueil"),IF(S29=1,IF(OR(WEEKDAY(B29,2)=7,T29=1),IF(AND(T29=1,Q29>0),"Férié chômé payé","Repos"),"Congé payé assmat"),IF(S29=4,IF(Q29>0,"Congé sans solde assmat","Repos"),IF(Q29=0,"Repos",IF(S29=2,"Semaine non programmée",IF(S29=3,"Absence enfant – payée",IF(T29=1,"Férié chômé payé","Accueil")))))))))) | J29: =IF(OR(I29="Accueil",I29="Férié travaillé (+10 %)",I29="1er mai travaillé"),IF(OR(S29=1,S29=2),0,Q29),0) | K29: =IF(OR(I29="Accueil",I29="Férié travaillé (+10 %)",I29="1er mai travaillé"),IF(U29=1,ROUND(MOD(F29-E29,1)*24,2),J29),0) | L29: =IF(OR(I29="Maladie enfant – retenue",I29="Absence assmat – non payée",I29="Congé sans solde assmat",I29="Hors contrat"),Q29,0) | M29: =IF(K29>0,ROUND(MAX(PlancherEnt,Entretien9h/9*K29),2),0) | P29: =IF(B29="","",B29-WEEKDAY(B29,2)+1) | Q29: =IF(B29="",0,INDEX(PlanH,WEEKDAY(B29,2))) | R29: =IF(B29="",0,IF(AND(OR(DateDebut="",B29>=DateDebut),OR(DateFin="",B29<=DateFin)),1,0)) | S29: =IF(B29="",0,SUMPRODUCT((PerDu<=B29)*(PerAu>=B29)*PerCode)) | T29: =IF(B29="",0,IF(COUNTIF(FeriesEff,B29)>0,1,0)) | U29: =IF(AND(E29<>"",F29<>""),1,0) | V29: =MAX(0,K29-J29) | W29: =IF(L29>0,1,0) | X29: =IF(Q29>0,1,0) | Y29: =IF(FournitRepas="L'assistante maternelle",IF(G29<>"",G29,IF(K29>0,RepasParJour,0)),0) | Z29: =IF(I29="Congé payé assmat",IF(AND(WEEKDAY(B29,2)<=6,T29=0),1,0),0) | AA29: =IF(I29="Férié travaillé (+10 %)",K29*MajFerie,IF(I29="1er mai travaillé",K29,0)) | AC29: =IF(B29="",0,IF(B29<AnnivRegul,0,IF(OR(I29="Accueil",I29="Férié travaillé (+10 %)",I29="1er mai travaillé"),MIN(K29,J29),IF(OR(I29="Absence enfant – payée",I29="Férié chômé payé"),Q29,0)))) | AD29: =IF(I29="Maladie enfant – retenue",1,0)
B30: =IF(13<=$AB$3,$AB$2+13-1,"") | C30: =IF(B30="","",CHOOSE(WEEKDAY(B30,2),"lun","mar","mer","jeu","ven","sam","dim")) | I30: =IF(B30="","",IF(R30=0,"Hors contrat",IF(D30<>"",D30,IF(U30=1,IF(T30=1,IF(AND(DAY(B30)=1,MONTH(B30)=5),"1er mai travaillé","Férié travaillé (+10 %)"),"Accueil"),IF(S30=1,IF(OR(WEEKDAY(B30,2)=7,T30=1),IF(AND(T30=1,Q30>0),"Férié chômé payé","Repos"),"Congé payé assmat"),IF(S30=4,IF(Q30>0,"Congé sans solde assmat","Repos"),IF(Q30=0,"Repos",IF(S30=2,"Semaine non programmée",IF(S30=3,"Absence enfant – payée",IF(T30=1,"Férié chômé payé","Accueil")))))))))) | J30: =IF(OR(I30="Accueil",I30="Férié travaillé (+10 %)",I30="1er mai travaillé"),IF(OR(S30=1,S30=2),0,Q30),0) | K30: =IF(OR(I30="Accueil",I30="Férié travaillé (+10 %)",I30="1er mai travaillé"),IF(U30=1,ROUND(MOD(F30-E30,1)*24,2),J30),0) | L30: =IF(OR(I30="Maladie enfant – retenue",I30="Absence assmat – non payée",I30="Congé sans solde assmat",I30="Hors contrat"),Q30,0) | M30: =IF(K30>0,ROUND(MAX(PlancherEnt,Entretien9h/9*K30),2),0) | P30: =IF(B30="","",B30-WEEKDAY(B30,2)+1) | Q30: =IF(B30="",0,INDEX(PlanH,WEEKDAY(B30,2))) | R30: =IF(B30="",0,IF(AND(OR(DateDebut="",B30>=DateDebut),OR(DateFin="",B30<=DateFin)),1,0)) | S30: =IF(B30="",0,SUMPRODUCT((PerDu<=B30)*(PerAu>=B30)*PerCode)) | T30: =IF(B30="",0,IF(COUNTIF(FeriesEff,B30)>0,1,0)) | U30: =IF(AND(E30<>"",F30<>""),1,0) | V30: =MAX(0,K30-J30) | W30: =IF(L30>0,1,0) | X30: =IF(Q30>0,1,0) | Y30: =IF(FournitRepas="L'assistante maternelle",IF(G30<>"",G30,IF(K30>0,RepasParJour,0)),0) | Z30: =IF(I30="Congé payé assmat",IF(AND(WEEKDAY(B30,2)<=6,T30=0),1,0),0) | AA30: =IF(I30="Férié travaillé (+10 %)",K30*MajFerie,IF(I30="1er mai travaillé",K30,0)) | AC30: =IF(B30="",0,IF(B30<AnnivRegul,0,IF(OR(I30="Accueil",I30="Férié travaillé (+10 %)",I30="1er mai travaillé"),MIN(K30,J30),IF(OR(I30="Absence enfant – payée",I30="Férié chômé payé"),Q30,0)))) | AD30: =IF(I30="Maladie enfant – retenue",1,0)
B31: =IF(14<=$AB$3,$AB$2+14-1,"") | C31: =IF(B31="","",CHOOSE(WEEKDAY(B31,2),"lun","mar","mer","jeu","ven","sam","dim")) | I31: =IF(B31="","",IF(R31=0,"Hors contrat",IF(D31<>"",D31,IF(U31=1,IF(T31=1,IF(AND(DAY(B31)=1,MONTH(B31)=5),"1er mai travaillé","Férié travaillé (+10 %)"),"Accueil"),IF(S31=1,IF(OR(WEEKDAY(B31,2)=7,T31=1),IF(AND(T31=1,Q31>0),"Férié chômé payé","Repos"),"Congé payé assmat"),IF(S31=4,IF(Q31>0,"Congé sans solde assmat","Repos"),IF(Q31=0,"Repos",IF(S31=2,"Semaine non programmée",IF(S31=3,"Absence enfant – payée",IF(T31=1,"Férié chômé payé","Accueil")))))))))) | J31: =IF(OR(I31="Accueil",I31="Férié travaillé (+10 %)",I31="1er mai travaillé"),IF(OR(S31=1,S31=2),0,Q31),0) | K31: =IF(OR(I31="Accueil",I31="Férié travaillé (+10 %)",I31="1er mai travaillé"),IF(U31=1,ROUND(MOD(F31-E31,1)*24,2),J31),0) | L31: =IF(OR(I31="Maladie enfant – retenue",I31="Absence assmat – non payée",I31="Congé sans solde assmat",I31="Hors contrat"),Q31,0) | M31: =IF(K31>0,ROUND(MAX(PlancherEnt,Entretien9h/9*K31),2),0) | P31: =IF(B31="","",B31-WEEKDAY(B31,2)+1) | Q31: =IF(B31="",0,INDEX(PlanH,WEEKDAY(B31,2))) | R31: =IF(B31="",0,IF(AND(OR(DateDebut="",B31>=DateDebut),OR(DateFin="",B31<=DateFin)),1,0)) | S31: =IF(B31="",0,SUMPRODUCT((PerDu<=B31)*(PerAu>=B31)*PerCode)) | T31: =IF(B31="",0,IF(COUNTIF(FeriesEff,B31)>0,1,0)) | U31: =IF(AND(E31<>"",F31<>""),1,0) | V31: =MAX(0,K31-J31) | W31: =IF(L31>0,1,0) | X31: =IF(Q31>0,1,0) | Y31: =IF(FournitRepas="L'assistante maternelle",IF(G31<>"",G31,IF(K31>0,RepasParJour,0)),0) | Z31: =IF(I31="Congé payé assmat",IF(AND(WEEKDAY(B31,2)<=6,T31=0),1,0),0) | AA31: =IF(I31="Férié travaillé (+10 %)",K31*MajFerie,IF(I31="1er mai travaillé",K31,0)) | AC31: =IF(B31="",0,IF(B31<AnnivRegul,0,IF(OR(I31="Accueil",I31="Férié travaillé (+10 %)",I31="1er mai travaillé"),MIN(K31,J31),IF(OR(I31="Absence enfant – payée",I31="Férié chômé payé"),Q31,0)))) | AD31: =IF(I31="Maladie enfant – retenue",1,0)
B32: =IF(15<=$AB$3,$AB$2+15-1,"") | C32: =IF(B32="","",CHOOSE(WEEKDAY(B32,2),"lun","mar","mer","jeu","ven","sam","dim")) | I32: =IF(B32="","",IF(R32=0,"Hors contrat",IF(D32<>"",D32,IF(U32=1,IF(T32=1,IF(AND(DAY(B32)=1,MONTH(B32)=5),"1er mai travaillé","Férié travaillé (+10 %)"),"Accueil"),IF(S32=1,IF(OR(WEEKDAY(B32,2)=7,T32=1),IF(AND(T32=1,Q32>0),"Férié chômé payé","Repos"),"Congé payé assmat"),IF(S32=4,IF(Q32>0,"Congé sans solde assmat","Repos"),IF(Q32=0,"Repos",IF(S32=2,"Semaine non programmée",IF(S32=3,"Absence enfant – payée",IF(T32=1,"Férié chômé payé","Accueil")))))))))) | J32: =IF(OR(I32="Accueil",I32="Férié travaillé (+10 %)",I32="1er mai travaillé"),IF(OR(S32=1,S32=2),0,Q32),0) | K32: =IF(OR(I32="Accueil",I32="Férié travaillé (+10 %)",I32="1er mai travaillé"),IF(U32=1,ROUND(MOD(F32-E32,1)*24,2),J32),0) | L32: =IF(OR(I32="Maladie enfant – retenue",I32="Absence assmat – non payée",I32="Congé sans solde assmat",I32="Hors contrat"),Q32,0) | M32: =IF(K32>0,ROUND(MAX(PlancherEnt,Entretien9h/9*K32),2),0) | P32: =IF(B32="","",B32-WEEKDAY(B32,2)+1) | Q32: =IF(B32="",0,INDEX(PlanH,WEEKDAY(B32,2))) | R32: =IF(B32="",0,IF(AND(OR(DateDebut="",B32>=DateDebut),OR(DateFin="",B32<=DateFin)),1,0)) | S32: =IF(B32="",0,SUMPRODUCT((PerDu<=B32)*(PerAu>=B32)*PerCode)) | T32: =IF(B32="",0,IF(COUNTIF(FeriesEff,B32)>0,1,0)) | U32: =IF(AND(E32<>"",F32<>""),1,0) | V32: =MAX(0,K32-J32) | W32: =IF(L32>0,1,0) | X32: =IF(Q32>0,1,0) | Y32: =IF(FournitRepas="L'assistante maternelle",IF(G32<>"",G32,IF(K32>0,RepasParJour,0)),0) | Z32: =IF(I32="Congé payé assmat",IF(AND(WEEKDAY(B32,2)<=6,T32=0),1,0),0) | AA32: =IF(I32="Férié travaillé (+10 %)",K32*MajFerie,IF(I32="1er mai travaillé",K32,0)) | AC32: =IF(B32="",0,IF(B32<AnnivRegul,0,IF(OR(I32="Accueil",I32="Férié travaillé (+10 %)",I32="1er mai travaillé"),MIN(K32,J32),IF(OR(I32="Absence enfant – payée",I32="Férié chômé payé"),Q32,0)))) | AD32: =IF(I32="Maladie enfant – retenue",1,0)
B33: =IF(16<=$AB$3,$AB$2+16-1,"") | C33: =IF(B33="","",CHOOSE(WEEKDAY(B33,2),"lun","mar","mer","jeu","ven","sam","dim")) | I33: =IF(B33="","",IF(R33=0,"Hors contrat",IF(D33<>"",D33,IF(U33=1,IF(T33=1,IF(AND(DAY(B33)=1,MONTH(B33)=5),"1er mai travaillé","Férié travaillé (+10 %)"),"Accueil"),IF(S33=1,IF(OR(WEEKDAY(B33,2)=7,T33=1),IF(AND(T33=1,Q33>0),"Férié chômé payé","Repos"),"Congé payé assmat"),IF(S33=4,IF(Q33>0,"Congé sans solde assmat","Repos"),IF(Q33=0,"Repos",IF(S33=2,"Semaine non programmée",IF(S33=3,"Absence enfant – payée",IF(T33=1,"Férié chômé payé","Accueil")))))))))) | J33: =IF(OR(I33="Accueil",I33="Férié travaillé (+10 %)",I33="1er mai travaillé"),IF(OR(S33=1,S33=2),0,Q33),0) | K33: =IF(OR(I33="Accueil",I33="Férié travaillé (+10 %)",I33="1er mai travaillé"),IF(U33=1,ROUND(MOD(F33-E33,1)*24,2),J33),0) | L33: =IF(OR(I33="Maladie enfant – retenue",I33="Absence assmat – non payée",I33="Congé sans solde assmat",I33="Hors contrat"),Q33,0) | M33: =IF(K33>0,ROUND(MAX(PlancherEnt,Entretien9h/9*K33),2),0) | P33: =IF(B33="","",B33-WEEKDAY(B33,2)+1) | Q33: =IF(B33="",0,INDEX(PlanH,WEEKDAY(B33,2))) | R33: =IF(B33="",0,IF(AND(OR(DateDebut="",B33>=DateDebut),OR(DateFin="",B33<=DateFin)),1,0)) | S33: =IF(B33="",0,SUMPRODUCT((PerDu<=B33)*(PerAu>=B33)*PerCode)) | T33: =IF(B33="",0,IF(COUNTIF(FeriesEff,B33)>0,1,0)) | U33: =IF(AND(E33<>"",F33<>""),1,0) | V33: =MAX(0,K33-J33) | W33: =IF(L33>0,1,0) | X33: =IF(Q33>0,1,0) | Y33: =IF(FournitRepas="L'assistante maternelle",IF(G33<>"",G33,IF(K33>0,RepasParJour,0)),0) | Z33: =IF(I33="Congé payé assmat",IF(AND(WEEKDAY(B33,2)<=6,T33=0),1,0),0) | AA33: =IF(I33="Férié travaillé (+10 %)",K33*MajFerie,IF(I33="1er mai travaillé",K33,0)) | AC33: =IF(B33="",0,IF(B33<AnnivRegul,0,IF(OR(I33="Accueil",I33="Férié travaillé (+10 %)",I33="1er mai travaillé"),MIN(K33,J33),IF(OR(I33="Absence enfant – payée",I33="Férié chômé payé"),Q33,0)))) | AD33: =IF(I33="Maladie enfant – retenue",1,0)
B34: =IF(17<=$AB$3,$AB$2+17-1,"") | C34: =IF(B34="","",CHOOSE(WEEKDAY(B34,2),"lun","mar","mer","jeu","ven","sam","dim")) | I34: =IF(B34="","",IF(R34=0,"Hors contrat",IF(D34<>"",D34,IF(U34=1,IF(T34=1,IF(AND(DAY(B34)=1,MONTH(B34)=5),"1er mai travaillé","Férié travaillé (+10 %)"),"Accueil"),IF(S34=1,IF(OR(WEEKDAY(B34,2)=7,T34=1),IF(AND(T34=1,Q34>0),"Férié chômé payé","Repos"),"Congé payé assmat"),IF(S34=4,IF(Q34>0,"Congé sans solde assmat","Repos"),IF(Q34=0,"Repos",IF(S34=2,"Semaine non programmée",IF(S34=3,"Absence enfant – payée",IF(T34=1,"Férié chômé payé","Accueil")))))))))) | J34: =IF(OR(I34="Accueil",I34="Férié travaillé (+10 %)",I34="1er mai travaillé"),IF(OR(S34=1,S34=2),0,Q34),0) | K34: =IF(OR(I34="Accueil",I34="Férié travaillé (+10 %)",I34="1er mai travaillé"),IF(U34=1,ROUND(MOD(F34-E34,1)*24,2),J34),0) | L34: =IF(OR(I34="Maladie enfant – retenue",I34="Absence assmat – non payée",I34="Congé sans solde assmat",I34="Hors contrat"),Q34,0) | M34: =IF(K34>0,ROUND(MAX(PlancherEnt,Entretien9h/9*K34),2),0) | P34: =IF(B34="","",B34-WEEKDAY(B34,2)+1) | Q34: =IF(B34="",0,INDEX(PlanH,WEEKDAY(B34,2))) | R34: =IF(B34="",0,IF(AND(OR(DateDebut="",B34>=DateDebut),OR(DateFin="",B34<=DateFin)),1,0)) | S34: =IF(B34="",0,SUMPRODUCT((PerDu<=B34)*(PerAu>=B34)*PerCode)) | T34: =IF(B34="",0,IF(COUNTIF(FeriesEff,B34)>0,1,0)) | U34: =IF(AND(E34<>"",F34<>""),1,0) | V34: =MAX(0,K34-J34) | W34: =IF(L34>0,1,0) | X34: =IF(Q34>0,1,0) | Y34: =IF(FournitRepas="L'assistante maternelle",IF(G34<>"",G34,IF(K34>0,RepasParJour,0)),0) | Z34: =IF(I34="Congé payé assmat",IF(AND(WEEKDAY(B34,2)<=6,T34=0),1,0),0) | AA34: =IF(I34="Férié travaillé (+10 %)",K34*MajFerie,IF(I34="1er mai travaillé",K34,0)) | AC34: =IF(B34="",0,IF(B34<AnnivRegul,0,IF(OR(I34="Accueil",I34="Férié travaillé (+10 %)",I34="1er mai travaillé"),MIN(K34,J34),IF(OR(I34="Absence enfant – payée",I34="Férié chômé payé"),Q34,0)))) | AD34: =IF(I34="Maladie enfant – retenue",1,0)
B35: =IF(18<=$AB$3,$AB$2+18-1,"") | C35: =IF(B35="","",CHOOSE(WEEKDAY(B35,2),"lun","mar","mer","jeu","ven","sam","dim")) | I35: =IF(B35="","",IF(R35=0,"Hors contrat",IF(D35<>"",D35,IF(U35=1,IF(T35=1,IF(AND(DAY(B35)=1,MONTH(B35)=5),"1er mai travaillé","Férié travaillé (+10 %)"),"Accueil"),IF(S35=1,IF(OR(WEEKDAY(B35,2)=7,T35=1),IF(AND(T35=1,Q35>0),"Férié chômé payé","Repos"),"Congé payé assmat"),IF(S35=4,IF(Q35>0,"Congé sans solde assmat","Repos"),IF(Q35=0,"Repos",IF(S35=2,"Semaine non programmée",IF(S35=3,"Absence enfant – payée",IF(T35=1,"Férié chômé payé","Accueil")))))))))) | J35: =IF(OR(I35="Accueil",I35="Férié travaillé (+10 %)",I35="1er mai travaillé"),IF(OR(S35=1,S35=2),0,Q35),0) | K35: =IF(OR(I35="Accueil",I35="Férié travaillé (+10 %)",I35="1er mai travaillé"),IF(U35=1,ROUND(MOD(F35-E35,1)*24,2),J35),0) | L35: =IF(OR(I35="Maladie enfant – retenue",I35="Absence assmat – non payée",I35="Congé sans solde assmat",I35="Hors contrat"),Q35,0) | M35: =IF(K35>0,ROUND(MAX(PlancherEnt,Entretien9h/9*K35),2),0) | P35: =IF(B35="","",B35-WEEKDAY(B35,2)+1) | Q35: =IF(B35="",0,INDEX(PlanH,WEEKDAY(B35,2))) | R35: =IF(B35="",0,IF(AND(OR(DateDebut="",B35>=DateDebut),OR(DateFin="",B35<=DateFin)),1,0)) | S35: =IF(B35="",0,SUMPRODUCT((PerDu<=B35)*(PerAu>=B35)*PerCode)) | T35: =IF(B35="",0,IF(COUNTIF(FeriesEff,B35)>0,1,0)) | U35: =IF(AND(E35<>"",F35<>""),1,0) | V35: =MAX(0,K35-J35) | W35: =IF(L35>0,1,0) | X35: =IF(Q35>0,1,0) | Y35: =IF(FournitRepas="L'assistante maternelle",IF(G35<>"",G35,IF(K35>0,RepasParJour,0)),0) | Z35: =IF(I35="Congé payé assmat",IF(AND(WEEKDAY(B35,2)<=6,T35=0),1,0),0) | AA35: =IF(I35="Férié travaillé (+10 %)",K35*MajFerie,IF(I35="1er mai travaillé",K35,0)) | AC35: =IF(B35="",0,IF(B35<AnnivRegul,0,IF(OR(I35="Accueil",I35="Férié travaillé (+10 %)",I35="1er mai travaillé"),MIN(K35,J35),IF(OR(I35="Absence enfant – payée",I35="Férié chômé payé"),Q35,0)))) | AD35: =IF(I35="Maladie enfant – retenue",1,0)
B36: =IF(19<=$AB$3,$AB$2+19-1,"") | C36: =IF(B36="","",CHOOSE(WEEKDAY(B36,2),"lun","mar","mer","jeu","ven","sam","dim")) | I36: =IF(B36="","",IF(R36=0,"Hors contrat",IF(D36<>"",D36,IF(U36=1,IF(T36=1,IF(AND(DAY(B36)=1,MONTH(B36)=5),"1er mai travaillé","Férié travaillé (+10 %)"),"Accueil"),IF(S36=1,IF(OR(WEEKDAY(B36,2)=7,T36=1),IF(AND(T36=1,Q36>0),"Férié chômé payé","Repos"),"Congé payé assmat"),IF(S36=4,IF(Q36>0,"Congé sans solde assmat","Repos"),IF(Q36=0,"Repos",IF(S36=2,"Semaine non programmée",IF(S36=3,"Absence enfant – payée",IF(T36=1,"Férié chômé payé","Accueil")))))))))) | J36: =IF(OR(I36="Accueil",I36="Férié travaillé (+10 %)",I36="1er mai travaillé"),IF(OR(S36=1,S36=2),0,Q36),0) | K36: =IF(OR(I36="Accueil",I36="Férié travaillé (+10 %)",I36="1er mai travaillé"),IF(U36=1,ROUND(MOD(F36-E36,1)*24,2),J36),0) | L36: =IF(OR(I36="Maladie enfant – retenue",I36="Absence assmat – non payée",I36="Congé sans solde assmat",I36="Hors contrat"),Q36,0) | M36: =IF(K36>0,ROUND(MAX(PlancherEnt,Entretien9h/9*K36),2),0) | P36: =IF(B36="","",B36-WEEKDAY(B36,2)+1) | Q36: =IF(B36="",0,INDEX(PlanH,WEEKDAY(B36,2))) | R36: =IF(B36="",0,IF(AND(OR(DateDebut="",B36>=DateDebut),OR(DateFin="",B36<=DateFin)),1,0)) | S36: =IF(B36="",0,SUMPRODUCT((PerDu<=B36)*(PerAu>=B36)*PerCode)) | T36: =IF(B36="",0,IF(COUNTIF(FeriesEff,B36)>0,1,0)) | U36: =IF(AND(E36<>"",F36<>""),1,0) | V36: =MAX(0,K36-J36) | W36: =IF(L36>0,1,0) | X36: =IF(Q36>0,1,0) | Y36: =IF(FournitRepas="L'assistante maternelle",IF(G36<>"",G36,IF(K36>0,RepasParJour,0)),0) | Z36: =IF(I36="Congé payé assmat",IF(AND(WEEKDAY(B36,2)<=6,T36=0),1,0),0) | AA36: =IF(I36="Férié travaillé (+10 %)",K36*MajFerie,IF(I36="1er mai travaillé",K36,0)) | AC36: =IF(B36="",0,IF(B36<AnnivRegul,0,IF(OR(I36="Accueil",I36="Férié travaillé (+10 %)",I36="1er mai travaillé"),MIN(K36,J36),IF(OR(I36="Absence enfant – payée",I36="Férié chômé payé"),Q36,0)))) | AD36: =IF(I36="Maladie enfant – retenue",1,0)
B37: =IF(20<=$AB$3,$AB$2+20-1,"") | C37: =IF(B37="","",CHOOSE(WEEKDAY(B37,2),"lun","mar","mer","jeu","ven","sam","dim")) | I37: =IF(B37="","",IF(R37=0,"Hors contrat",IF(D37<>"",D37,IF(U37=1,IF(T37=1,IF(AND(DAY(B37)=1,MONTH(B37)=5),"1er mai travaillé","Férié travaillé (+10 %)"),"Accueil"),IF(S37=1,IF(OR(WEEKDAY(B37,2)=7,T37=1),IF(AND(T37=1,Q37>0),"Férié chômé payé","Repos"),"Congé payé assmat"),IF(S37=4,IF(Q37>0,"Congé sans solde assmat","Repos"),IF(Q37=0,"Repos",IF(S37=2,"Semaine non programmée",IF(S37=3,"Absence enfant – payée",IF(T37=1,"Férié chômé payé","Accueil")))))))))) | J37: =IF(OR(I37="Accueil",I37="Férié travaillé (+10 %)",I37="1er mai travaillé"),IF(OR(S37=1,S37=2),0,Q37),0) | K37: =IF(OR(I37="Accueil",I37="Férié travaillé (+10 %)",I37="1er mai travaillé"),IF(U37=1,ROUND(MOD(F37-E37,1)*24,2),J37),0) | L37: =IF(OR(I37="Maladie enfant – retenue",I37="Absence assmat – non payée",I37="Congé sans solde assmat",I37="Hors contrat"),Q37,0) | M37: =IF(K37>0,ROUND(MAX(PlancherEnt,Entretien9h/9*K37),2),0) | P37: =IF(B37="","",B37-WEEKDAY(B37,2)+1) | Q37: =IF(B37="",0,INDEX(PlanH,WEEKDAY(B37,2))) | R37: =IF(B37="",0,IF(AND(OR(DateDebut="",B37>=DateDebut),OR(DateFin="",B37<=DateFin)),1,0)) | S37: =IF(B37="",0,SUMPRODUCT((PerDu<=B37)*(PerAu>=B37)*PerCode)) | T37: =IF(B37="",0,IF(COUNTIF(FeriesEff,B37)>0,1,0)) | U37: =IF(AND(E37<>"",F37<>""),1,0) | V37: =MAX(0,K37-J37) | W37: =IF(L37>0,1,0) | X37: =IF(Q37>0,1,0) | Y37: =IF(FournitRepas="L'assistante maternelle",IF(G37<>"",G37,IF(K37>0,RepasParJour,0)),0) | Z37: =IF(I37="Congé payé assmat",IF(AND(WEEKDAY(B37,2)<=6,T37=0),1,0),0) | AA37: =IF(I37="Férié travaillé (+10 %)",K37*MajFerie,IF(I37="1er mai travaillé",K37,0)) | AC37: =IF(B37="",0,IF(B37<AnnivRegul,0,IF(OR(I37="Accueil",I37="Férié travaillé (+10 %)",I37="1er mai travaillé"),MIN(K37,J37),IF(OR(I37="Absence enfant – payée",I37="Férié chômé payé"),Q37,0)))) | AD37: =IF(I37="Maladie enfant – retenue",1,0)
B38: =IF(21<=$AB$3,$AB$2+21-1,"") | C38: =IF(B38="","",CHOOSE(WEEKDAY(B38,2),"lun","mar","mer","jeu","ven","sam","dim")) | I38: =IF(B38="","",IF(R38=0,"Hors contrat",IF(D38<>"",D38,IF(U38=1,IF(T38=1,IF(AND(DAY(B38)=1,MONTH(B38)=5),"1er mai travaillé","Férié travaillé (+10 %)"),"Accueil"),IF(S38=1,IF(OR(WEEKDAY(B38,2)=7,T38=1),IF(AND(T38=1,Q38>0),"Férié chômé payé","Repos"),"Congé payé assmat"),IF(S38=4,IF(Q38>0,"Congé sans solde assmat","Repos"),IF(Q38=0,"Repos",IF(S38=2,"Semaine non programmée",IF(S38=3,"Absence enfant – payée",IF(T38=1,"Férié chômé payé","Accueil")))))))))) | J38: =IF(OR(I38="Accueil",I38="Férié travaillé (+10 %)",I38="1er mai travaillé"),IF(OR(S38=1,S38=2),0,Q38),0) | K38: =IF(OR(I38="Accueil",I38="Férié travaillé (+10 %)",I38="1er mai travaillé"),IF(U38=1,ROUND(MOD(F38-E38,1)*24,2),J38),0) | L38: =IF(OR(I38="Maladie enfant – retenue",I38="Absence assmat – non payée",I38="Congé sans solde assmat",I38="Hors contrat"),Q38,0) | M38: =IF(K38>0,ROUND(MAX(PlancherEnt,Entretien9h/9*K38),2),0) | P38: =IF(B38="","",B38-WEEKDAY(B38,2)+1) | Q38: =IF(B38="",0,INDEX(PlanH,WEEKDAY(B38,2))) | R38: =IF(B38="",0,IF(AND(OR(DateDebut="",B38>=DateDebut),OR(DateFin="",B38<=DateFin)),1,0)) | S38: =IF(B38="",0,SUMPRODUCT((PerDu<=B38)*(PerAu>=B38)*PerCode)) | T38: =IF(B38="",0,IF(COUNTIF(FeriesEff,B38)>0,1,0)) | U38: =IF(AND(E38<>"",F38<>""),1,0) | V38: =MAX(0,K38-J38) | W38: =IF(L38>0,1,0) | X38: =IF(Q38>0,1,0) | Y38: =IF(FournitRepas="L'assistante maternelle",IF(G38<>"",G38,IF(K38>0,RepasParJour,0)),0) | Z38: =IF(I38="Congé payé assmat",IF(AND(WEEKDAY(B38,2)<=6,T38=0),1,0),0) | AA38: =IF(I38="Férié travaillé (+10 %)",K38*MajFerie,IF(I38="1er mai travaillé",K38,0)) | AC38: =IF(B38="",0,IF(B38<AnnivRegul,0,IF(OR(I38="Accueil",I38="Férié travaillé (+10 %)",I38="1er mai travaillé"),MIN(K38,J38),IF(OR(I38="Absence enfant – payée",I38="Férié chômé payé"),Q38,0)))) | AD38: =IF(I38="Maladie enfant – retenue",1,0)
B39: =IF(22<=$AB$3,$AB$2+22-1,"") | C39: =IF(B39="","",CHOOSE(WEEKDAY(B39,2),"lun","mar","mer","jeu","ven","sam","dim")) | I39: =IF(B39="","",IF(R39=0,"Hors contrat",IF(D39<>"",D39,IF(U39=1,IF(T39=1,IF(AND(DAY(B39)=1,MONTH(B39)=5),"1er mai travaillé","Férié travaillé (+10 %)"),"Accueil"),IF(S39=1,IF(OR(WEEKDAY(B39,2)=7,T39=1),IF(AND(T39=1,Q39>0),"Férié chômé payé","Repos"),"Congé payé assmat"),IF(S39=4,IF(Q39>0,"Congé sans solde assmat","Repos"),IF(Q39=0,"Repos",IF(S39=2,"Semaine non programmée",IF(S39=3,"Absence enfant – payée",IF(T39=1,"Férié chômé payé","Accueil")))))))))) | J39: =IF(OR(I39="Accueil",I39="Férié travaillé (+10 %)",I39="1er mai travaillé"),IF(OR(S39=1,S39=2),0,Q39),0) | K39: =IF(OR(I39="Accueil",I39="Férié travaillé (+10 %)",I39="1er mai travaillé"),IF(U39=1,ROUND(MOD(F39-E39,1)*24,2),J39),0) | L39: =IF(OR(I39="Maladie enfant – retenue",I39="Absence assmat – non payée",I39="Congé sans solde assmat",I39="Hors contrat"),Q39,0) | M39: =IF(K39>0,ROUND(MAX(PlancherEnt,Entretien9h/9*K39),2),0) | P39: =IF(B39="","",B39-WEEKDAY(B39,2)+1) | Q39: =IF(B39="",0,INDEX(PlanH,WEEKDAY(B39,2))) | R39: =IF(B39="",0,IF(AND(OR(DateDebut="",B39>=DateDebut),OR(DateFin="",B39<=DateFin)),1,0)) | S39: =IF(B39="",0,SUMPRODUCT((PerDu<=B39)*(PerAu>=B39)*PerCode)) | T39: =IF(B39="",0,IF(COUNTIF(FeriesEff,B39)>0,1,0)) | U39: =IF(AND(E39<>"",F39<>""),1,0) | V39: =MAX(0,K39-J39) | W39: =IF(L39>0,1,0) | X39: =IF(Q39>0,1,0) | Y39: =IF(FournitRepas="L'assistante maternelle",IF(G39<>"",G39,IF(K39>0,RepasParJour,0)),0) | Z39: =IF(I39="Congé payé assmat",IF(AND(WEEKDAY(B39,2)<=6,T39=0),1,0),0) | AA39: =IF(I39="Férié travaillé (+10 %)",K39*MajFerie,IF(I39="1er mai travaillé",K39,0)) | AC39: =IF(B39="",0,IF(B39<AnnivRegul,0,IF(OR(I39="Accueil",I39="Férié travaillé (+10 %)",I39="1er mai travaillé"),MIN(K39,J39),IF(OR(I39="Absence enfant – payée",I39="Férié chômé payé"),Q39,0)))) | AD39: =IF(I39="Maladie enfant – retenue",1,0)
B40: =IF(23<=$AB$3,$AB$2+23-1,"") | C40: =IF(B40="","",CHOOSE(WEEKDAY(B40,2),"lun","mar","mer","jeu","ven","sam","dim")) | I40: =IF(B40="","",IF(R40=0,"Hors contrat",IF(D40<>"",D40,IF(U40=1,IF(T40=1,IF(AND(DAY(B40)=1,MONTH(B40)=5),"1er mai travaillé","Férié travaillé (+10 %)"),"Accueil"),IF(S40=1,IF(OR(WEEKDAY(B40,2)=7,T40=1),IF(AND(T40=1,Q40>0),"Férié chômé payé","Repos"),"Congé payé assmat"),IF(S40=4,IF(Q40>0,"Congé sans solde assmat","Repos"),IF(Q40=0,"Repos",IF(S40=2,"Semaine non programmée",IF(S40=3,"Absence enfant – payée",IF(T40=1,"Férié chômé payé","Accueil")))))))))) | J40: =IF(OR(I40="Accueil",I40="Férié travaillé (+10 %)",I40="1er mai travaillé"),IF(OR(S40=1,S40=2),0,Q40),0) | K40: =IF(OR(I40="Accueil",I40="Férié travaillé (+10 %)",I40="1er mai travaillé"),IF(U40=1,ROUND(MOD(F40-E40,1)*24,2),J40),0) | L40: =IF(OR(I40="Maladie enfant – retenue",I40="Absence assmat – non payée",I40="Congé sans solde assmat",I40="Hors contrat"),Q40,0) | M40: =IF(K40>0,ROUND(MAX(PlancherEnt,Entretien9h/9*K40),2),0) | P40: =IF(B40="","",B40-WEEKDAY(B40,2)+1) | Q40: =IF(B40="",0,INDEX(PlanH,WEEKDAY(B40,2))) | R40: =IF(B40="",0,IF(AND(OR(DateDebut="",B40>=DateDebut),OR(DateFin="",B40<=DateFin)),1,0)) | S40: =IF(B40="",0,SUMPRODUCT((PerDu<=B40)*(PerAu>=B40)*PerCode)) | T40: =IF(B40="",0,IF(COUNTIF(FeriesEff,B40)>0,1,0)) | U40: =IF(AND(E40<>"",F40<>""),1,0) | V40: =MAX(0,K40-J40) | W40: =IF(L40>0,1,0) | X40: =IF(Q40>0,1,0) | Y40: =IF(FournitRepas="L'assistante maternelle",IF(G40<>"",G40,IF(K40>0,RepasParJour,0)),0) | Z40: =IF(I40="Congé payé assmat",IF(AND(WEEKDAY(B40,2)<=6,T40=0),1,0),0) | AA40: =IF(I40="Férié travaillé (+10 %)",K40*MajFerie,IF(I40="1er mai travaillé",K40,0)) | AC40: =IF(B40="",0,IF(B40<AnnivRegul,0,IF(OR(I40="Accueil",I40="Férié travaillé (+10 %)",I40="1er mai travaillé"),MIN(K40,J40),IF(OR(I40="Absence enfant – payée",I40="Férié chômé payé"),Q40,0)))) | AD40: =IF(I40="Maladie enfant – retenue",1,0)
B41: =IF(24<=$AB$3,$AB$2+24-1,"") | C41: =IF(B41="","",CHOOSE(WEEKDAY(B41,2),"lun","mar","mer","jeu","ven","sam","dim")) | I41: =IF(B41="","",IF(R41=0,"Hors contrat",IF(D41<>"",D41,IF(U41=1,IF(T41=1,IF(AND(DAY(B41)=1,MONTH(B41)=5),"1er mai travaillé","Férié travaillé (+10 %)"),"Accueil"),IF(S41=1,IF(OR(WEEKDAY(B41,2)=7,T41=1),IF(AND(T41=1,Q41>0),"Férié chômé payé","Repos"),"Congé payé assmat"),IF(S41=4,IF(Q41>0,"Congé sans solde assmat","Repos"),IF(Q41=0,"Repos",IF(S41=2,"Semaine non programmée",IF(S41=3,"Absence enfant – payée",IF(T41=1,"Férié chômé payé","Accueil")))))))))) | J41: =IF(OR(I41="Accueil",I41="Férié travaillé (+10 %)",I41="1er mai travaillé"),IF(OR(S41=1,S41=2),0,Q41),0) | K41: =IF(OR(I41="Accueil",I41="Férié travaillé (+10 %)",I41="1er mai travaillé"),IF(U41=1,ROUND(MOD(F41-E41,1)*24,2),J41),0) | L41: =IF(OR(I41="Maladie enfant – retenue",I41="Absence assmat – non payée",I41="Congé sans solde assmat",I41="Hors contrat"),Q41,0) | M41: =IF(K41>0,ROUND(MAX(PlancherEnt,Entretien9h/9*K41),2),0) | P41: =IF(B41="","",B41-WEEKDAY(B41,2)+1) | Q41: =IF(B41="",0,INDEX(PlanH,WEEKDAY(B41,2))) | R41: =IF(B41="",0,IF(AND(OR(DateDebut="",B41>=DateDebut),OR(DateFin="",B41<=DateFin)),1,0)) | S41: =IF(B41="",0,SUMPRODUCT((PerDu<=B41)*(PerAu>=B41)*PerCode)) | T41: =IF(B41="",0,IF(COUNTIF(FeriesEff,B41)>0,1,0)) | U41: =IF(AND(E41<>"",F41<>""),1,0) | V41: =MAX(0,K41-J41) | W41: =IF(L41>0,1,0) | X41: =IF(Q41>0,1,0) | Y41: =IF(FournitRepas="L'assistante maternelle",IF(G41<>"",G41,IF(K41>0,RepasParJour,0)),0) | Z41: =IF(I41="Congé payé assmat",IF(AND(WEEKDAY(B41,2)<=6,T41=0),1,0),0) | AA41: =IF(I41="Férié travaillé (+10 %)",K41*MajFerie,IF(I41="1er mai travaillé",K41,0)) | AC41: =IF(B41="",0,IF(B41<AnnivRegul,0,IF(OR(I41="Accueil",I41="Férié travaillé (+10 %)",I41="1er mai travaillé"),MIN(K41,J41),IF(OR(I41="Absence enfant – payée",I41="Férié chômé payé"),Q41,0)))) | AD41: =IF(I41="Maladie enfant – retenue",1,0)
B42: =IF(25<=$AB$3,$AB$2+25-1,"") | C42: =IF(B42="","",CHOOSE(WEEKDAY(B42,2),"lun","mar","mer","jeu","ven","sam","dim")) | I42: =IF(B42="","",IF(R42=0,"Hors contrat",IF(D42<>"",D42,IF(U42=1,IF(T42=1,IF(AND(DAY(B42)=1,MONTH(B42)=5),"1er mai travaillé","Férié travaillé (+10 %)"),"Accueil"),IF(S42=1,IF(OR(WEEKDAY(B42,2)=7,T42=1),IF(AND(T42=1,Q42>0),"Férié chômé payé","Repos"),"Congé payé assmat"),IF(S42=4,IF(Q42>0,"Congé sans solde assmat","Repos"),IF(Q42=0,"Repos",IF(S42=2,"Semaine non programmée",IF(S42=3,"Absence enfant – payée",IF(T42=1,"Férié chômé payé","Accueil")))))))))) | J42: =IF(OR(I42="Accueil",I42="Férié travaillé (+10 %)",I42="1er mai travaillé"),IF(OR(S42=1,S42=2),0,Q42),0) | K42: =IF(OR(I42="Accueil",I42="Férié travaillé (+10 %)",I42="1er mai travaillé"),IF(U42=1,ROUND(MOD(F42-E42,1)*24,2),J42),0) | L42: =IF(OR(I42="Maladie enfant – retenue",I42="Absence assmat – non payée",I42="Congé sans solde assmat",I42="Hors contrat"),Q42,0) | M42: =IF(K42>0,ROUND(MAX(PlancherEnt,Entretien9h/9*K42),2),0) | P42: =IF(B42="","",B42-WEEKDAY(B42,2)+1) | Q42: =IF(B42="",0,INDEX(PlanH,WEEKDAY(B42,2))) | R42: =IF(B42="",0,IF(AND(OR(DateDebut="",B42>=DateDebut),OR(DateFin="",B42<=DateFin)),1,0)) | S42: =IF(B42="",0,SUMPRODUCT((PerDu<=B42)*(PerAu>=B42)*PerCode)) | T42: =IF(B42="",0,IF(COUNTIF(FeriesEff,B42)>0,1,0)) | U42: =IF(AND(E42<>"",F42<>""),1,0) | V42: =MAX(0,K42-J42) | W42: =IF(L42>0,1,0) | X42: =IF(Q42>0,1,0) | Y42: =IF(FournitRepas="L'assistante maternelle",IF(G42<>"",G42,IF(K42>0,RepasParJour,0)),0) | Z42: =IF(I42="Congé payé assmat",IF(AND(WEEKDAY(B42,2)<=6,T42=0),1,0),0) | AA42: =IF(I42="Férié travaillé (+10 %)",K42*MajFerie,IF(I42="1er mai travaillé",K42,0)) | AC42: =IF(B42="",0,IF(B42<AnnivRegul,0,IF(OR(I42="Accueil",I42="Férié travaillé (+10 %)",I42="1er mai travaillé"),MIN(K42,J42),IF(OR(I42="Absence enfant – payée",I42="Férié chômé payé"),Q42,0)))) | AD42: =IF(I42="Maladie enfant – retenue",1,0)
B43: =IF(26<=$AB$3,$AB$2+26-1,"") | C43: =IF(B43="","",CHOOSE(WEEKDAY(B43,2),"lun","mar","mer","jeu","ven","sam","dim")) | I43: =IF(B43="","",IF(R43=0,"Hors contrat",IF(D43<>"",D43,IF(U43=1,IF(T43=1,IF(AND(DAY(B43)=1,MONTH(B43)=5),"1er mai travaillé","Férié travaillé (+10 %)"),"Accueil"),IF(S43=1,IF(OR(WEEKDAY(B43,2)=7,T43=1),IF(AND(T43=1,Q43>0),"Férié chômé payé","Repos"),"Congé payé assmat"),IF(S43=4,IF(Q43>0,"Congé sans solde assmat","Repos"),IF(Q43=0,"Repos",IF(S43=2,"Semaine non programmée",IF(S43=3,"Absence enfant – payée",IF(T43=1,"Férié chômé payé","Accueil")))))))))) | J43: =IF(OR(I43="Accueil",I43="Férié travaillé (+10 %)",I43="1er mai travaillé"),IF(OR(S43=1,S43=2),0,Q43),0) | K43: =IF(OR(I43="Accueil",I43="Férié travaillé (+10 %)",I43="1er mai travaillé"),IF(U43=1,ROUND(MOD(F43-E43,1)*24,2),J43),0) | L43: =IF(OR(I43="Maladie enfant – retenue",I43="Absence assmat – non payée",I43="Congé sans solde assmat",I43="Hors contrat"),Q43,0) | M43: =IF(K43>0,ROUND(MAX(PlancherEnt,Entretien9h/9*K43),2),0) | P43: =IF(B43="","",B43-WEEKDAY(B43,2)+1) | Q43: =IF(B43="",0,INDEX(PlanH,WEEKDAY(B43,2))) | R43: =IF(B43="",0,IF(AND(OR(DateDebut="",B43>=DateDebut),OR(DateFin="",B43<=DateFin)),1,0)) | S43: =IF(B43="",0,SUMPRODUCT((PerDu<=B43)*(PerAu>=B43)*PerCode)) | T43: =IF(B43="",0,IF(COUNTIF(FeriesEff,B43)>0,1,0)) | U43: =IF(AND(E43<>"",F43<>""),1,0) | V43: =MAX(0,K43-J43) | W43: =IF(L43>0,1,0) | X43: =IF(Q43>0,1,0) | Y43: =IF(FournitRepas="L'assistante maternelle",IF(G43<>"",G43,IF(K43>0,RepasParJour,0)),0) | Z43: =IF(I43="Congé payé assmat",IF(AND(WEEKDAY(B43,2)<=6,T43=0),1,0),0) | AA43: =IF(I43="Férié travaillé (+10 %)",K43*MajFerie,IF(I43="1er mai travaillé",K43,0)) | AC43: =IF(B43="",0,IF(B43<AnnivRegul,0,IF(OR(I43="Accueil",I43="Férié travaillé (+10 %)",I43="1er mai travaillé"),MIN(K43,J43),IF(OR(I43="Absence enfant – payée",I43="Férié chômé payé"),Q43,0)))) | AD43: =IF(I43="Maladie enfant – retenue",1,0)
B44: =IF(27<=$AB$3,$AB$2+27-1,"") | C44: =IF(B44="","",CHOOSE(WEEKDAY(B44,2),"lun","mar","mer","jeu","ven","sam","dim")) | I44: =IF(B44="","",IF(R44=0,"Hors contrat",IF(D44<>"",D44,IF(U44=1,IF(T44=1,IF(AND(DAY(B44)=1,MONTH(B44)=5),"1er mai travaillé","Férié travaillé (+10 %)"),"Accueil"),IF(S44=1,IF(OR(WEEKDAY(B44,2)=7,T44=1),IF(AND(T44=1,Q44>0),"Férié chômé payé","Repos"),"Congé payé assmat"),IF(S44=4,IF(Q44>0,"Congé sans solde assmat","Repos"),IF(Q44=0,"Repos",IF(S44=2,"Semaine non programmée",IF(S44=3,"Absence enfant – payée",IF(T44=1,"Férié chômé payé","Accueil")))))))))) | J44: =IF(OR(I44="Accueil",I44="Férié travaillé (+10 %)",I44="1er mai travaillé"),IF(OR(S44=1,S44=2),0,Q44),0) | K44: =IF(OR(I44="Accueil",I44="Férié travaillé (+10 %)",I44="1er mai travaillé"),IF(U44=1,ROUND(MOD(F44-E44,1)*24,2),J44),0) | L44: =IF(OR(I44="Maladie enfant – retenue",I44="Absence assmat – non payée",I44="Congé sans solde assmat",I44="Hors contrat"),Q44,0) | M44: =IF(K44>0,ROUND(MAX(PlancherEnt,Entretien9h/9*K44),2),0) | P44: =IF(B44="","",B44-WEEKDAY(B44,2)+1) | Q44: =IF(B44="",0,INDEX(PlanH,WEEKDAY(B44,2))) | R44: =IF(B44="",0,IF(AND(OR(DateDebut="",B44>=DateDebut),OR(DateFin="",B44<=DateFin)),1,0)) | S44: =IF(B44="",0,SUMPRODUCT((PerDu<=B44)*(PerAu>=B44)*PerCode)) | T44: =IF(B44="",0,IF(COUNTIF(FeriesEff,B44)>0,1,0)) | U44: =IF(AND(E44<>"",F44<>""),1,0) | V44: =MAX(0,K44-J44) | W44: =IF(L44>0,1,0) | X44: =IF(Q44>0,1,0) | Y44: =IF(FournitRepas="L'assistante maternelle",IF(G44<>"",G44,IF(K44>0,RepasParJour,0)),0) | Z44: =IF(I44="Congé payé assmat",IF(AND(WEEKDAY(B44,2)<=6,T44=0),1,0),0) | AA44: =IF(I44="Férié travaillé (+10 %)",K44*MajFerie,IF(I44="1er mai travaillé",K44,0)) | AC44: =IF(B44="",0,IF(B44<AnnivRegul,0,IF(OR(I44="Accueil",I44="Férié travaillé (+10 %)",I44="1er mai travaillé"),MIN(K44,J44),IF(OR(I44="Absence enfant – payée",I44="Férié chômé payé"),Q44,0)))) | AD44: =IF(I44="Maladie enfant – retenue",1,0)
B45: =IF(28<=$AB$3,$AB$2+28-1,"") | C45: =IF(B45="","",CHOOSE(WEEKDAY(B45,2),"lun","mar","mer","jeu","ven","sam","dim")) | I45: =IF(B45="","",IF(R45=0,"Hors contrat",IF(D45<>"",D45,IF(U45=1,IF(T45=1,IF(AND(DAY(B45)=1,MONTH(B45)=5),"1er mai travaillé","Férié travaillé (+10 %)"),"Accueil"),IF(S45=1,IF(OR(WEEKDAY(B45,2)=7,T45=1),IF(AND(T45=1,Q45>0),"Férié chômé payé","Repos"),"Congé payé assmat"),IF(S45=4,IF(Q45>0,"Congé sans solde assmat","Repos"),IF(Q45=0,"Repos",IF(S45=2,"Semaine non programmée",IF(S45=3,"Absence enfant – payée",IF(T45=1,"Férié chômé payé","Accueil")))))))))) | J45: =IF(OR(I45="Accueil",I45="Férié travaillé (+10 %)",I45="1er mai travaillé"),IF(OR(S45=1,S45=2),0,Q45),0) | K45: =IF(OR(I45="Accueil",I45="Férié travaillé (+10 %)",I45="1er mai travaillé"),IF(U45=1,ROUND(MOD(F45-E45,1)*24,2),J45),0) | L45: =IF(OR(I45="Maladie enfant – retenue",I45="Absence assmat – non payée",I45="Congé sans solde assmat",I45="Hors contrat"),Q45,0) | M45: =IF(K45>0,ROUND(MAX(PlancherEnt,Entretien9h/9*K45),2),0) | P45: =IF(B45="","",B45-WEEKDAY(B45,2)+1) | Q45: =IF(B45="",0,INDEX(PlanH,WEEKDAY(B45,2))) | R45: =IF(B45="",0,IF(AND(OR(DateDebut="",B45>=DateDebut),OR(DateFin="",B45<=DateFin)),1,0)) | S45: =IF(B45="",0,SUMPRODUCT((PerDu<=B45)*(PerAu>=B45)*PerCode)) | T45: =IF(B45="",0,IF(COUNTIF(FeriesEff,B45)>0,1,0)) | U45: =IF(AND(E45<>"",F45<>""),1,0) | V45: =MAX(0,K45-J45) | W45: =IF(L45>0,1,0) | X45: =IF(Q45>0,1,0) | Y45: =IF(FournitRepas="L'assistante maternelle",IF(G45<>"",G45,IF(K45>0,RepasParJour,0)),0) | Z45: =IF(I45="Congé payé assmat",IF(AND(WEEKDAY(B45,2)<=6,T45=0),1,0),0) | AA45: =IF(I45="Férié travaillé (+10 %)",K45*MajFerie,IF(I45="1er mai travaillé",K45,0)) | AC45: =IF(B45="",0,IF(B45<AnnivRegul,0,IF(OR(I45="Accueil",I45="Férié travaillé (+10 %)",I45="1er mai travaillé"),MIN(K45,J45),IF(OR(I45="Absence enfant – payée",I45="Férié chômé payé"),Q45,0)))) | AD45: =IF(I45="Maladie enfant – retenue",1,0)
B46: =IF(29<=$AB$3,$AB$2+29-1,"") | C46: =IF(B46="","",CHOOSE(WEEKDAY(B46,2),"lun","mar","mer","jeu","ven","sam","dim")) | I46: =IF(B46="","",IF(R46=0,"Hors contrat",IF(D46<>"",D46,IF(U46=1,IF(T46=1,IF(AND(DAY(B46)=1,MONTH(B46)=5),"1er mai travaillé","Férié travaillé (+10 %)"),"Accueil"),IF(S46=1,IF(OR(WEEKDAY(B46,2)=7,T46=1),IF(AND(T46=1,Q46>0),"Férié chômé payé","Repos"),"Congé payé assmat"),IF(S46=4,IF(Q46>0,"Congé sans solde assmat","Repos"),IF(Q46=0,"Repos",IF(S46=2,"Semaine non programmée",IF(S46=3,"Absence enfant – payée",IF(T46=1,"Férié chômé payé","Accueil")))))))))) | J46: =IF(OR(I46="Accueil",I46="Férié travaillé (+10 %)",I46="1er mai travaillé"),IF(OR(S46=1,S46=2),0,Q46),0) | K46: =IF(OR(I46="Accueil",I46="Férié travaillé (+10 %)",I46="1er mai travaillé"),IF(U46=1,ROUND(MOD(F46-E46,1)*24,2),J46),0) | L46: =IF(OR(I46="Maladie enfant – retenue",I46="Absence assmat – non payée",I46="Congé sans solde assmat",I46="Hors contrat"),Q46,0) | M46: =IF(K46>0,ROUND(MAX(PlancherEnt,Entretien9h/9*K46),2),0) | P46: =IF(B46="","",B46-WEEKDAY(B46,2)+1) | Q46: =IF(B46="",0,INDEX(PlanH,WEEKDAY(B46,2))) | R46: =IF(B46="",0,IF(AND(OR(DateDebut="",B46>=DateDebut),OR(DateFin="",B46<=DateFin)),1,0)) | S46: =IF(B46="",0,SUMPRODUCT((PerDu<=B46)*(PerAu>=B46)*PerCode)) | T46: =IF(B46="",0,IF(COUNTIF(FeriesEff,B46)>0,1,0)) | U46: =IF(AND(E46<>"",F46<>""),1,0) | V46: =MAX(0,K46-J46) | W46: =IF(L46>0,1,0) | X46: =IF(Q46>0,1,0) | Y46: =IF(FournitRepas="L'assistante maternelle",IF(G46<>"",G46,IF(K46>0,RepasParJour,0)),0) | Z46: =IF(I46="Congé payé assmat",IF(AND(WEEKDAY(B46,2)<=6,T46=0),1,0),0) | AA46: =IF(I46="Férié travaillé (+10 %)",K46*MajFerie,IF(I46="1er mai travaillé",K46,0)) | AC46: =IF(B46="",0,IF(B46<AnnivRegul,0,IF(OR(I46="Accueil",I46="Férié travaillé (+10 %)",I46="1er mai travaillé"),MIN(K46,J46),IF(OR(I46="Absence enfant – payée",I46="Férié chômé payé"),Q46,0)))) | AD46: =IF(I46="Maladie enfant – retenue",1,0)
B47: =IF(30<=$AB$3,$AB$2+30-1,"") | C47: =IF(B47="","",CHOOSE(WEEKDAY(B47,2),"lun","mar","mer","jeu","ven","sam","dim")) | I47: =IF(B47="","",IF(R47=0,"Hors contrat",IF(D47<>"",D47,IF(U47=1,IF(T47=1,IF(AND(DAY(B47)=1,MONTH(B47)=5),"1er mai travaillé","Férié travaillé (+10 %)"),"Accueil"),IF(S47=1,IF(OR(WEEKDAY(B47,2)=7,T47=1),IF(AND(T47=1,Q47>0),"Férié chômé payé","Repos"),"Congé payé assmat"),IF(S47=4,IF(Q47>0,"Congé sans solde assmat","Repos"),IF(Q47=0,"Repos",IF(S47=2,"Semaine non programmée",IF(S47=3,"Absence enfant – payée",IF(T47=1,"Férié chômé payé","Accueil")))))))))) | J47: =IF(OR(I47="Accueil",I47="Férié travaillé (+10 %)",I47="1er mai travaillé"),IF(OR(S47=1,S47=2),0,Q47),0) | K47: =IF(OR(I47="Accueil",I47="Férié travaillé (+10 %)",I47="1er mai travaillé"),IF(U47=1,ROUND(MOD(F47-E47,1)*24,2),J47),0) | L47: =IF(OR(I47="Maladie enfant – retenue",I47="Absence assmat – non payée",I47="Congé sans solde assmat",I47="Hors contrat"),Q47,0) | M47: =IF(K47>0,ROUND(MAX(PlancherEnt,Entretien9h/9*K47),2),0) | P47: =IF(B47="","",B47-WEEKDAY(B47,2)+1) | Q47: =IF(B47="",0,INDEX(PlanH,WEEKDAY(B47,2))) | R47: =IF(B47="",0,IF(AND(OR(DateDebut="",B47>=DateDebut),OR(DateFin="",B47<=DateFin)),1,0)) | S47: =IF(B47="",0,SUMPRODUCT((PerDu<=B47)*(PerAu>=B47)*PerCode)) | T47: =IF(B47="",0,IF(COUNTIF(FeriesEff,B47)>0,1,0)) | U47: =IF(AND(E47<>"",F47<>""),1,0) | V47: =MAX(0,K47-J47) | W47: =IF(L47>0,1,0) | X47: =IF(Q47>0,1,0) | Y47: =IF(FournitRepas="L'assistante maternelle",IF(G47<>"",G47,IF(K47>0,RepasParJour,0)),0) | Z47: =IF(I47="Congé payé assmat",IF(AND(WEEKDAY(B47,2)<=6,T47=0),1,0),0) | AA47: =IF(I47="Férié travaillé (+10 %)",K47*MajFerie,IF(I47="1er mai travaillé",K47,0)) | AC47: =IF(B47="",0,IF(B47<AnnivRegul,0,IF(OR(I47="Accueil",I47="Férié travaillé (+10 %)",I47="1er mai travaillé"),MIN(K47,J47),IF(OR(I47="Absence enfant – payée",I47="Férié chômé payé"),Q47,0)))) | AD47: =IF(I47="Maladie enfant – retenue",1,0)
B48: =IF(31<=$AB$3,$AB$2+31-1,"") | C48: =IF(B48="","",CHOOSE(WEEKDAY(B48,2),"lun","mar","mer","jeu","ven","sam","dim")) | I48: =IF(B48="","",IF(R48=0,"Hors contrat",IF(D48<>"",D48,IF(U48=1,IF(T48=1,IF(AND(DAY(B48)=1,MONTH(B48)=5),"1er mai travaillé","Férié travaillé (+10 %)"),"Accueil"),IF(S48=1,IF(OR(WEEKDAY(B48,2)=7,T48=1),IF(AND(T48=1,Q48>0),"Férié chômé payé","Repos"),"Congé payé assmat"),IF(S48=4,IF(Q48>0,"Congé sans solde assmat","Repos"),IF(Q48=0,"Repos",IF(S48=2,"Semaine non programmée",IF(S48=3,"Absence enfant – payée",IF(T48=1,"Férié chômé payé","Accueil")))))))))) | J48: =IF(OR(I48="Accueil",I48="Férié travaillé (+10 %)",I48="1er mai travaillé"),IF(OR(S48=1,S48=2),0,Q48),0) | K48: =IF(OR(I48="Accueil",I48="Férié travaillé (+10 %)",I48="1er mai travaillé"),IF(U48=1,ROUND(MOD(F48-E48,1)*24,2),J48),0) | L48: =IF(OR(I48="Maladie enfant – retenue",I48="Absence assmat – non payée",I48="Congé sans solde assmat",I48="Hors contrat"),Q48,0) | M48: =IF(K48>0,ROUND(MAX(PlancherEnt,Entretien9h/9*K48),2),0) | P48: =IF(B48="","",B48-WEEKDAY(B48,2)+1) | Q48: =IF(B48="",0,INDEX(PlanH,WEEKDAY(B48,2))) | R48: =IF(B48="",0,IF(AND(OR(DateDebut="",B48>=DateDebut),OR(DateFin="",B48<=DateFin)),1,0)) | S48: =IF(B48="",0,SUMPRODUCT((PerDu<=B48)*(PerAu>=B48)*PerCode)) | T48: =IF(B48="",0,IF(COUNTIF(FeriesEff,B48)>0,1,0)) | U48: =IF(AND(E48<>"",F48<>""),1,0) | V48: =MAX(0,K48-J48) | W48: =IF(L48>0,1,0) | X48: =IF(Q48>0,1,0) | Y48: =IF(FournitRepas="L'assistante maternelle",IF(G48<>"",G48,IF(K48>0,RepasParJour,0)),0) | Z48: =IF(I48="Congé payé assmat",IF(AND(WEEKDAY(B48,2)<=6,T48=0),1,0),0) | AA48: =IF(I48="Férié travaillé (+10 %)",K48*MajFerie,IF(I48="1er mai travaillé",K48,0)) | AC48: =IF(B48="",0,IF(B48<AnnivRegul,0,IF(OR(I48="Accueil",I48="Férié travaillé (+10 %)",I48="1er mai travaillé"),MIN(K48,J48),IF(OR(I48="Absence enfant – payée",I48="Férié chômé payé"),Q48,0)))) | AD48: =IF(I48="Maladie enfant – retenue",1,0)
G49: =SUM(Y18:Y48) | H49: =SUM(H18:H48) | I49: Totaux du mois | J49: =SUM(J18:J48) | K49: =SUM(K18:K48) | L49: =SUM(L18:L48) | M49: =SUM(M18:M48)
B51: HEURES PAR SEMAINE (CALCUL DES HEURES COMPLÉMENTAIRES ET MAJORÉES)
B52: Semaine du | C52: au | D52: Réalisées | E52: Au planning | F52: En plus | G52: dont compl. | H52: dont major. | I52: Une heure est « en plus » dès qu'elle dépasse le planning du jour. Jusqu'à 45 h dans la semaine, elle est complémentaire (taux normal, sauf majoration prévue au contrat). Au-delà de 45 h, elle est majorée (10 % minimum).
B53: =$AB$2-WEEKDAY($AB$2,2)+1 | C53: =IF(B53="","",MIN(B53+6,EOMONTH($AB$2,0))) | D53: =IF(B53="",0,SUMIFS($K$18:$K$48,$P$18:$P$48,B53)) | E53: =IF(B53="",0,SUMIFS($J$18:$J$48,$P$18:$P$48,B53)) | F53: =IF(B53="",0,SUMIFS($V$18:$V$48,$P$18:$P$48,B53)) | G53: =IF(B53="",0,F53-H53) | H53: =IF(B53="",0,MIN(F53,MAX(0,D53-SeuilMaj)))
B54: =IF(B53="","",IF(B53+7<=EOMONTH($AB$2,0),B53+7,"")) | C54: =IF(B54="","",MIN(B54+6,EOMONTH($AB$2,0))) | D54: =IF(B54="",0,SUMIFS($K$18:$K$48,$P$18:$P$48,B54)) | E54: =IF(B54="",0,SUMIFS($J$18:$J$48,$P$18:$P$48,B54)) | F54: =IF(B54="",0,SUMIFS($V$18:$V$48,$P$18:$P$48,B54)) | G54: =IF(B54="",0,F54-H54) | H54: =IF(B54="",0,MIN(F54,MAX(0,D54-SeuilMaj)))
B55: =IF(B54="","",IF(B54+7<=EOMONTH($AB$2,0),B54+7,"")) | C55: =IF(B55="","",MIN(B55+6,EOMONTH($AB$2,0))) | D55: =IF(B55="",0,SUMIFS($K$18:$K$48,$P$18:$P$48,B55)) | E55: =IF(B55="",0,SUMIFS($J$18:$J$48,$P$18:$P$48,B55)) | F55: =IF(B55="",0,SUMIFS($V$18:$V$48,$P$18:$P$48,B55)) | G55: =IF(B55="",0,F55-H55) | H55: =IF(B55="",0,MIN(F55,MAX(0,D55-SeuilMaj)))
B56: =IF(B55="","",IF(B55+7<=EOMONTH($AB$2,0),B55+7,"")) | C56: =IF(B56="","",MIN(B56+6,EOMONTH($AB$2,0))) | D56: =IF(B56="",0,SUMIFS($K$18:$K$48,$P$18:$P$48,B56)) | E56: =IF(B56="",0,SUMIFS($J$18:$J$48,$P$18:$P$48,B56)) | F56: =IF(B56="",0,SUMIFS($V$18:$V$48,$P$18:$P$48,B56)) | G56: =IF(B56="",0,F56-H56) | H56: =IF(B56="",0,MIN(F56,MAX(0,D56-SeuilMaj)))
B57: =IF(B56="","",IF(B56+7<=EOMONTH($AB$2,0),B56+7,"")) | C57: =IF(B57="","",MIN(B57+6,EOMONTH($AB$2,0))) | D57: =IF(B57="",0,SUMIFS($K$18:$K$48,$P$18:$P$48,B57)) | E57: =IF(B57="",0,SUMIFS($J$18:$J$48,$P$18:$P$48,B57)) | F57: =IF(B57="",0,SUMIFS($V$18:$V$48,$P$18:$P$48,B57)) | G57: =IF(B57="",0,F57-H57) | H57: =IF(B57="",0,MIN(F57,MAX(0,D57-SeuilMaj)))
B58: =IF(B57="","",IF(B57+7<=EOMONTH($AB$2,0),B57+7,"")) | C58: =IF(B58="","",MIN(B58+6,EOMONTH($AB$2,0))) | D58: =IF(B58="",0,SUMIFS($K$18:$K$48,$P$18:$P$48,B58)) | E58: =IF(B58="",0,SUMIFS($J$18:$J$48,$P$18:$P$48,B58)) | F58: =IF(B58="",0,SUMIFS($V$18:$V$48,$P$18:$P$48,B58)) | G58: =IF(B58="",0,F58-H58) | H58: =IF(B58="",0,MIN(F58,MAX(0,D58-SeuilMaj)))
D59: =SUM(D53:D58) | E59: =SUM(E53:E58) | F59: =SUM(F53:F58) | G59: =SUM(G53:G58) | H59: =SUM(H53:H58)
B62: Signature du parent employeur | I62: Signature de l'assistante maternelle

Sheet Août 2026
B2: Août 2026 | N2: Nid Serein · Édition 2026-2027 | AB2: 46235
B3: ="Présence, salaire et déclaration Pajemploi"&IF(EnfantNom<>""," — "&EnfantNom,"")&IF(AssmatNom<>""," chez "&AssmatNom,"") | AB3: =DAY(EOMONTH(AB2,0))
B5: SALAIRE DU MOIS (BRUT) | I5: À DÉCLARER SUR PAJEMPLOI | M5: À VERSER À L'ASSMAT | AB5: =SUM(Q18:Q48)
B6: Salaire mensualisé | F6: =IF(AB19=1,SalMensBrut,0) | I6: Nombre d'heures normales | K6: =IFERROR(IF(F6=0,0,ROUND(HeuresMens+F7/TauxBrut,0)),0) | M6: Salaire net (estimé) | AB6: =SUM(L18:L48)
B7: Retenue pour absence(s) | F7: =IF(AB19=1,-AB9,0) | I7: Nombre de jours d'activité | K7: =IF(F6=0,0,ROUNDUP(JoursMens*(F6+F7)/F6,0)) | M7: =K11 | AB7: =SUM(X18:X48)
B8: Heures complémentaires | E8: =AB17 | F8: =ROUND(E8*TauxBrut*(1+MajCompl),2) | I8: Jours de congés payés | K8: ='Congés payés'!F36 | M8: Indemnités (non imposables) | AB8: =SUM(W18:W48)
B9: Heures majorées (au-delà de 45 h) | E9: =AB18 | F9: =ROUND(E9*TauxBrut*(1+MajSup),2) | I9: Heures complémentaires | K9: =E8 | M9: =SUM(K12:K15) | AB9: =ROUND(IF(TypeCode=1,IF(AB5>0,SalMensBrut*AB6/AB5,0),IF(AB7>0,SalMensBrut*AB8/AB7,0)),2)
B10: Jours fériés travaillés | F10: =ROUND(SUM(AA18:AA48)*TauxBrut,2) | I10: Heures majorées | K10: =E9 | M10: TOTAL DU MOIS | AB10: =SUM(Z18:Z48)
B11: Congés payés versés ce mois-ci | F11: ='Congés payés'!E36 | I11: Salaire net total | K11: =ROUND(F15*CoefNet,2) | M11: =M7+M9 | AB11: =SUM(AD18:AD48)
B12: Fin de contrat (régularisation, congés) | F12: =IF(AB14=1,FinSoumis,0) | I12: Indemnités d'entretien | K12: =SUM(M18:M48) | AB12: =SUM(AC18:AC48)
B13: Autre somme brute (prime, rappel…) | I13: Indemnités de repas | K13: =ROUND(SUM(Y18:Y48)*PrixRepas,2) | M13: Avec Pajemploi+, ce montant (moins votre CMG) est prélevé puis versé à l'assmat par Pajemploi. | AB13: =IF(OR(AB19=0,SalMensBrut=0),0,HeuresMens*(F6+F7)/SalMensBrut)
I14: Indemnités kilométriques | K14: =ROUND(SUM(H18:H48)*TarifKm,2) | AB14: =IF(DateFin="",0,IF(AND(DateFin>=AB2,DateFin<=EOMONTH(AB2,0)),1,0))
B15: Salaire brut du mois | F15: =SUM(F6:F13) | I15: Indemnité de rupture | K15: =IF(AB14=1,IndemRupture,0) | AB15: =SUM(F6:F11)+F13
B16: =IF(AB19=0,"Mois hors contrat (avant le début ou après la fin) : rien à déclarer ce mois-ci.",IF(AB20>4,"⚠ Deux périodes de l'onglet Contrat se chevauchent : corrigez-les.",IF(AB11>5,"⚠ Plus de 5 jours de maladie de l'enfant retenus : au-delà de 5 jours par an (absences courtes), le salaire est dû, sauf absence d'au moins 14 jours consécutifs.",""))) | AB16: =SUM(K18:K48)
B17: Date | C17: Jour | D17: ✎ Statut (si différent) | E17: ✎ Arrivée | F17: ✎ Départ | G17: ✎ Repas | H17: ✎ Km | I17: Statut retenu | J17: Prévu | K17: Réalisé | L17: Retenue | M17: Entretien | N17: ✎ Notes | AB17: =G59
B18: =IF(1<=$AB$3,$AB$2+1-1,"") | C18: =IF(B18="","",CHOOSE(WEEKDAY(B18,2),"lun","mar","mer","jeu","ven","sam","dim")) | I18: =IF(B18="","",IF(R18=0,"Hors contrat",IF(D18<>"",D18,IF(U18=1,IF(T18=1,IF(AND(DAY(B18)=1,MONTH(B18)=5),"1er mai travaillé","Férié travaillé (+10 %)"),"Accueil"),IF(S18=1,IF(OR(WEEKDAY(B18,2)=7,T18=1),IF(AND(T18=1,Q18>0),"Férié chômé payé","Repos"),"Congé payé assmat"),IF(S18=4,IF(Q18>0,"Congé sans solde assmat","Repos"),IF(Q18=0,"Repos",IF(S18=2,"Semaine non programmée",IF(S18=3,"Absence enfant – payée",IF(T18=1,"Férié chômé payé","Accueil")))))))))) | J18: =IF(OR(I18="Accueil",I18="Férié travaillé (+10 %)",I18="1er mai travaillé"),IF(OR(S18=1,S18=2),0,Q18),0) | K18: =IF(OR(I18="Accueil",I18="Férié travaillé (+10 %)",I18="1er mai travaillé"),IF(U18=1,ROUND(MOD(F18-E18,1)*24,2),J18),0) | L18: =IF(OR(I18="Maladie enfant – retenue",I18="Absence assmat – non payée",I18="Congé sans solde assmat",I18="Hors contrat"),Q18,0) | M18: =IF(K18>0,ROUND(MAX(PlancherEnt,Entretien9h/9*K18),2),0) | P18: =IF(B18="","",B18-WEEKDAY(B18,2)+1) | Q18: =IF(B18="",0,INDEX(PlanH,WEEKDAY(B18,2))) | R18: =IF(B18="",0,IF(AND(OR(DateDebut="",B18>=DateDebut),OR(DateFin="",B18<=DateFin)),1,0)) | S18: =IF(B18="",0,SUMPRODUCT((PerDu<=B18)*(PerAu>=B18)*PerCode)) | T18: =IF(B18="",0,IF(COUNTIF(FeriesEff,B18)>0,1,0)) | U18: =IF(AND(E18<>"",F18<>""),1,0) | V18: =MAX(0,K18-J18) | W18: =IF(L18>0,1,0) | X18: =IF(Q18>0,1,0) | Y18: =IF(FournitRepas="L'assistante maternelle",IF(G18<>"",G18,IF(K18>0,RepasParJour,0)),0) | Z18: =IF(I18="Congé payé assmat",IF(AND(WEEKDAY(B18,2)<=6,T18=0),1,0),0) | AA18: =IF(I18="Férié travaillé (+10 %)",K18*MajFerie,IF(I18="1er mai travaillé",K18,0)) | AB18: =H59 | AC18: =IF(B18="",0,IF(B18<AnnivRegul,0,IF(OR(I18="Accueil",I18="Férié travaillé (+10 %)",I18="1er mai travaillé"),MIN(K18,J18),IF(OR(I18="Absence enfant – payée",I18="Férié chômé payé"),Q18,0)))) | AD18: =IF(I18="Maladie enfant – retenue",1,0)
B19: =IF(2<=$AB$3,$AB$2+2-1,"") | C19: =IF(B19="","",CHOOSE(WEEKDAY(B19,2),"lun","mar","mer","jeu","ven","sam","dim")) | I19: =IF(B19="","",IF(R19=0,"Hors contrat",IF(D19<>"",D19,IF(U19=1,IF(T19=1,IF(AND(DAY(B19)=1,MONTH(B19)=5),"1er mai travaillé","Férié travaillé (+10 %)"),"Accueil"),IF(S19=1,IF(OR(WEEKDAY(B19,2)=7,T19=1),IF(AND(T19=1,Q19>0),"Férié chômé payé","Repos"),"Congé payé assmat"),IF(S19=4,IF(Q19>0,"Congé sans solde assmat","Repos"),IF(Q19=0,"Repos",IF(S19=2,"Semaine non programmée",IF(S19=3,"Absence enfant – payée",IF(T19=1,"Férié chômé payé","Accueil")))))))))) | J19: =IF(OR(I19="Accueil",I19="Férié travaillé (+10 %)",I19="1er mai travaillé"),IF(OR(S19=1,S19=2),0,Q19),0) | K19: =IF(OR(I19="Accueil",I19="Férié travaillé (+10 %)",I19="1er mai travaillé"),IF(U19=1,ROUND(MOD(F19-E19,1)*24,2),J19),0) | L19: =IF(OR(I19="Maladie enfant – retenue",I19="Absence assmat – non payée",I19="Congé sans solde assmat",I19="Hors contrat"),Q19,0) | M19: =IF(K19>0,ROUND(MAX(PlancherEnt,Entretien9h/9*K19),2),0) | P19: =IF(B19="","",B19-WEEKDAY(B19,2)+1) | Q19: =IF(B19="",0,INDEX(PlanH,WEEKDAY(B19,2))) | R19: =IF(B19="",0,IF(AND(OR(DateDebut="",B19>=DateDebut),OR(DateFin="",B19<=DateFin)),1,0)) | S19: =IF(B19="",0,SUMPRODUCT((PerDu<=B19)*(PerAu>=B19)*PerCode)) | T19: =IF(B19="",0,IF(COUNTIF(FeriesEff,B19)>0,1,0)) | U19: =IF(AND(E19<>"",F19<>""),1,0) | V19: =MAX(0,K19-J19) | W19: =IF(L19>0,1,0) | X19: =IF(Q19>0,1,0) | Y19: =IF(FournitRepas="L'assistante maternelle",IF(G19<>"",G19,IF(K19>0,RepasParJour,0)),0) | Z19: =IF(I19="Congé payé assmat",IF(AND(WEEKDAY(B19,2)<=6,T19=0),1,0),0) | AA19: =IF(I19="Férié travaillé (+10 %)",K19*MajFerie,IF(I19="1er mai travaillé",K19,0)) | AB19: =MAX(R18:R48) | AC19: =IF(B19="",0,IF(B19<AnnivRegul,0,IF(OR(I19="Accueil",I19="Férié travaillé (+10 %)",I19="1er mai travaillé"),MIN(K19,J19),IF(OR(I19="Absence enfant – payée",I19="Férié chômé payé"),Q19,0)))) | AD19: =IF(I19="Maladie enfant – retenue",1,0)
B20: =IF(3<=$AB$3,$AB$2+3-1,"") | C20: =IF(B20="","",CHOOSE(WEEKDAY(B20,2),"lun","mar","mer","jeu","ven","sam","dim")) | I20: =IF(B20="","",IF(R20=0,"Hors contrat",IF(D20<>"",D20,IF(U20=1,IF(T20=1,IF(AND(DAY(B20)=1,MONTH(B20)=5),"1er mai travaillé","Férié travaillé (+10 %)"),"Accueil"),IF(S20=1,IF(OR(WEEKDAY(B20,2)=7,T20=1),IF(AND(T20=1,Q20>0),"Férié chômé payé","Repos"),"Congé payé assmat"),IF(S20=4,IF(Q20>0,"Congé sans solde assmat","Repos"),IF(Q20=0,"Repos",IF(S20=2,"Semaine non programmée",IF(S20=3,"Absence enfant – payée",IF(T20=1,"Férié chômé payé","Accueil")))))))))) | J20: =IF(OR(I20="Accueil",I20="Férié travaillé (+10 %)",I20="1er mai travaillé"),IF(OR(S20=1,S20=2),0,Q20),0) | K20: =IF(OR(I20="Accueil",I20="Férié travaillé (+10 %)",I20="1er mai travaillé"),IF(U20=1,ROUND(MOD(F20-E20,1)*24,2),J20),0) | L20: =IF(OR(I20="Maladie enfant – retenue",I20="Absence assmat – non payée",I20="Congé sans solde assmat",I20="Hors contrat"),Q20,0) | M20: =IF(K20>0,ROUND(MAX(PlancherEnt,Entretien9h/9*K20),2),0) | P20: =IF(B20="","",B20-WEEKDAY(B20,2)+1) | Q20: =IF(B20="",0,INDEX(PlanH,WEEKDAY(B20,2))) | R20: =IF(B20="",0,IF(AND(OR(DateDebut="",B20>=DateDebut),OR(DateFin="",B20<=DateFin)),1,0)) | S20: =IF(B20="",0,SUMPRODUCT((PerDu<=B20)*(PerAu>=B20)*PerCode)) | T20: =IF(B20="",0,IF(COUNTIF(FeriesEff,B20)>0,1,0)) | U20: =IF(AND(E20<>"",F20<>""),1,0) | V20: =MAX(0,K20-J20) | W20: =IF(L20>0,1,0) | X20: =IF(Q20>0,1,0) | Y20: =IF(FournitRepas="L'assistante maternelle",IF(G20<>"",G20,IF(K20>0,RepasParJour,0)),0) | Z20: =IF(I20="Congé payé assmat",IF(AND(WEEKDAY(B20,2)<=6,T20=0),1,0),0) | AA20: =IF(I20="Férié travaillé (+10 %)",K20*MajFerie,IF(I20="1er mai travaillé",K20,0)) | AB20: =MAX(S18:S48) | AC20: =IF(B20="",0,IF(B20<AnnivRegul,0,IF(OR(I20="Accueil",I20="Férié travaillé (+10 %)",I20="1er mai travaillé"),MIN(K20,J20),IF(OR(I20="Absence enfant – payée",I20="Férié chômé payé"),Q20,0)))) | AD20: =IF(I20="Maladie enfant – retenue",1,0)
B21: =IF(4<=$AB$3,$AB$2+4-1,"") | C21: =IF(B21="","",CHOOSE(WEEKDAY(B21,2),"lun","mar","mer","jeu","ven","sam","dim")) | I21: =IF(B21="","",IF(R21=0,"Hors contrat",IF(D21<>"",D21,IF(U21=1,IF(T21=1,IF(AND(DAY(B21)=1,MONTH(B21)=5),"1er mai travaillé","Férié travaillé (+10 %)"),"Accueil"),IF(S21=1,IF(OR(WEEKDAY(B21,2)=7,T21=1),IF(AND(T21=1,Q21>0),"Férié chômé payé","Repos"),"Congé payé assmat"),IF(S21=4,IF(Q21>0,"Congé sans solde assmat","Repos"),IF(Q21=0,"Repos",IF(S21=2,"Semaine non programmée",IF(S21=3,"Absence enfant – payée",IF(T21=1,"Férié chômé payé","Accueil")))))))))) | J21: =IF(OR(I21="Accueil",I21="Férié travaillé (+10 %)",I21="1er mai travaillé"),IF(OR(S21=1,S21=2),0,Q21),0) | K21: =IF(OR(I21="Accueil",I21="Férié travaillé (+10 %)",I21="1er mai travaillé"),IF(U21=1,ROUND(MOD(F21-E21,1)*24,2),J21),0) | L21: =IF(OR(I21="Maladie enfant – retenue",I21="Absence assmat – non payée",I21="Congé sans solde assmat",I21="Hors contrat"),Q21,0) | M21: =IF(K21>0,ROUND(MAX(PlancherEnt,Entretien9h/9*K21),2),0) | P21: =IF(B21="","",B21-WEEKDAY(B21,2)+1) | Q21: =IF(B21="",0,INDEX(PlanH,WEEKDAY(B21,2))) | R21: =IF(B21="",0,IF(AND(OR(DateDebut="",B21>=DateDebut),OR(DateFin="",B21<=DateFin)),1,0)) | S21: =IF(B21="",0,SUMPRODUCT((PerDu<=B21)*(PerAu>=B21)*PerCode)) | T21: =IF(B21="",0,IF(COUNTIF(FeriesEff,B21)>0,1,0)) | U21: =IF(AND(E21<>"",F21<>""),1,0) | V21: =MAX(0,K21-J21) | W21: =IF(L21>0,1,0) | X21: =IF(Q21>0,1,0) | Y21: =IF(FournitRepas="L'assistante maternelle",IF(G21<>"",G21,IF(K21>0,RepasParJour,0)),0) | Z21: =IF(I21="Congé payé assmat",IF(AND(WEEKDAY(B21,2)<=6,T21=0),1,0),0) | AA21: =IF(I21="Férié travaillé (+10 %)",K21*MajFerie,IF(I21="1er mai travaillé",K21,0)) | AC21: =IF(B21="",0,IF(B21<AnnivRegul,0,IF(OR(I21="Accueil",I21="Férié travaillé (+10 %)",I21="1er mai travaillé"),MIN(K21,J21),IF(OR(I21="Absence enfant – payée",I21="Férié chômé payé"),Q21,0)))) | AD21: =IF(I21="Maladie enfant – retenue",1,0)
B22: =IF(5<=$AB$3,$AB$2+5-1,"") | C22: =IF(B22="","",CHOOSE(WEEKDAY(B22,2),"lun","mar","mer","jeu","ven","sam","dim")) | I22: =IF(B22="","",IF(R22=0,"Hors contrat",IF(D22<>"",D22,IF(U22=1,IF(T22=1,IF(AND(DAY(B22)=1,MONTH(B22)=5),"1er mai travaillé","Férié travaillé (+10 %)"),"Accueil"),IF(S22=1,IF(OR(WEEKDAY(B22,2)=7,T22=1),IF(AND(T22=1,Q22>0),"Férié chômé payé","Repos"),"Congé payé assmat"),IF(S22=4,IF(Q22>0,"Congé sans solde assmat","Repos"),IF(Q22=0,"Repos",IF(S22=2,"Semaine non programmée",IF(S22=3,"Absence enfant – payée",IF(T22=1,"Férié chômé payé","Accueil")))))))))) | J22: =IF(OR(I22="Accueil",I22="Férié travaillé (+10 %)",I22="1er mai travaillé"),IF(OR(S22=1,S22=2),0,Q22),0) | K22: =IF(OR(I22="Accueil",I22="Férié travaillé (+10 %)",I22="1er mai travaillé"),IF(U22=1,ROUND(MOD(F22-E22,1)*24,2),J22),0) | L22: =IF(OR(I22="Maladie enfant – retenue",I22="Absence assmat – non payée",I22="Congé sans solde assmat",I22="Hors contrat"),Q22,0) | M22: =IF(K22>0,ROUND(MAX(PlancherEnt,Entretien9h/9*K22),2),0) | P22: =IF(B22="","",B22-WEEKDAY(B22,2)+1) | Q22: =IF(B22="",0,INDEX(PlanH,WEEKDAY(B22,2))) | R22: =IF(B22="",0,IF(AND(OR(DateDebut="",B22>=DateDebut),OR(DateFin="",B22<=DateFin)),1,0)) | S22: =IF(B22="",0,SUMPRODUCT((PerDu<=B22)*(PerAu>=B22)*PerCode)) | T22: =IF(B22="",0,IF(COUNTIF(FeriesEff,B22)>0,1,0)) | U22: =IF(AND(E22<>"",F22<>""),1,0) | V22: =MAX(0,K22-J22) | W22: =IF(L22>0,1,0) | X22: =IF(Q22>0,1,0) | Y22: =IF(FournitRepas="L'assistante maternelle",IF(G22<>"",G22,IF(K22>0,RepasParJour,0)),0) | Z22: =IF(I22="Congé payé assmat",IF(AND(WEEKDAY(B22,2)<=6,T22=0),1,0),0) | AA22: =IF(I22="Férié travaillé (+10 %)",K22*MajFerie,IF(I22="1er mai travaillé",K22,0)) | AC22: =IF(B22="",0,IF(B22<AnnivRegul,0,IF(OR(I22="Accueil",I22="Férié travaillé (+10 %)",I22="1er mai travaillé"),MIN(K22,J22),IF(OR(I22="Absence enfant – payée",I22="Férié chômé payé"),Q22,0)))) | AD22: =IF(I22="Maladie enfant – retenue",1,0)
B23: =IF(6<=$AB$3,$AB$2+6-1,"") | C23: =IF(B23="","",CHOOSE(WEEKDAY(B23,2),"lun","mar","mer","jeu","ven","sam","dim")) | I23: =IF(B23="","",IF(R23=0,"Hors contrat",IF(D23<>"",D23,IF(U23=1,IF(T23=1,IF(AND(DAY(B23)=1,MONTH(B23)=5),"1er mai travaillé","Férié travaillé (+10 %)"),"Accueil"),IF(S23=1,IF(OR(WEEKDAY(B23,2)=7,T23=1),IF(AND(T23=1,Q23>0),"Férié chômé payé","Repos"),"Congé payé assmat"),IF(S23=4,IF(Q23>0,"Congé sans solde assmat","Repos"),IF(Q23=0,"Repos",IF(S23=2,"Semaine non programmée",IF(S23=3,"Absence enfant – payée",IF(T23=1,"Férié chômé payé","Accueil")))))))))) | J23: =IF(OR(I23="Accueil",I23="Férié travaillé (+10 %)",I23="1er mai travaillé"),IF(OR(S23=1,S23=2),0,Q23),0) | K23: =IF(OR(I23="Accueil",I23="Férié travaillé (+10 %)",I23="1er mai travaillé"),IF(U23=1,ROUND(MOD(F23-E23,1)*24,2),J23),0) | L23: =IF(OR(I23="Maladie enfant – retenue",I23="Absence assmat – non payée",I23="Congé sans solde assmat",I23="Hors contrat"),Q23,0) | M23: =IF(K23>0,ROUND(MAX(PlancherEnt,Entretien9h/9*K23),2),0) | P23: =IF(B23="","",B23-WEEKDAY(B23,2)+1) | Q23: =IF(B23="",0,INDEX(PlanH,WEEKDAY(B23,2))) | R23: =IF(B23="",0,IF(AND(OR(DateDebut="",B23>=DateDebut),OR(DateFin="",B23<=DateFin)),1,0)) | S23: =IF(B23="",0,SUMPRODUCT((PerDu<=B23)*(PerAu>=B23)*PerCode)) | T23: =IF(B23="",0,IF(COUNTIF(FeriesEff,B23)>0,1,0)) | U23: =IF(AND(E23<>"",F23<>""),1,0) | V23: =MAX(0,K23-J23) | W23: =IF(L23>0,1,0) | X23: =IF(Q23>0,1,0) | Y23: =IF(FournitRepas="L'assistante maternelle",IF(G23<>"",G23,IF(K23>0,RepasParJour,0)),0) | Z23: =IF(I23="Congé payé assmat",IF(AND(WEEKDAY(B23,2)<=6,T23=0),1,0),0) | AA23: =IF(I23="Férié travaillé (+10 %)",K23*MajFerie,IF(I23="1er mai travaillé",K23,0)) | AC23: =IF(B23="",0,IF(B23<AnnivRegul,0,IF(OR(I23="Accueil",I23="Férié travaillé (+10 %)",I23="1er mai travaillé"),MIN(K23,J23),IF(OR(I23="Absence enfant – payée",I23="Férié chômé payé"),Q23,0)))) | AD23: =IF(I23="Maladie enfant – retenue",1,0)
B24: =IF(7<=$AB$3,$AB$2+7-1,"") | C24: =IF(B24="","",CHOOSE(WEEKDAY(B24,2),"lun","mar","mer","jeu","ven","sam","dim")) | I24: =IF(B24="","",IF(R24=0,"Hors contrat",IF(D24<>"",D24,IF(U24=1,IF(T24=1,IF(AND(DAY(B24)=1,MONTH(B24)=5),"1er mai travaillé","Férié travaillé (+10 %)"),"Accueil"),IF(S24=1,IF(OR(WEEKDAY(B24,2)=7,T24=1),IF(AND(T24=1,Q24>0),"Férié chômé payé","Repos"),"Congé payé assmat"),IF(S24=4,IF(Q24>0,"Congé sans solde assmat","Repos"),IF(Q24=0,"Repos",IF(S24=2,"Semaine non programmée",IF(S24=3,"Absence enfant – payée",IF(T24=1,"Férié chômé payé","Accueil")))))))))) | J24: =IF(OR(I24="Accueil",I24="Férié travaillé (+10 %)",I24="1er mai travaillé"),IF(OR(S24=1,S24=2),0,Q24),0) | K24: =IF(OR(I24="Accueil",I24="Férié travaillé (+10 %)",I24="1er mai travaillé"),IF(U24=1,ROUND(MOD(F24-E24,1)*24,2),J24),0) | L24: =IF(OR(I24="Maladie enfant – retenue",I24="Absence assmat – non payée",I24="Congé sans solde assmat",I24="Hors contrat"),Q24,0) | M24: =IF(K24>0,ROUND(MAX(PlancherEnt,Entretien9h/9*K24),2),0) | P24: =IF(B24="","",B24-WEEKDAY(B24,2)+1) | Q24: =IF(B24="",0,INDEX(PlanH,WEEKDAY(B24,2))) | R24: =IF(B24="",0,IF(AND(OR(DateDebut="",B24>=DateDebut),OR(DateFin="",B24<=DateFin)),1,0)) | S24: =IF(B24="",0,SUMPRODUCT((PerDu<=B24)*(PerAu>=B24)*PerCode)) | T24: =IF(B24="",0,IF(COUNTIF(FeriesEff,B24)>0,1,0)) | U24: =IF(AND(E24<>"",F24<>""),1,0) | V24: =MAX(0,K24-J24) | W24: =IF(L24>0,1,0) | X24: =IF(Q24>0,1,0) | Y24: =IF(FournitRepas="L'assistante maternelle",IF(G24<>"",G24,IF(K24>0,RepasParJour,0)),0) | Z24: =IF(I24="Congé payé assmat",IF(AND(WEEKDAY(B24,2)<=6,T24=0),1,0),0) | AA24: =IF(I24="Férié travaillé (+10 %)",K24*MajFerie,IF(I24="1er mai travaillé",K24,0)) | AC24: =IF(B24="",0,IF(B24<AnnivRegul,0,IF(OR(I24="Accueil",I24="Férié travaillé (+10 %)",I24="1er mai travaillé"),MIN(K24,J24),IF(OR(I24="Absence enfant – payée",I24="Férié chômé payé"),Q24,0)))) | AD24: =IF(I24="Maladie enfant – retenue",1,0)
B25: =IF(8<=$AB$3,$AB$2+8-1,"") | C25: =IF(B25="","",CHOOSE(WEEKDAY(B25,2),"lun","mar","mer","jeu","ven","sam","dim")) | I25: =IF(B25="","",IF(R25=0,"Hors contrat",IF(D25<>"",D25,IF(U25=1,IF(T25=1,IF(AND(DAY(B25)=1,MONTH(B25)=5),"1er mai travaillé","Férié travaillé (+10 %)"),"Accueil"),IF(S25=1,IF(OR(WEEKDAY(B25,2)=7,T25=1),IF(AND(T25=1,Q25>0),"Férié chômé payé","Repos"),"Congé payé assmat"),IF(S25=4,IF(Q25>0,"Congé sans solde assmat","Repos"),IF(Q25=0,"Repos",IF(S25=2,"Semaine non programmée",IF(S25=3,"Absence enfant – payée",IF(T25=1,"Férié chômé payé","Accueil")))))))))) | J25: =IF(OR(I25="Accueil",I25="Férié travaillé (+10 %)",I25="1er mai travaillé"),IF(OR(S25=1,S25=2),0,Q25),0) | K25: =IF(OR(I25="Accueil",I25="Férié travaillé (+10 %)",I25="1er mai travaillé"),IF(U25=1,ROUND(MOD(F25-E25,1)*24,2),J25),0) | L25: =IF(OR(I25="Maladie enfant – retenue",I25="Absence assmat – non payée",I25="Congé sans solde assmat",I25="Hors contrat"),Q25,0) | M25: =IF(K25>0,ROUND(MAX(PlancherEnt,Entretien9h/9*K25),2),0) | P25: =IF(B25="","",B25-WEEKDAY(B25,2)+1) | Q25: =IF(B25="",0,INDEX(PlanH,WEEKDAY(B25,2))) | R25: =IF(B25="",0,IF(AND(OR(DateDebut="",B25>=DateDebut),OR(DateFin="",B25<=DateFin)),1,0)) | S25: =IF(B25="",0,SUMPRODUCT((PerDu<=B25)*(PerAu>=B25)*PerCode)) | T25: =IF(B25="",0,IF(COUNTIF(FeriesEff,B25)>0,1,0)) | U25: =IF(AND(E25<>"",F25<>""),1,0) | V25: =MAX(0,K25-J25) | W25: =IF(L25>0,1,0) | X25: =IF(Q25>0,1,0) | Y25: =IF(FournitRepas="L'assistante maternelle",IF(G25<>"",G25,IF(K25>0,RepasParJour,0)),0) | Z25: =IF(I25="Congé payé assmat",IF(AND(WEEKDAY(B25,2)<=6,T25=0),1,0),0) | AA25: =IF(I25="Férié travaillé (+10 %)",K25*MajFerie,IF(I25="1er mai travaillé",K25,0)) | AC25: =IF(B25="",0,IF(B25<AnnivRegul,0,IF(OR(I25="Accueil",I25="Férié travaillé (+10 %)",I25="1er mai travaillé"),MIN(K25,J25),IF(OR(I25="Absence enfant – payée",I25="Férié chômé payé"),Q25,0)))) | AD25: =IF(I25="Maladie enfant – retenue",1,0)
B26: =IF(9<=$AB$3,$AB$2+9-1,"") | C26: =IF(B26="","",CHOOSE(WEEKDAY(B26,2),"lun","mar","mer","jeu","ven","sam","dim")) | I26: =IF(B26="","",IF(R26=0,"Hors contrat",IF(D26<>"",D26,IF(U26=1,IF(T26=1,IF(AND(DAY(B26)=1,MONTH(B26)=5),"1er mai travaillé","Férié travaillé (+10 %)"),"Accueil"),IF(S26=1,IF(OR(WEEKDAY(B26,2)=7,T26=1),IF(AND(T26=1,Q26>0),"Férié chômé payé","Repos"),"Congé payé assmat"),IF(S26=4,IF(Q26>0,"Congé sans solde assmat","Repos"),IF(Q26=0,"Repos",IF(S26=2,"Semaine non programmée",IF(S26=3,"Absence enfant – payée",IF(T26=1,"Férié chômé payé","Accueil")))))))))) | J26: =IF(OR(I26="Accueil",I26="Férié travaillé (+10 %)",I26="1er mai travaillé"),IF(OR(S26=1,S26=2),0,Q26),0) | K26: =IF(OR(I26="Accueil",I26="Férié travaillé (+10 %)",I26="1er mai travaillé"),IF(U26=1,ROUND(MOD(F26-E26,1)*24,2),J26),0) | L26: =IF(OR(I26="Maladie enfant – retenue",I26="Absence assmat – non payée",I26="Congé sans solde assmat",I26="Hors contrat"),Q26,0) | M26: =IF(K26>0,ROUND(MAX(PlancherEnt,Entretien9h/9*K26),2),0) | P26: =IF(B26="","",B26-WEEKDAY(B26,2)+1) | Q26: =IF(B26="",0,INDEX(PlanH,WEEKDAY(B26,2))) | R26: =IF(B26="",0,IF(AND(OR(DateDebut="",B26>=DateDebut),OR(DateFin="",B26<=DateFin)),1,0)) | S26: =IF(B26="",0,SUMPRODUCT((PerDu<=B26)*(PerAu>=B26)*PerCode)) | T26: =IF(B26="",0,IF(COUNTIF(FeriesEff,B26)>0,1,0)) | U26: =IF(AND(E26<>"",F26<>""),1,0) | V26: =MAX(0,K26-J26) | W26: =IF(L26>0,1,0) | X26: =IF(Q26>0,1,0) | Y26: =IF(FournitRepas="L'assistante maternelle",IF(G26<>"",G26,IF(K26>0,RepasParJour,0)),0) | Z26: =IF(I26="Congé payé assmat",IF(AND(WEEKDAY(B26,2)<=6,T26=0),1,0),0) | AA26: =IF(I26="Férié travaillé (+10 %)",K26*MajFerie,IF(I26="1er mai travaillé",K26,0)) | AC26: =IF(B26="",0,IF(B26<AnnivRegul,0,IF(OR(I26="Accueil",I26="Férié travaillé (+10 %)",I26="1er mai travaillé"),MIN(K26,J26),IF(OR(I26="Absence enfant – payée",I26="Férié chômé payé"),Q26,0)))) | AD26: =IF(I26="Maladie enfant – retenue",1,0)
B27: =IF(10<=$AB$3,$AB$2+10-1,"") | C27: =IF(B27="","",CHOOSE(WEEKDAY(B27,2),"lun","mar","mer","jeu","ven","sam","dim")) | I27: =IF(B27="","",IF(R27=0,"Hors contrat",IF(D27<>"",D27,IF(U27=1,IF(T27=1,IF(AND(DAY(B27)=1,MONTH(B27)=5),"1er mai travaillé","Férié travaillé (+10 %)"),"Accueil"),IF(S27=1,IF(OR(WEEKDAY(B27,2)=7,T27=1),IF(AND(T27=1,Q27>0),"Férié chômé payé","Repos"),"Congé payé assmat"),IF(S27=4,IF(Q27>0,"Congé sans solde assmat","Repos"),IF(Q27=0,"Repos",IF(S27=2,"Semaine non programmée",IF(S27=3,"Absence enfant – payée",IF(T27=1,"Férié chômé payé","Accueil")))))))))) | J27: =IF(OR(I27="Accueil",I27="Férié travaillé (+10 %)",I27="1er mai travaillé"),IF(OR(S27=1,S27=2),0,Q27),0) | K27: =IF(OR(I27="Accueil",I27="Férié travaillé (+10 %)",I27="1er mai travaillé"),IF(U27=1,ROUND(MOD(F27-E27,1)*24,2),J27),0) | L27: =IF(OR(I27="Maladie enfant – retenue",I27="Absence assmat – non payée",I27="Congé sans solde assmat",I27="Hors contrat"),Q27,0) | M27: =IF(K27>0,ROUND(MAX(PlancherEnt,Entretien9h/9*K27),2),0) | P27: =IF(B27="","",B27-WEEKDAY(B27,2)+1) | Q27: =IF(B27="",0,INDEX(PlanH,WEEKDAY(B27,2))) | R27: =IF(B27="",0,IF(AND(OR(DateDebut="",B27>=DateDebut),OR(DateFin="",B27<=DateFin)),1,0)) | S27: =IF(B27="",0,SUMPRODUCT((PerDu<=B27)*(PerAu>=B27)*PerCode)) | T27: =IF(B27="",0,IF(COUNTIF(FeriesEff,B27)>0,1,0)) | U27: =IF(AND(E27<>"",F27<>""),1,0) | V27: =MAX(0,K27-J27) | W27: =IF(L27>0,1,0) | X27: =IF(Q27>0,1,0) | Y27: =IF(FournitRepas="L'assistante maternelle",IF(G27<>"",G27,IF(K27>0,RepasParJour,0)),0) | Z27: =IF(I27="Congé payé assmat",IF(AND(WEEKDAY(B27,2)<=6,T27=0),1,0),0) | AA27: =IF(I27="Férié travaillé (+10 %)",K27*MajFerie,IF(I27="1er mai travaillé",K27,0)) | AC27: =IF(B27="",0,IF(B27<AnnivRegul,0,IF(OR(I27="Accueil",I27="Férié travaillé (+10 %)",I27="1er mai travaillé"),MIN(K27,J27),IF(OR(I27="Absence enfant – payée",I27="Férié chômé payé"),Q27,0)))) | AD27: =IF(I27="Maladie enfant – retenue",1,0)
B28: =IF(11<=$AB$3,$AB$2+11-1,"") | C28: =IF(B28="","",CHOOSE(WEEKDAY(B28,2),"lun","mar","mer","jeu","ven","sam","dim")) | I28: =IF(B28="","",IF(R28=0,"Hors contrat",IF(D28<>"",D28,IF(U28=1,IF(T28=1,IF(AND(DAY(B28)=1,MONTH(B28)=5),"1er mai travaillé","Férié travaillé (+10 %)"),"Accueil"),IF(S28=1,IF(OR(WEEKDAY(B28,2)=7,T28=1),IF(AND(T28=1,Q28>0),"Férié chômé payé","Repos"),"Congé payé assmat"),IF(S28=4,IF(Q28>0,"Congé sans solde assmat","Repos"),IF(Q28=0,"Repos",IF(S28=2,"Semaine non programmée",IF(S28=3,"Absence enfant – payée",IF(T28=1,"Férié chômé payé","Accueil")))))))))) | J28: =IF(OR(I28="Accueil",I28="Férié travaillé (+10 %)",I28="1er mai travaillé"),IF(OR(S28=1,S28=2),0,Q28),0) | K28: =IF(OR(I28="Accueil",I28="Férié travaillé (+10 %)",I28="1er mai travaillé"),IF(U28=1,ROUND(MOD(F28-E28,1)*24,2),J28),0) | L28: =IF(OR(I28="Maladie enfant – retenue",I28="Absence assmat – non payée",I28="Congé sans solde assmat",I28="Hors contrat"),Q28,0) | M28: =IF(K28>0,ROUND(MAX(PlancherEnt,Entretien9h/9*K28),2),0) | P28: =IF(B28="","",B28-WEEKDAY(B28,2)+1) | Q28: =IF(B28="",0,INDEX(PlanH,WEEKDAY(B28,2))) | R28: =IF(B28="",0,IF(AND(OR(DateDebut="",B28>=DateDebut),OR(DateFin="",B28<=DateFin)),1,0)) | S28: =IF(B28="",0,SUMPRODUCT((PerDu<=B28)*(PerAu>=B28)*PerCode)) | T28: =IF(B28="",0,IF(COUNTIF(FeriesEff,B28)>0,1,0)) | U28: =IF(AND(E28<>"",F28<>""),1,0) | V28: =MAX(0,K28-J28) | W28: =IF(L28>0,1,0) | X28: =IF(Q28>0,1,0) | Y28: =IF(FournitRepas="L'assistante maternelle",IF(G28<>"",G28,IF(K28>0,RepasParJour,0)),0) | Z28: =IF(I28="Congé payé assmat",IF(AND(WEEKDAY(B28,2)<=6,T28=0),1,0),0) | AA28: =IF(I28="Férié travaillé (+10 %)",K28*MajFerie,IF(I28="1er mai travaillé",K28,0)) | AC28: =IF(B28="",0,IF(B28<AnnivRegul,0,IF(OR(I28="Accueil",I28="Férié travaillé (+10 %)",I28="1er mai travaillé"),MIN(K28,J28),IF(OR(I28="Absence enfant – payée",I28="Férié chômé payé"),Q28,0)))) | AD28: =IF(I28="Maladie enfant – retenue",1,0)
B29: =IF(12<=$AB$3,$AB$2+12-1,"") | C29: =IF(B29="","",CHOOSE(WEEKDAY(B29,2),"lun","mar","mer","jeu","ven","sam","dim")) | I29: =IF(B29="","",IF(R29=0,"Hors contrat",IF(D29<>"",D29,IF(U29=1,IF(T29=1,IF(AND(DAY(B29)=1,MONTH(B29)=5),"1er mai travaillé","Férié travaillé (+10 %)"),"Accueil"),IF(S29=1,IF(OR(WEEKDAY(B29,2)=7,T29=1),IF(AND(T29=1,Q29>0),"Férié chômé payé","Repos"),"Congé payé assmat"),IF(S29=4,IF(Q29>0,"Congé sans solde assmat","Repos"),IF(Q29=0,"Repos",IF(S29=2,"Semaine non programmée",IF(S29=3,"Absence enfant – payée",IF(T29=1,"Férié chômé payé","Accueil")))))))))) | J29: =IF(OR(I29="Accueil",I29="Férié travaillé (+10 %)",I29="1er mai travaillé"),IF(OR(S29=1,S29=2),0,Q29),0) | K29: =IF(OR(I29="Accueil",I29="Férié travaillé (+10 %)",I29="1er mai travaillé"),IF(U29=1,ROUND(MOD(F29-E29,1)*24,2),J29),0) | L29: =IF(OR(I29="Maladie enfant – retenue",I29="Absence assmat – non payée",I29="Congé sans solde assmat",I29="Hors contrat"),Q29,0) | M29: =IF(K29>0,ROUND(MAX(PlancherEnt,Entretien9h/9*K29),2),0) | P29: =IF(B29="","",B29-WEEKDAY(B29,2)+1) | Q29: =IF(B29="",0,INDEX(PlanH,WEEKDAY(B29,2))) | R29: =IF(B29="",0,IF(AND(OR(DateDebut="",B29>=DateDebut),OR(DateFin="",B29<=DateFin)),1,0)) | S29: =IF(B29="",0,SUMPRODUCT((PerDu<=B29)*(PerAu>=B29)*PerCode)) | T29: =IF(B29="",0,IF(COUNTIF(FeriesEff,B29)>0,1,0)) | U29: =IF(AND(E29<>"",F29<>""),1,0) | V29: =MAX(0,K29-J29) | W29: =IF(L29>0,1,0) | X29: =IF(Q29>0,1,0) | Y29: =IF(FournitRepas="L'assistante maternelle",IF(G29<>"",G29,IF(K29>0,RepasParJour,0)),0) | Z29: =IF(I29="Congé payé assmat",IF(AND(WEEKDAY(B29,2)<=6,T29=0),1,0),0) | AA29: =IF(I29="Férié travaillé (+10 %)",K29*MajFerie,IF(I29="1er mai travaillé",K29,0)) | AC29: =IF(B29="",0,IF(B29<AnnivRegul,0,IF(OR(I29="Accueil",I29="Férié travaillé (+10 %)",I29="1er mai travaillé"),MIN(K29,J29),IF(OR(I29="Absence enfant – payée",I29="Férié chômé payé"),Q29,0)))) | AD29: =IF(I29="Maladie enfant – retenue",1,0)
B30: =IF(13<=$AB$3,$AB$2+13-1,"") | C30: =IF(B30="","",CHOOSE(WEEKDAY(B30,2),"lun","mar","mer","jeu","ven","sam","dim")) | I30: =IF(B30="","",IF(R30=0,"Hors contrat",IF(D30<>"",D30,IF(U30=1,IF(T30=1,IF(AND(DAY(B30)=1,MONTH(B30)=5),"1er mai travaillé","Férié travaillé (+10 %)"),"Accueil"),IF(S30=1,IF(OR(WEEKDAY(B30,2)=7,T30=1),IF(AND(T30=1,Q30>0),"Férié chômé payé","Repos"),"Congé payé assmat"),IF(S30=4,IF(Q30>0,"Congé sans solde assmat","Repos"),IF(Q30=0,"Repos",IF(S30=2,"Semaine non programmée",IF(S30=3,"Absence enfant – payée",IF(T30=1,"Férié chômé payé","Accueil")))))))))) | J30: =IF(OR(I30="Accueil",I30="Férié travaillé (+10 %)",I30="1er mai travaillé"),IF(OR(S30=1,S30=2),0,Q30),0) | K30: =IF(OR(I30="Accueil",I30="Férié travaillé (+10 %)",I30="1er mai travaillé"),IF(U30=1,ROUND(MOD(F30-E30,1)*24,2),J30),0) | L30: =IF(OR(I30="Maladie enfant – retenue",I30="Absence assmat – non payée",I30="Congé sans solde assmat",I30="Hors contrat"),Q30,0) | M30: =IF(K30>0,ROUND(MAX(PlancherEnt,Entretien9h/9*K30),2),0) | P30: =IF(B30="","",B30-WEEKDAY(B30,2)+1) | Q30: =IF(B30="",0,INDEX(PlanH,WEEKDAY(B30,2))) | R30: =IF(B30="",0,IF(AND(OR(DateDebut="",B30>=DateDebut),OR(DateFin="",B30<=DateFin)),1,0)) | S30: =IF(B30="",0,SUMPRODUCT((PerDu<=B30)*(PerAu>=B30)*PerCode)) | T30: =IF(B30="",0,IF(COUNTIF(FeriesEff,B30)>0,1,0)) | U30: =IF(AND(E30<>"",F30<>""),1,0) | V30: =MAX(0,K30-J30) | W30: =IF(L30>0,1,0) | X30: =IF(Q30>0,1,0) | Y30: =IF(FournitRepas="L'assistante maternelle",IF(G30<>"",G30,IF(K30>0,RepasParJour,0)),0) | Z30: =IF(I30="Congé payé assmat",IF(AND(WEEKDAY(B30,2)<=6,T30=0),1,0),0) | AA30: =IF(I30="Férié travaillé (+10 %)",K30*MajFerie,IF(I30="1er mai travaillé",K30,0)) | AC30: =IF(B30="",0,IF(B30<AnnivRegul,0,IF(OR(I30="Accueil",I30="Férié travaillé (+10 %)",I30="1er mai travaillé"),MIN(K30,J30),IF(OR(I30="Absence enfant – payée",I30="Férié chômé payé"),Q30,0)))) | AD30: =IF(I30="Maladie enfant – retenue",1,0)
B31: =IF(14<=$AB$3,$AB$2+14-1,"") | C31: =IF(B31="","",CHOOSE(WEEKDAY(B31,2),"lun","mar","mer","jeu","ven","sam","dim")) | I31: =IF(B31="","",IF(R31=0,"Hors contrat",IF(D31<>"",D31,IF(U31=1,IF(T31=1,IF(AND(DAY(B31)=1,MONTH(B31)=5),"1er mai travaillé","Férié travaillé (+10 %)"),"Accueil"),IF(S31=1,IF(OR(WEEKDAY(B31,2)=7,T31=1),IF(AND(T31=1,Q31>0),"Férié chômé payé","Repos"),"Congé payé assmat"),IF(S31=4,IF(Q31>0,"Congé sans solde assmat","Repos"),IF(Q31=0,"Repos",IF(S31=2,"Semaine non programmée",IF(S31=3,"Absence enfant – payée",IF(T31=1,"Férié chômé payé","Accueil")))))))))) | J31: =IF(OR(I31="Accueil",I31="Férié travaillé (+10 %)",I31="1er mai travaillé"),IF(OR(S31=1,S31=2),0,Q31),0) | K31: =IF(OR(I31="Accueil",I31="Férié travaillé (+10 %)",I31="1er mai travaillé"),IF(U31=1,ROUND(MOD(F31-E31,1)*24,2),J31),0) | L31: =IF(OR(I31="Maladie enfant – retenue",I31="Absence assmat – non payée",I31="Congé sans solde assmat",I31="Hors contrat"),Q31,0) | M31: =IF(K31>0,ROUND(MAX(PlancherEnt,Entretien9h/9*K31),2),0) | P31: =IF(B31="","",B31-WEEKDAY(B31,2)+1) | Q31: =IF(B31="",0,INDEX(PlanH,WEEKDAY(B31,2))) | R31: =IF(B31="",0,IF(AND(OR(DateDebut="",B31>=DateDebut),OR(DateFin="",B31<=DateFin)),1,0)) | S31: =IF(B31="",0,SUMPRODUCT((PerDu<=B31)*(PerAu>=B31)*PerCode)) | T31: =IF(B31="",0,IF(COUNTIF(FeriesEff,B31)>0,1,0)) | U31: =IF(AND(E31<>"",F31<>""),1,0) | V31: =MAX(0,K31-J31) | W31: =IF(L31>0,1,0) | X31: =IF(Q31>0,1,0) | Y31: =IF(FournitRepas="L'assistante maternelle",IF(G31<>"",G31,IF(K31>0,RepasParJour,0)),0) | Z31: =IF(I31="Congé payé assmat",IF(AND(WEEKDAY(B31,2)<=6,T31=0),1,0),0) | AA31: =IF(I31="Férié travaillé (+10 %)",K31*MajFerie,IF(I31="1er mai travaillé",K31,0)) | AC31: =IF(B31="",0,IF(B31<AnnivRegul,0,IF(OR(I31="Accueil",I31="Férié travaillé (+10 %)",I31="1er mai travaillé"),MIN(K31,J31),IF(OR(I31="Absence enfant – payée",I31="Férié chômé payé"),Q31,0)))) | AD31: =IF(I31="Maladie enfant – retenue",1,0)
B32: =IF(15<=$AB$3,$AB$2+15-1,"") | C32: =IF(B32="","",CHOOSE(WEEKDAY(B32,2),"lun","mar","mer","jeu","ven","sam","dim")) | I32: =IF(B32="","",IF(R32=0,"Hors contrat",IF(D32<>"",D32,IF(U32=1,IF(T32=1,IF(AND(DAY(B32)=1,MONTH(B32)=5),"1er mai travaillé","Férié travaillé (+10 %)"),"Accueil"),IF(S32=1,IF(OR(WEEKDAY(B32,2)=7,T32=1),IF(AND(T32=1,Q32>0),"Férié chômé payé","Repos"),"Congé payé assmat"),IF(S32=4,IF(Q32>0,"Congé sans solde assmat","Repos"),IF(Q32=0,"Repos",IF(S32=2,"Semaine non programmée",IF(S32=3,"Absence enfant – payée",IF(T32=1,"Férié chômé payé","Accueil")))))))))) | J32: =IF(OR(I32="Accueil",I32="Férié travaillé (+10 %)",I32="1er mai travaillé"),IF(OR(S32=1,S32=2),0,Q32),0) | K32: =IF(OR(I32="Accueil",I32="Férié travaillé (+10 %)",I32="1er mai travaillé"),IF(U32=1,ROUND(MOD(F32-E32,1)*24,2),J32),0) | L32: =IF(OR(I32="Maladie enfant – retenue",I32="Absence assmat – non payée",I32="Congé sans solde assmat",I32="Hors contrat"),Q32,0) | M32: =IF(K32>0,ROUND(MAX(PlancherEnt,Entretien9h/9*K32),2),0) | P32: =IF(B32="","",B32-WEEKDAY(B32,2)+1) | Q32: =IF(B32="",0,INDEX(PlanH,WEEKDAY(B32,2))) | R32: =IF(B32="",0,IF(AND(OR(DateDebut="",B32>=DateDebut),OR(DateFin="",B32<=DateFin)),1,0)) | S32: =IF(B32="",0,SUMPRODUCT((PerDu<=B32)*(PerAu>=B32)*PerCode)) | T32: =IF(B32="",0,IF(COUNTIF(FeriesEff,B32)>0,1,0)) | U32: =IF(AND(E32<>"",F32<>""),1,0) | V32: =MAX(0,K32-J32) | W32: =IF(L32>0,1,0) | X32: =IF(Q32>0,1,0) | Y32: =IF(FournitRepas="L'assistante maternelle",IF(G32<>"",G32,IF(K32>0,RepasParJour,0)),0) | Z32: =IF(I32="Congé payé assmat",IF(AND(WEEKDAY(B32,2)<=6,T32=0),1,0),0) | AA32: =IF(I32="Férié travaillé (+10 %)",K32*MajFerie,IF(I32="1er mai travaillé",K32,0)) | AC32: =IF(B32="",0,IF(B32<AnnivRegul,0,IF(OR(I32="Accueil",I32="Férié travaillé (+10 %)",I32="1er mai travaillé"),MIN(K32,J32),IF(OR(I32="Absence enfant – payée",I32="Férié chômé payé"),Q32,0)))) | AD32: =IF(I32="Maladie enfant – retenue",1,0)
B33: =IF(16<=$AB$3,$AB$2+16-1,"") | C33: =IF(B33="","",CHOOSE(WEEKDAY(B33,2),"lun","mar","mer","jeu","ven","sam","dim")) | I33: =IF(B33="","",IF(R33=0,"Hors contrat",IF(D33<>"",D33,IF(U33=1,IF(T33=1,IF(AND(DAY(B33)=1,MONTH(B33)=5),"1er mai travaillé","Férié travaillé (+10 %)"),"Accueil"),IF(S33=1,IF(OR(WEEKDAY(B33,2)=7,T33=1),IF(AND(T33=1,Q33>0),"Férié chômé payé","Repos"),"Congé payé assmat"),IF(S33=4,IF(Q33>0,"Congé sans solde assmat","Repos"),IF(Q33=0,"Repos",IF(S33=2,"Semaine non programmée",IF(S33=3,"Absence enfant – payée",IF(T33=1,"Férié chômé payé","Accueil")))))))))) | J33: =IF(OR(I33="Accueil",I33="Férié travaillé (+10 %)",I33="1er mai travaillé"),IF(OR(S33=1,S33=2),0,Q33),0) | K33: =IF(OR(I33="Accueil",I33="Férié travaillé (+10 %)",I33="1er mai travaillé"),IF(U33=1,ROUND(MOD(F33-E33,1)*24,2),J33),0) | L33: =IF(OR(I33="Maladie enfant – retenue",I33="Absence assmat – non payée",I33="Congé sans solde assmat",I33="Hors contrat"),Q33,0) | M33: =IF(K33>0,ROUND(MAX(PlancherEnt,Entretien9h/9*K33),2),0) | P33: =IF(B33="","",B33-WEEKDAY(B33,2)+1) | Q33: =IF(B33="",0,INDEX(PlanH,WEEKDAY(B33,2))) | R33: =IF(B33="",0,IF(AND(OR(DateDebut="",B33>=DateDebut),OR(DateFin="",B33<=DateFin)),1,0)) | S33: =IF(B33="",0,SUMPRODUCT((PerDu<=B33)*(PerAu>=B33)*PerCode)) | T33: =IF(B33="",0,IF(COUNTIF(FeriesEff,B33)>0,1,0)) | U33: =IF(AND(E33<>"",F33<>""),1,0) | V33: =MAX(0,K33-J33) | W33: =IF(L33>0,1,0) | X33: =IF(Q33>0,1,0) | Y33: =IF(FournitRepas="L'assistante maternelle",IF(G33<>"",G33,IF(K33>0,RepasParJour,0)),0) | Z33: =IF(I33="Congé payé assmat",IF(AND(WEEKDAY(B33,2)<=6,T33=0),1,0),0) | AA33: =IF(I33="Férié travaillé (+10 %)",K33*MajFerie,IF(I33="1er mai travaillé",K33,0)) | AC33: =IF(B33="",0,IF(B33<AnnivRegul,0,IF(OR(I33="Accueil",I33="Férié travaillé (+10 %)",I33="1er mai travaillé"),MIN(K33,J33),IF(OR(I33="Absence enfant – payée",I33="Férié chômé payé"),Q33,0)))) | AD33: =IF(I33="Maladie enfant – retenue",1,0)
B34: =IF(17<=$AB$3,$AB$2+17-1,"") | C34: =IF(B34="","",CHOOSE(WEEKDAY(B34,2),"lun","mar","mer","jeu","ven","sam","dim")) | I34: =IF(B34="","",IF(R34=0,"Hors contrat",IF(D34<>"",D34,IF(U34=1,IF(T34=1,IF(AND(DAY(B34)=1,MONTH(B34)=5),"1er mai travaillé","Férié travaillé (+10 %)"),"Accueil"),IF(S34=1,IF(OR(WEEKDAY(B34,2)=7,T34=1),IF(AND(T34=1,Q34>0),"Férié chômé payé","Repos"),"Congé payé assmat"),IF(S34=4,IF(Q34>0,"Congé sans solde assmat","Repos"),IF(Q34=0,"Repos",IF(S34=2,"Semaine non programmée",IF(S34=3,"Absence enfant – payée",IF(T34=1,"Férié chômé payé","Accueil")))))))))) | J34: =IF(OR(I34="Accueil",I34="Férié travaillé (+10 %)",I34="1er mai travaillé"),IF(OR(S34=1,S34=2),0,Q34),0) | K34: =IF(OR(I34="Accueil",I34="Férié travaillé (+10 %)",I34="1er mai travaillé"),IF(U34=1,ROUND(MOD(F34-E34,1)*24,2),J34),0) | L34: =IF(OR(I34="Maladie enfant – retenue",I34="Absence assmat – non payée",I34="Congé sans solde assmat",I34="Hors contrat"),Q34,0) | M34: =IF(K34>0,ROUND(MAX(PlancherEnt,Entretien9h/9*K34),2),0) | P34: =IF(B34="","",B34-WEEKDAY(B34,2)+1) | Q34: =IF(B34="",0,INDEX(PlanH,WEEKDAY(B34,2))) | R34: =IF(B34="",0,IF(AND(OR(DateDebut="",B34>=DateDebut),OR(DateFin="",B34<=DateFin)),1,0)) | S34: =IF(B34="",0,SUMPRODUCT((PerDu<=B34)*(PerAu>=B34)*PerCode)) | T34: =IF(B34="",0,IF(COUNTIF(FeriesEff,B34)>0,1,0)) | U34: =IF(AND(E34<>"",F34<>""),1,0) | V34: =MAX(0,K34-J34) | W34: =IF(L34>0,1,0) | X34: =IF(Q34>0,1,0) | Y34: =IF(FournitRepas="L'assistante maternelle",IF(G34<>"",G34,IF(K34>0,RepasParJour,0)),0) | Z34: =IF(I34="Congé payé assmat",IF(AND(WEEKDAY(B34,2)<=6,T34=0),1,0),0) | AA34: =IF(I34="Férié travaillé (+10 %)",K34*MajFerie,IF(I34="1er mai travaillé",K34,0)) | AC34: =IF(B34="",0,IF(B34<AnnivRegul,0,IF(OR(I34="Accueil",I34="Férié travaillé (+10 %)",I34="1er mai travaillé"),MIN(K34,J34),IF(OR(I34="Absence enfant – payée",I34="Férié chômé payé"),Q34,0)))) | AD34: =IF(I34="Maladie enfant – retenue",1,0)
B35: =IF(18<=$AB$3,$AB$2+18-1,"") | C35: =IF(B35="","",CHOOSE(WEEKDAY(B35,2),"lun","mar","mer","jeu","ven","sam","dim")) | I35: =IF(B35="","",IF(R35=0,"Hors contrat",IF(D35<>"",D35,IF(U35=1,IF(T35=1,IF(AND(DAY(B35)=1,MONTH(B35)=5),"1er mai travaillé","Férié travaillé (+10 %)"),"Accueil"),IF(S35=1,IF(OR(WEEKDAY(B35,2)=7,T35=1),IF(AND(T35=1,Q35>0),"Férié chômé payé","Repos"),"Congé payé assmat"),IF(S35=4,IF(Q35>0,"Congé sans solde assmat","Repos"),IF(Q35=0,"Repos",IF(S35=2,"Semaine non programmée",IF(S35=3,"Absence enfant – payée",IF(T35=1,"Férié chômé payé","Accueil")))))))))) | J35: =IF(OR(I35="Accueil",I35="Férié travaillé (+10 %)",I35="1er mai travaillé"),IF(OR(S35=1,S35=2),0,Q35),0) | K35: =IF(OR(I35="Accueil",I35="Férié travaillé (+10 %)",I35="1er mai travaillé"),IF(U35=1,ROUND(MOD(F35-E35,1)*24,2),J35),0) | L35: =IF(OR(I35="Maladie enfant – retenue",I35="Absence assmat – non payée",I35="Congé sans solde assmat",I35="Hors contrat"),Q35,0) | M35: =IF(K35>0,ROUND(MAX(PlancherEnt,Entretien9h/9*K35),2),0) | P35: =IF(B35="","",B35-WEEKDAY(B35,2)+1) | Q35: =IF(B35="",0,INDEX(PlanH,WEEKDAY(B35,2))) | R35: =IF(B35="",0,IF(AND(OR(DateDebut="",B35>=DateDebut),OR(DateFin="",B35<=DateFin)),1,0)) | S35: =IF(B35="",0,SUMPRODUCT((PerDu<=B35)*(PerAu>=B35)*PerCode)) | T35: =IF(B35="",0,IF(COUNTIF(FeriesEff,B35)>0,1,0)) | U35: =IF(AND(E35<>"",F35<>""),1,0) | V35: =MAX(0,K35-J35) | W35: =IF(L35>0,1,0) | X35: =IF(Q35>0,1,0) | Y35: =IF(FournitRepas="L'assistante maternelle",IF(G35<>"",G35,IF(K35>0,RepasParJour,0)),0) | Z35: =IF(I35="Congé payé assmat",IF(AND(WEEKDAY(B35,2)<=6,T35=0),1,0),0) | AA35: =IF(I35="Férié travaillé (+10 %)",K35*MajFerie,IF(I35="1er mai travaillé",K35,0)) | AC35: =IF(B35="",0,IF(B35<AnnivRegul,0,IF(OR(I35="Accueil",I35="Férié travaillé (+10 %)",I35="1er mai travaillé"),MIN(K35,J35),IF(OR(I35="Absence enfant – payée",I35="Férié chômé payé"),Q35,0)))) | AD35: =IF(I35="Maladie enfant – retenue",1,0)
B36: =IF(19<=$AB$3,$AB$2+19-1,"") | C36: =IF(B36="","",CHOOSE(WEEKDAY(B36,2),"lun","mar","mer","jeu","ven","sam","dim")) | I36: =IF(B36="","",IF(R36=0,"Hors contrat",IF(D36<>"",D36,IF(U36=1,IF(T36=1,IF(AND(DAY(B36)=1,MONTH(B36)=5),"1er mai travaillé","Férié travaillé (+10 %)"),"Accueil"),IF(S36=1,IF(OR(WEEKDAY(B36,2)=7,T36=1),IF(AND(T36=1,Q36>0),"Férié chômé payé","Repos"),"Congé payé assmat"),IF(S36=4,IF(Q36>0,"Congé sans solde assmat","Repos"),IF(Q36=0,"Repos",IF(S36=2,"Semaine non programmée",IF(S36=3,"Absence enfant – payée",IF(T36=1,"Férié chômé payé","Accueil")))))))))) | J36: =IF(OR(I36="Accueil",I36="Férié travaillé (+10 %)",I36="1er mai travaillé"),IF(OR(S36=1,S36=2),0,Q36),0) | K36: =IF(OR(I36="Accueil",I36="Férié travaillé (+10 %)",I36="1er mai travaillé"),IF(U36=1,ROUND(MOD(F36-E36,1)*24,2),J36),0) | L36: =IF(OR(I36="Maladie enfant – retenue",I36="Absence assmat – non payée",I36="Congé sans solde assmat",I36="Hors contrat"),Q36,0) | M36: =IF(K36>0,ROUND(MAX(PlancherEnt,Entretien9h/9*K36),2),0) | P36: =IF(B36="","",B36-WEEKDAY(B36,2)+1) | Q36: =IF(B36="",0,INDEX(PlanH,WEEKDAY(B36,2))) | R36: =IF(B36="",0,IF(AND(OR(DateDebut="",B36>=DateDebut),OR(DateFin="",B36<=DateFin)),1,0)) | S36: =IF(B36="",0,SUMPRODUCT((PerDu<=B36)*(PerAu>=B36)*PerCode)) | T36: =IF(B36="",0,IF(COUNTIF(FeriesEff,B36)>0,1,0)) | U36: =IF(AND(E36<>"",F36<>""),1,0) | V36: =MAX(0,K36-J36) | W36: =IF(L36>0,1,0) | X36: =IF(Q36>0,1,0) | Y36: =IF(FournitRepas="L'assistante maternelle",IF(G36<>"",G36,IF(K36>0,RepasParJour,0)),0) | Z36: =IF(I36="Congé payé assmat",IF(AND(WEEKDAY(B36,2)<=6,T36=0),1,0),0) | AA36: =IF(I36="Férié travaillé (+10 %)",K36*MajFerie,IF(I36="1er mai travaillé",K36,0)) | AC36: =IF(B36="",0,IF(B36<AnnivRegul,0,IF(OR(I36="Accueil",I36="Férié travaillé (+10 %)",I36="1er mai travaillé"),MIN(K36,J36),IF(OR(I36="Absence enfant – payée",I36="Férié chômé payé"),Q36,0)))) | AD36: =IF(I36="Maladie enfant – retenue",1,0)
B37: =IF(20<=$AB$3,$AB$2+20-1,"") | C37: =IF(B37="","",CHOOSE(WEEKDAY(B37,2),"lun","mar","mer","jeu","ven","sam","dim")) | I37: =IF(B37="","",IF(R37=0,"Hors contrat",IF(D37<>"",D37,IF(U37=1,IF(T37=1,IF(AND(DAY(B37)=1,MONTH(B37)=5),"1er mai travaillé","Férié travaillé (+10 %)"),"Accueil"),IF(S37=1,IF(OR(WEEKDAY(B37,2)=7,T37=1),IF(AND(T37=1,Q37>0),"Férié chômé payé","Repos"),"Congé payé assmat"),IF(S37=4,IF(Q37>0,"Congé sans solde assmat","Repos"),IF(Q37=0,"Repos",IF(S37=2,"Semaine non programmée",IF(S37=3,"Absence enfant – payée",IF(T37=1,"Férié chômé payé","Accueil")))))))))) | J37: =IF(OR(I37="Accueil",I37="Férié travaillé (+10 %)",I37="1er mai travaillé"),IF(OR(S37=1,S37=2),0,Q37),0) | K37: =IF(OR(I37="Accueil",I37="Férié travaillé (+10 %)",I37="1er mai travaillé"),IF(U37=1,ROUND(MOD(F37-E37,1)*24,2),J37),0) | L37: =IF(OR(I37="Maladie enfant – retenue",I37="Absence assmat – non payée",I37="Congé sans solde assmat",I37="Hors contrat"),Q37,0) | M37: =IF(K37>0,ROUND(MAX(PlancherEnt,Entretien9h/9*K37),2),0) | P37: =IF(B37="","",B37-WEEKDAY(B37,2)+1) | Q37: =IF(B37="",0,INDEX(PlanH,WEEKDAY(B37,2))) | R37: =IF(B37="",0,IF(AND(OR(DateDebut="",B37>=DateDebut),OR(DateFin="",B37<=DateFin)),1,0)) | S37: =IF(B37="",0,SUMPRODUCT((PerDu<=B37)*(PerAu>=B37)*PerCode)) | T37: =IF(B37="",0,IF(COUNTIF(FeriesEff,B37)>0,1,0)) | U37: =IF(AND(E37<>"",F37<>""),1,0) | V37: =MAX(0,K37-J37) | W37: =IF(L37>0,1,0) | X37: =IF(Q37>0,1,0) | Y37: =IF(FournitRepas="L'assistante maternelle",IF(G37<>"",G37,IF(K37>0,RepasParJour,0)),0) | Z37: =IF(I37="Congé payé assmat",IF(AND(WEEKDAY(B37,2)<=6,T37=0),1,0),0) | AA37: =IF(I37="Férié travaillé (+10 %)",K37*MajFerie,IF(I37="1er mai travaillé",K37,0)) | AC37: =IF(B37="",0,IF(B37<AnnivRegul,0,IF(OR(I37="Accueil",I37="Férié travaillé (+10 %)",I37="1er mai travaillé"),MIN(K37,J37),IF(OR(I37="Absence enfant – payée",I37="Férié chômé payé"),Q37,0)))) | AD37: =IF(I37="Maladie enfant – retenue",1,0)
B38: =IF(21<=$AB$3,$AB$2+21-1,"") | C38: =IF(B38="","",CHOOSE(WEEKDAY(B38,2),"lun","mar","mer","jeu","ven","sam","dim")) | I38: =IF(B38="","",IF(R38=0,"Hors contrat",IF(D38<>"",D38,IF(U38=1,IF(T38=1,IF(AND(DAY(B38)=1,MONTH(B38)=5),"1er mai travaillé","Férié travaillé (+10 %)"),"Accueil"),IF(S38=1,IF(OR(WEEKDAY(B38,2)=7,T38=1),IF(AND(T38=1,Q38>0),"Férié chômé payé","Repos"),"Congé payé assmat"),IF(S38=4,IF(Q38>0,"Congé sans solde assmat","Repos"),IF(Q38=0,"Repos",IF(S38=2,"Semaine non programmée",IF(S38=3,"Absence enfant – payée",IF(T38=1,"Férié chômé payé","Accueil")))))))))) | J38: =IF(OR(I38="Accueil",I38="Férié travaillé (+10 %)",I38="1er mai travaillé"),IF(OR(S38=1,S38=2),0,Q38),0) | K38: =IF(OR(I38="Accueil",I38="Férié travaillé (+10 %)",I38="1er mai travaillé"),IF(U38=1,ROUND(MOD(F38-E38,1)*24,2),J38),0) | L38: =IF(OR(I38="Maladie enfant – retenue",I38="Absence assmat – non payée",I38="Congé sans solde assmat",I38="Hors contrat"),Q38,0) | M38: =IF(K38>0,ROUND(MAX(PlancherEnt,Entretien9h/9*K38),2),0) | P38: =IF(B38="","",B38-WEEKDAY(B38,2)+1) | Q38: =IF(B38="",0,INDEX(PlanH,WEEKDAY(B38,2))) | R38: =IF(B38="",0,IF(AND(OR(DateDebut="",B38>=DateDebut),OR(DateFin="",B38<=DateFin)),1,0)) | S38: =IF(B38="",0,SUMPRODUCT((PerDu<=B38)*(PerAu>=B38)*PerCode)) | T38: =IF(B38="",0,IF(COUNTIF(FeriesEff,B38)>0,1,0)) | U38: =IF(AND(E38<>"",F38<>""),1,0) | V38: =MAX(0,K38-J38) | W38: =IF(L38>0,1,0) | X38: =IF(Q38>0,1,0) | Y38: =IF(FournitRepas="L'assistante maternelle",IF(G38<>"",G38,IF(K38>0,RepasParJour,0)),0) | Z38: =IF(I38="Congé payé assmat",IF(AND(WEEKDAY(B38,2)<=6,T38=0),1,0),0) | AA38: =IF(I38="Férié travaillé (+10 %)",K38*MajFerie,IF(I38="1er mai travaillé",K38,0)) | AC38: =IF(B38="",0,IF(B38<AnnivRegul,0,IF(OR(I38="Accueil",I38="Férié travaillé (+10 %)",I38="1er mai travaillé"),MIN(K38,J38),IF(OR(I38="Absence enfant – payée",I38="Férié chômé payé"),Q38,0)))) | AD38: =IF(I38="Maladie enfant – retenue",1,0)
B39: =IF(22<=$AB$3,$AB$2+22-1,"") | C39: =IF(B39="","",CHOOSE(WEEKDAY(B39,2),"lun","mar","mer","jeu","ven","sam","dim")) | I39: =IF(B39="","",IF(R39=0,"Hors contrat",IF(D39<>"",D39,IF(U39=1,IF(T39=1,IF(AND(DAY(B39)=1,MONTH(B39)=5),"1er mai travaillé","Férié travaillé (+10 %)"),"Accueil"),IF(S39=1,IF(OR(WEEKDAY(B39,2)=7,T39=1),IF(AND(T39=1,Q39>0),"Férié chômé payé","Repos"),"Congé payé assmat"),IF(S39=4,IF(Q39>0,"Congé sans solde assmat","Repos"),IF(Q39=0,"Repos",IF(S39=2,"Semaine non programmée",IF(S39=3,"Absence enfant – payée",IF(T39=1,"Férié chômé payé","Accueil")))))))))) | J39: =IF(OR(I39="Accueil",I39="Férié travaillé (+10 %)",I39="1er mai travaillé"),IF(OR(S39=1,S39=2),0,Q39),0) | K39: =IF(OR(I39="Accueil",I39="Férié travaillé (+10 %)",I39="1er mai travaillé"),IF(U39=1,ROUND(MOD(F39-E39,1)*24,2),J39),0) | L39: =IF(OR(I39="Maladie enfant – retenue",I39="Absence assmat – non payée",I39="Congé sans solde assmat",I39="Hors contrat"),Q39,0) | M39: =IF(K39>0,ROUND(MAX(PlancherEnt,Entretien9h/9*K39),2),0) | P39: =IF(B39="","",B39-WEEKDAY(B39,2)+1) | Q39: =IF(B39="",0,INDEX(PlanH,WEEKDAY(B39,2))) | R39: =IF(B39="",0,IF(AND(OR(DateDebut="",B39>=DateDebut),OR(DateFin="",B39<=DateFin)),1,0)) | S39: =IF(B39="",0,SUMPRODUCT((PerDu<=B39)*(PerAu>=B39)*PerCode)) | T39: =IF(B39="",0,IF(COUNTIF(FeriesEff,B39)>0,1,0)) | U39: =IF(AND(E39<>"",F39<>""),1,0) | V39: =MAX(0,K39-J39) | W39: =IF(L39>0,1,0) | X39: =IF(Q39>0,1,0) | Y39: =IF(FournitRepas="L'assistante maternelle",IF(G39<>"",G39,IF(K39>0,RepasParJour,0)),0) | Z39: =IF(I39="Congé payé assmat",IF(AND(WEEKDAY(B39,2)<=6,T39=0),1,0),0) | AA39: =IF(I39="Férié travaillé (+10 %)",K39*MajFerie,IF(I39="1er mai travaillé",K39,0)) | AC39: =IF(B39="",0,IF(B39<AnnivRegul,0,IF(OR(I39="Accueil",I39="Férié travaillé (+10 %)",I39="1er mai travaillé"),MIN(K39,J39),IF(OR(I39="Absence enfant – payée",I39="Férié chômé payé"),Q39,0)))) | AD39: =IF(I39="Maladie enfant – retenue",1,0)
B40: =IF(23<=$AB$3,$AB$2+23-1,"") | C40: =IF(B40="","",CHOOSE(WEEKDAY(B40,2),"lun","mar","mer","jeu","ven","sam","dim")) | I40: =IF(B40="","",IF(R40=0,"Hors contrat",IF(D40<>"",D40,IF(U40=1,IF(T40=1,IF(AND(DAY(B40)=1,MONTH(B40)=5),"1er mai travaillé","Férié travaillé (+10 %)"),"Accueil"),IF(S40=1,IF(OR(WEEKDAY(B40,2)=7,T40=1),IF(AND(T40=1,Q40>0),"Férié chômé payé","Repos"),"Congé payé assmat"),IF(S40=4,IF(Q40>0,"Congé sans solde assmat","Repos"),IF(Q40=0,"Repos",IF(S40=2,"Semaine non programmée",IF(S40=3,"Absence enfant – payée",IF(T40=1,"Férié chômé payé","Accueil")))))))))) | J40: =IF(OR(I40="Accueil",I40="Férié travaillé (+10 %)",I40="1er mai travaillé"),IF(OR(S40=1,S40=2),0,Q40),0) | K40: =IF(OR(I40="Accueil",I40="Férié travaillé (+10 %)",I40="1er mai travaillé"),IF(U40=1,ROUND(MOD(F40-E40,1)*24,2),J40),0) | L40: =IF(OR(I40="Maladie enfant – retenue",I40="Absence assmat – non payée",I40="Congé sans solde assmat",I40="Hors contrat"),Q40,0) | M40: =IF(K40>0,ROUND(MAX(PlancherEnt,Entretien9h/9*K40),2),0) | P40: =IF(B40="","",B40-WEEKDAY(B40,2)+1) | Q40: =IF(B40="",0,INDEX(PlanH,WEEKDAY(B40,2))) | R40: =IF(B40="",0,IF(AND(OR(DateDebut="",B40>=DateDebut),OR(DateFin="",B40<=DateFin)),1,0)) | S40: =IF(B40="",0,SUMPRODUCT((PerDu<=B40)*(PerAu>=B40)*PerCode)) | T40: =IF(B40="",0,IF(COUNTIF(FeriesEff,B40)>0,1,0)) | U40: =IF(AND(E40<>"",F40<>""),1,0) | V40: =MAX(0,K40-J40) | W40: =IF(L40>0,1,0) | X40: =IF(Q40>0,1,0) | Y40: =IF(FournitRepas="L'assistante maternelle",IF(G40<>"",G40,IF(K40>0,RepasParJour,0)),0) | Z40: =IF(I40="Congé payé assmat",IF(AND(WEEKDAY(B40,2)<=6,T40=0),1,0),0) | AA40: =IF(I40="Férié travaillé (+10 %)",K40*MajFerie,IF(I40="1er mai travaillé",K40,0)) | AC40: =IF(B40="",0,IF(B40<AnnivRegul,0,IF(OR(I40="Accueil",I40="Férié travaillé (+10 %)",I40="1er mai travaillé"),MIN(K40,J40),IF(OR(I40="Absence enfant – payée",I40="Férié chômé payé"),Q40,0)))) | AD40: =IF(I40="Maladie enfant – retenue",1,0)
B41: =IF(24<=$AB$3,$AB$2+24-1,"") | C41: =IF(B41="","",CHOOSE(WEEKDAY(B41,2),"lun","mar","mer","jeu","ven","sam","dim")) | I41: =IF(B41="","",IF(R41=0,"Hors contrat",IF(D41<>"",D41,IF(U41=1,IF(T41=1,IF(AND(DAY(B41)=1,MONTH(B41)=5),"1er mai travaillé","Férié travaillé (+10 %)"),"Accueil"),IF(S41=1,IF(OR(WEEKDAY(B41,2)=7,T41=1),IF(AND(T41=1,Q41>0),"Férié chômé payé","Repos"),"Congé payé assmat"),IF(S41=4,IF(Q41>0,"Congé sans solde assmat","Repos"),IF(Q41=0,"Repos",IF(S41=2,"Semaine non programmée",IF(S41=3,"Absence enfant – payée",IF(T41=1,"Férié chômé payé","Accueil")))))))))) | J41: =IF(OR(I41="Accueil",I41="Férié travaillé (+10 %)",I41="1er mai travaillé"),IF(OR(S41=1,S41=2),0,Q41),0) | K41: =IF(OR(I41="Accueil",I41="Férié travaillé (+10 %)",I41="1er mai travaillé"),IF(U41=1,ROUND(MOD(F41-E41,1)*24,2),J41),0) | L41: =IF(OR(I41="Maladie enfant – retenue",I41="Absence assmat – non payée",I41="Congé sans solde assmat",I41="Hors contrat"),Q41,0) | M41: =IF(K41>0,ROUND(MAX(PlancherEnt,Entretien9h/9*K41),2),0) | P41: =IF(B41="","",B41-WEEKDAY(B41,2)+1) | Q41: =IF(B41="",0,INDEX(PlanH,WEEKDAY(B41,2))) | R41: =IF(B41="",0,IF(AND(OR(DateDebut="",B41>=DateDebut),OR(DateFin="",B41<=DateFin)),1,0)) | S41: =IF(B41="",0,SUMPRODUCT((PerDu<=B41)*(PerAu>=B41)*PerCode)) | T41: =IF(B41="",0,IF(COUNTIF(FeriesEff,B41)>0,1,0)) | U41: =IF(AND(E41<>"",F41<>""),1,0) | V41: =MAX(0,K41-J41) | W41: =IF(L41>0,1,0) | X41: =IF(Q41>0,1,0) | Y41: =IF(FournitRepas="L'assistante maternelle",IF(G41<>"",G41,IF(K41>0,RepasParJour,0)),0) | Z41: =IF(I41="Congé payé assmat",IF(AND(WEEKDAY(B41,2)<=6,T41=0),1,0),0) | AA41: =IF(I41="Férié travaillé (+10 %)",K41*MajFerie,IF(I41="1er mai travaillé",K41,0)) | AC41: =IF(B41="",0,IF(B41<AnnivRegul,0,IF(OR(I41="Accueil",I41="Férié travaillé (+10 %)",I41="1er mai travaillé"),MIN(K41,J41),IF(OR(I41="Absence enfant – payée",I41="Férié chômé payé"),Q41,0)))) | AD41: =IF(I41="Maladie enfant – retenue",1,0)
